Workbook
Name _: #REF!
Name _: #REF!
Name _: #REF!
Name _: #REF!
Name _: #REF!
Name _?: #REF!
Name _?: #REF!
Name _?: #REF!
Name _?: #REF!
Name _?: #REF!
Name _??????: #REF!
Name _??????: #REF!
Name _??????: #REF!
Name _??????: #REF!
Name _??????: #REF!
Name _2_?: #REF!
Name _2_?: #REF!
Name _2_?: #REF!
Name _2_?: #REF!
Name _2_?: #REF!
Name _3_?: #REF!
Name _3_?: #REF!
Name _3_?: #REF!
Name _3_?: #REF!
Name _3_?: #REF!
Name _4_??????: #REF!
Name _4_??????: #REF!
Name _4_??????: #REF!
Name _4_??????: #REF!
Name _4_??????: #REF!
Name _6_??????: #REF!
Name _6_??????: #REF!
Name _6_??????: #REF!
Name _6_??????: #REF!
Name _6_??????: #REF!
Name _8_8: EVALUATE+#REF!
Name _8_8: EVALUATE+#REF!
Name _8_8: EVALUATE+#REF!
Name _8_8: EVALUATE+#REF!
Name _8_8: EVALUATE+#REF!
Name _8_9: EVALUATE+#REF!
Name _8_9: EVALUATE+#REF!
Name _8_9: EVALUATE+#REF!
Name _8_9: EVALUATE+#REF!
Name _8_9: EVALUATE+#REF!
Name _999年12月31日股份应收帐款.dbf: #REF!
Name _999年12月31日股份应收帐款.dbf: #REF!
Name _999年12月31日股份应收帐款.dbf: #REF!
Name _999年12月31日股份应收帐款.dbf: #REF!
Name _999年12月31日股份应收帐款.dbf: #REF!
Name _aaa1: #REF!
Name _aaa1: #REF!
Name _aaa1: #REF!
Name _aaa1: #REF!
Name _aaa1: #REF!
Name _aaa2: #REF!
Name _aaa2: #REF!
Name _aaa2: #REF!
Name _aaa2: #REF!
Name _aaa2: #REF!

Sheet 目录
A1: 长沙五江项目-测算分析
A2: 编号 | B2: 名称
A3: 0 | B3: 基本假设与结果输出
A4: 1 | B4: 项目总投资估算表（汇总）
A5: 1.1 | B5: 项目总投资估算表（明细）
A6: 2 | B6: 投资计划与资金筹措平衡表
A7: 3 | B7: 营业收入汇总表
A8: 3.1 | B8: 销售分析
A9: 4 | B9: 增值税金及附加表
A10: 5 | B10: 运营成本汇总表
A11: 5.1 | B11: 运营成本明细表
A12: 6 | B12: 资产折旧摊销表
A13: 7 | B13: 贷款还本付息表
A14: 8 | B14: 总成本估算表
... A22: 16 | B22: 五江现金流量表（劣后级）

Sheet 0基本假设 
J1: 财务基本参数指标 | P1: 财务基本结果指标
J2: 财务基本假设/参数 | P2: 财务指标结果/评价
J3: 编号 | K3: 内容 | L3: 金额 | M3: 单位 | N3: 备注 | P3: 编号 | Q3: 内容 | R3: 金额 | S3: 单位 | T3: 备注
J4: 1 | K4: 项目总投资 | L4: ='附表1 总投资估算表（汇总)'!F20 -> 106762.97 | M4: 万元 | P4: 1 | Q4: 全投资回报指标（股权债权所有者）
J5: 1.1 | K5: 总投资估算（建安未下浮） | L5: ='附表1 总投资估算表（汇总)'!F20 -> 106762.97 | M5: 万元 | P5: 1.1 | Q5: 项目全投资所得税前收益率 | R5: ='附表12 项目全投资现金流量表'!D19 -> 0.019221046
J6: 1.2 | K6: 总投资估算（建安下浮后） | L6: - | M6: 万元 | P6: 1.2 | Q6: 项目全投资所得税后收益率 | R6: ='附表12 项目全投资现金流量表'!D20 -> 0.018534589
J7: 2 | K7: 工程费用 | L7: =L8 -> 40597.55 | M7: 万元 | N7: ="工程占比"&ROUND(L7/L4,2) -> 工程占比0.38 | P7: 1.3 | Q7: 项目全投资回收期（所得税前） | R7: ='附表12 项目全投资现金流量表'!F19 -> 4.96035 | S7: 年
J8: 2.1 | K8: 工程费用（未下浮） | L8: ='附表1 总投资估算表（汇总)'!F4 -> 40597.55 | M8: 万元 | P8: 1.4 | Q8: 项目全投资回收期（所得税后） | R8: ='附表12 项目全投资现金流量表'!F20 -> 4.9616006 | S8: 年
J9: 2.2 | K9: 工程下浮率 | L9: 0
J10: 2.3 | K10: 工程费用（建安下浮后） | L10: =L8*(1-L9) -> 40597.55 | M10: 万元 | P10: 2 | Q10: 资本金回报指标（股权投资者）
J11: 3.1 | K11: 资本金比例 | L11: =L12/L4 -> 0.59051769 | P11: 2.1 | Q11: 项目自有资金所得税前收益率 | R11: ='附表13 项目资本金现金流量'!D22 -> -0.036756886
J12: 3.2 | K12: 资本金金额 | L12: ='附表2 投资计划与资金筹措平衡表 '!O12 -> 63045.425 | M12: 万元 | P12: 2.2 | Q12: 项目自有资金投资所得税后收益率 | R12: ='附表13 项目资本金现金流量'!D23 -> -0.036756886
J13: 3.2.1 | K13: 注册资本金 | L13: 1000 | M13: 万元 | N13: 注册资本金出资比例 | P13: 2.3 | Q13: 项目自有资金投资回收期（所得税前） | R13: ='附表13 项目资本金现金流量'!F22 -> 2.767796 | S13: 年
J14: 3.2.1.1 | K14: 其中：五江方-劣后级 | L14: =$L$13*N14 -> 317.23158 | M14: 万元 | N14: =W18 -> 0.31723158 | P14: 2.4 | Q14: 项目自有资金投资回收期（所得税后） | R14: ='附表13 项目资本金现金流量'!F23 -> 2.767796 | S14: 年
J15: 3.2.1.2 | K15: 其中：中信建设-优先级 | L15: =$L$13*N15 -> 317.23158 | M15: 万元 | N15: =W18 -> 0.31723158
J16: 3.2.1.3 | K16: 其中：中信金资-中间级 | L16: =$L$13*N16 -> 111.75157 | M16: 万元 | N16: =1-N14-N15-N17 -> 0.11175157 | P16: 3 | Q16: 借贷资金回报指标（债权投资者）
J17: 3.2.1.4 | K17: 其中：其他股东 | L17: =$L$13*N17 -> 253.78527 | M17: 万元 | N17: =W19 -> 0.25378527 | P17: 3.1 | Q17: 综合偿债备付率（DSCR） | R17: ='附表7 银行贷款还本付息表'!D31 -> 2.1203097 | T17: 参考，一般需大于1.1
J18: 3.2.1.5 | K18: 其中：其他股东 | L18: =$L$13*N18 -> 0 | M18: 万元 | N18: 0 | P18: 3.2 | Q18: 利息备付系数 | R18: ='附表7 银行贷款还本付息表'!D32 -> 0.15265587 | T18: 参考，一般需大于2 | W18: =20000/L12 -> 0.31723158
J19: 3.2.2 | K19: 资本公积 | L19: =L12-L13 -> 62045.425 | M19: 万元 | N19: 资本金总出资比例 | W19: =16000/L12 -> 0.25378527
J20: 3.2.2.1 | K20: 其中：五江方-劣后级 | L20: =$L$19*N14 -> 19682.768 | M20: 万元 | N20: =N14 -> 0.31723158 | P20: 4 | Q20: 中信建设回报指标（股权投资者+工程总包商）
J21: 3.2.2.2 | K21: 其中：中信建设-优先级 | L21: =$L$19*N15 -> 19682.768 | M21: 万元 | N21: =N15 -> 0.31723158 | P21: 4.1 | Q21: 总包管理费率 | R21: ='附表14 中信建设现金流量表（优先级）'!D21 -> 0.05 | T21: ='附表14 中信建设现金流量表（优先级）'!E21 -> 0
J22: 3.2.2.3 | K22: 其中：中信金资-中间级 | L22: =$L$19*N16 -> 6933.6734 | M22: 万元 | N22: =N16 -> 0.11175157 | P22: 4.2 | Q22: 总包份额比例 | R22: ='附表14 中信建设现金流量表（优先级）'!D22 -> 1 | T22: ='附表14 中信建设现金流量表（优先级）'!E22 -> 0
J23: 3.2.2.6 | K23: =K17 -> 其中：其他股东 | L23: =$L$19*N17 -> 15746.215 | M23: 万元 | N23: =N17 -> 0.25378527 | P23: 4.3 | Q23: FIRR | R23: ='附表14 中信建设现金流量表（优先级）'!D23 -> 0.22291174 | T23: ='附表14 中信建设现金流量表（优先级）'!E23 -> 可行
J24: 3.2.2.7 | K24: =K18 -> 其中：其他股东 | L24: =$L$19*N18 -> 0 | M24: 万元 | N24: =N18 -> 0 | P24: 4.4 | Q24: 投资回收期（静态） | R24: ='附表14 中信建设现金流量表（优先级）'!D24 -> 2.960404 | S24: 年 | T24: ='附表14 中信建设现金流量表（优先级）'!E24 -> 0
J25: 4 | K25: 项目贷款 | L25: =L4-L12-L29 -> 43717.55 | M25: 万元 | N25: =L25/L4 -> 0.40948231 | P25: 4.5 | Q25: 净现值（基准投资折现率） | R25: ='附表14 中信建设现金流量表（优先级）'!D25 -> 4764.7211 | T25: ='附表14 中信建设现金流量表（优先级）'!E25 -> 可行
J26: 4.1 | K26: 贷款金额 | L26: =L4-L12-L29 -> 43717.55 | M26: 万元 | P26: 4.6 | Q26: 工程净利润 | R26: ='附表14 中信建设现金流量表（优先级）'!D26 -> 1220.2577 | T26: ='附表14 中信建设现金流量表（优先级）'!E26 -> 0
J27: 4.2 | K27: 还款期限(公益类) | L27: 0 | M27: 季度 | P27: 4.7 | Q27: 投资收益 | R27: ='附表14 中信建设现金流量表（优先级）'!D27 -> 6398.6552 | T27: ='附表14 中信建设现金流量表（优先级）'!E27 -> 0
J28: 4.3 | K28: 还款期限(经营类) | L28: 10 | M28: 季度 | P28: 4.8 | Q28: 建设期累计净现金流 | R28: ='附表14 中信建设现金流量表（优先级）'!D28 -> -394.51494 | T28: ='附表14 中信建设现金流量表（优先级）'!E28 -> 建设期回收率0.98
J29: 4 | K29: 政府建设期拨款 | L29: ='附表2 投资计划与资金筹措平衡表 '!O21 -> 0 | M29: 万元
J30: 5 | K30: 合作期 | L30: 36 | M30: 季度 | P30: 5 | Q30: 经营者回报指标 | T30: 假定第三方经营者
J31: 5.1 | K31: 建设期 | L31: 10 | M31: 季度 | P31: 5.1 | Q31: 年平均利润率
J32: 5.2 | K32: 运营期 | L32: 10 | M32: 季度 | P32: 5.2 | Q32: 年平均收入 | R32: =R34+R33 -> 327.39014
J33: 6 | K33: 资金成本 | L33: - | P33: 5.3 | Q33: 年平均成本 | R33: =AVERAGE('5.1运营成本明细表'!Q3:Z3) -> 327.39014 | S33: 万元
J34: 6.1 | K34: 长期借款利率 | L34: 0.015 | M34: 季度 | P34: 5.4 | Q34: 年平均利润 | R34: =R33*R31 -> 0 | S34: 万元
J35: 6.2 | K35: 短期借款利率 | L35: 0.008 | M35: 季度 | P35: 5.5 | Q35: 经营者资金周转率=5.2/5.3 | R35: =R32/R33 -> 1
J36: 6.3 | K36: 优先级利率 | L36: 0.0375 | M36: 季度
J37: 7 | K37: 税率与汇率 | L37: - | P37: 6 | Q37: 劣后方投资回报
J38: 7.1 | K38: 增值税及附加 | L38: - | N38: 增值税 | P38: 6.1 | Q38: 自有资金内部收益率 | R38: ='附表16五江现金流量表（劣后级）'!D24 -> -0.1303485
J39: 7.1.1 | K39: 房屋销售增值税税金及附加 | L39: 0.09 | P39: 6.2 | Q39: 投资回收期 | R39: ='附表16五江现金流量表（劣后级）'!D25 -> #REF! | S39: 年
J40: 7.1.2 | K40: 其他业务营业税金及附加 | L40: 0.06 | P40: 6.3 | Q40: 出资现值（按基准收益率） | R40: ='附表16五江现金流量表（劣后级）'!D26 -> -12048.128 | S40: 万元
J41: 7.3 | K41: 企业所得税 | L41: 0.25 | N41: 境内企业
J51: 8 | K51: 工程利润率 | P51: 7 | Q51: 资产与负债
J52: 8.3 | K52: 工程造价调整系数 | L52: 1 | P52: 7.1 | Q52: 建设期末股权投资者总资产 | R52: =#REF! -> #REF! | S52: 万元
J53: 8.4 | K53: 工程总包毛利率 | L53: 0.05 | P53: 7.2 | Q53: 建设期末股权投资者总负债 | R53: =#REF! -> #REF! | S53: 万元
J54: 9 | K54: 售价-成本 | P54: 7.3 | Q54: 建设期末股权投资者总所有者权益 | R54: =#REF! -> #REF! | S54: 万元
J55: 9.1 | K55: 住宅 | L55: 11500 | M55: 元 | P55: 7.4 | Q55: 投资回报率（ROI） | R55: =AVERAGE(附表9利润表!N12:W12)/'0基本假设 '!L4 -> 0.010989695 | T55: 反映经营回报
J56: 9.2 | K56: 商业 | L56: 18000 | M56: 元 | P56: 7.5 | Q56: 总资产回报率（ROA） | R56: =AVERAGE(附表9利润表!N12:W12)/AVERAGE(#REF!) -> #REF! | T56: 反映资产回报
J57: 9.3 | K57: 车位 | L57: 120000 | M57: 元 | P57: 7.6 | Q57: 股东权益回报率(ROE) | R57: =AVERAGE(附表9利润表!N12:W12)/'0基本假设 '!L12 -> 0.018610272 | T57: 反映股权回报
J58: 9.4 | K58: 住宅建设成本 | L58: 3300 | P58: 8 | Q58: 全投资现金流量图（所得税后） | T58: 所得税后
J59: 9.5 | K59: 商业建设成本 | L59: 3600
J60: 9.6 | K60: 车位建设成本 | L60: 50000 | M60: 元/个
J61: 9.7
J62: 9.8
J63: 9.9
J64: 9.10
J65: 9.11
J81: 点击返回目录

Sheet 附表1 总投资估算表（汇总)
A1: 附表1 项目总投资估算表 (单位：万元)
A2: 序号 | B2: 费用名称 | C2: 1号路段-平原105KM | D2: 清水湾项目 | E2: 3号公路-平原168KM | F2: 投资额 | G2: 估算说明
A3: 1 | B3: 建设投资 | C3: =SUM(C4:C15) -> 0 | D3: =SUM(D4:D15) -> 103549.74 | E3: =SUM(E4:E15) -> 0 | F3: =F4+F12+F15 -> 103549.74
A4: 1.1 | B4: 工程费用 | C4: ='附表1.1 总投资估算（明细）'!H6 -> 0 | D4: ='附表1.1 总投资估算（明细）'!H16 -> 40597.55 | E4: ='附表1.1 总投资估算（明细）'!H26 -> 0 | F4: ='附表1.1 总投资估算（明细）'!H4 -> 40597.55
A5: 1.1.1 | B5: 分部分项工程合价 | F5: 0
A6: 1.1.2 | B6: 其他项目合价 | F6: 0
A7: 1.1.2.1 | B7: 暂列金额 | F7: 0
A8: 1.1.2.2 | B8: 暂估价 | F8: 0
A9: 1.1.3 | B9: 总价措施项目合价 | F9: 0
A10: 1.1.4 | B10: 规费 | F10: 0
A11: 1.1.5 | B11: 税金 | F11: 0
A12: 1.2 | B12: 工程建设其他费用 | C12: ='附表1.1 总投资估算（明细）'!$H$37*'附表1 总投资估算表（汇总)'!C22 -> 0 | D12: ='附表1.1 总投资估算（明细）'!$H$37*'附表1 总投资估算表（汇总)'!D22 -> 62952.185 | E12: ='附表1.1 总投资估算（明细）'!$H$37*'附表1 总投资估算表（汇总)'!E22 -> 0 | F12: ='附表1.1 总投资估算（明细）'!H37 -> 62952.185
A13: 1.2.1 | B13: 招标文件约定前期工作费用
A14: 1.2.2 | B14: 其他工程建设其他费用（其他二类费） | F14: 0
A15: 1.3 | B15: 预备费 | C15: ='附表1.1 总投资估算（明细）'!$H$68*0 -> 0 | D15: ='附表1.1 总投资估算（明细）'!$H$68*0 -> 0 | E15: ='附表1.1 总投资估算（明细）'!$H$68*0 -> 0 | F15: ='附表1.1 总投资估算（明细）'!H68 -> 0
A16: 1.3.1 | B16: 基本预备费
A17: 1.3.2 | B17: 涨价预备费
A18: 2 | B18: 建设期利息 | C18: ='附表2 投资计划与资金筹措平衡表 '!#REF! -> #REF! | D18: ='附表1.1 总投资估算（明细）'!H69 -> 3213.2399 | E18: ='附表2 投资计划与资金筹措平衡表 '!#REF! -> #REF! | F18: ='附表1.1 总投资估算（明细）'!H69 -> 3213.2399
A19: 3 | B19: 流动资金
B20: 项目总投资 | C20: =C3+C18 -> #REF! | D20: =D3+D18 -> 106762.97 | E20: =E3+E18 -> #REF! | F20: =F3+F18+F19 -> 106762.97
B22: 工程费用占比 | C22: =C4/$F$4 -> 0 | D22: =D4/$F$4 -> 1 | E22: =E4/$F$4 -> 0 | F22: =F4/$F$4 -> 1
B23: 工程其他费用占比 | C23: =C12/$F$12 -> 0 | D23: =D12/$F$12 -> 1 | E23: =E12/$F$12 -> 0 | F23: =F12/$F$12 -> 1
B24: 预备费占比 | C24: =C15/$F$15 -> #DIV/0! | D24: =D15/$F$15 -> #DIV/0! | E24: =E15/$F$15 -> #DIV/0! | F24: =F15/$F$15 -> #DIV/0!
B25: 利息占比 | C25: =C18/$F$18 -> #REF! | D25: =D18/$F$18 -> 1 | E25: =E18/$F$18 -> #REF! | F25: =F18/$F$18 -> 1
B26: 总投占比 | C26: =C20/$F$20 -> #REF! | D26: =D20/$F$20 -> 1 | E26: =E20/$F$20 -> #REF! | F26: =F20/$F$20 -> 1
A27: 点击返回目录

Sheet 附表1.1 总投资估算（明细）
A1: 附表1.1 总投资估算表（明细）
A2: 总投资估算表(单位：万元)
A3: 序号 | B3: 指标 | C3: 单位 | F3: 总数量 | G3: 单价 | H3: 金额 | I3: 占比
A4: 一 | B4: 工程费 | H4: =H5+H36 -> 40597.55 | I4: =H4/$H$70 -> 0.3802587
A5: 1 | B5: 建安工程费 | H5: =H6+H16+H26 -> 40597.55 | I5: =H5/$H$70 -> 0.3802587
A6: 1.1 | B6: 1号路段-平原107KM | H6: =SUM(H7,H8:H13,H14:H15) -> 0 | I6: =H6/$H$70 -> 0
A7: 1.1.1 | B7: 临时工程 | F7: 1 | G7: 0 | H7: =ROUND(F7*G7,2) -> 0 | I7: =H7/$H$70 -> 0
A8: 1.1.2 | B8: 路基工程 | F8: 1 | H8: =ROUND(F8*G8,2) -> 0 | I8: =H8/$H$70 -> 0
A9: 1.1.3 | B9: 路面工程 | F9: 1 | H9: =ROUND(F9*G9,2) -> 0 | I9: =H9/$H$70 -> 0
A10: 1.1.4 | B10: 桥梁涵洞工程 | F10: 1 | H10: =ROUND(F10*G10,2) -> 0 | I10: =H10/$H$70 -> 0
A11: 1.1.5 | B11: 交叉工程 | F11: 1 | H11: =ROUND(F11*G11,2) -> 0 | I11: =H11/$H$70 -> 0
A12: 1.1.6 | B12: 隧道工程 | F12: 1 | H12: =ROUND(F12*G12,2) -> 0 | I12: =H12/$H$70 -> 0
A13: 1.1.7 | B13: 公路设施及预埋管线工程 | F13: 1 | G13: 0 | H13: =ROUND(F13*G13,2) -> 0 | I13: =H13/$H$70 -> 0
A14: 1.1.8 | B14: 绿化及环境保护工程 | F14: 1 | G14: 0 | H14: =ROUND(F14*G14,2) -> 0 | I14: =H14/$H$70 -> 0
A15: 1.1.9 | B15: 管理、养护及服务（建设期） | F15: 1 | G15: 0 | H15: =ROUND(F15*G15,2) -> 0 | I15: =H15/$H$70 -> 0
A16: 1.1 | B16: 五江项目 | H16: =SUM(H17,H18:H25) -> 40597.55 | I16: =H16/$H$70 -> 0.3802587
A17: 1.2.1 | F17: 1 | H17: =ROUND(F17*G17,2) -> 0 | I17: =H17/$H$70 -> 0
A18: 1.2.1 | B18: 住宅 | F18: =附表3营业收入汇总表!C28/10000 -> 8.694932 | G18: ='0基本假设 '!L58 -> 3300 | H18: =ROUND(F18*G18,2) -> 28693.28 | I18: =H18/$H$70 -> 0.26875684
A19: 1.2.2 | B19: 商业 | F19: =附表3营业收入汇总表!C27/10000 -> 1.617853 | G19: ='0基本假设 '!L59 -> 3600 | H19: =ROUND(F19*G19,2) -> 5824.27 | I19: =H19/$H$70 -> 0.054553276
A20: 1.2.3 | B20: 车位 | F20: =附表3营业收入汇总表!C26/10000 -> 0.0796 | G20: ='0基本假设 '!L60 -> 50000 | H20: =ROUND(F20*G20,2) -> 3980 | I20: =H20/$H$70 -> 0.037278841
A21: 1.2.4 | B21: 工程后续成本 | H21: =ROUND(F21*G21,2) -> 0 | I21: =H21/$H$70 -> 0
A22: 1.2.5 | B22: 基础设施费 | F22: 3 | G22: 700 | H22: =ROUND(F22*G22,2) -> 2100 | I22: =H22/$H$70 -> 0.01966974
A23: 1.2.7 | F23: 1 | G23: 0 | H23: =ROUND(F23*G23,2) -> 0 | I23: =H23/$H$70 -> 0
A24: 1.2.8 | F24: 1 | G24: 0 | H24: =ROUND(F24*G24,2) -> 0 | I24: =H24/$H$70 -> 0
A25: 1.2.9 | F25: 1 | G25: 0 | H25: =ROUND(F25*G25,2) -> 0 | I25: =H25/$H$70 -> 0
A26: 1.3 | B26: 3号公路-平原148KM | H26: =SUM(H27:H35) -> 0 | I26: =H26/$H$70 -> 0
A27: 1.3.1 | B27: 临时工程 | F27: 1 | H27: =ROUND(F27*G27,2) -> 0 | I27: =H27/$H$70 -> 0
A28: 1.3.2 | B28: 路基工程 | D28: 640.8 | E28: 144.4 | F28: 1 | H28: =ROUND(F28*G28,2) -> 0 | I28: =H28/$H$70 -> 0
A29: 1.3.3 | B29: 路面工程 | F29: 1 | H29: =ROUND(F29*G29,2) -> 0 | I29: =H29/$H$70 -> 0
A30: 1.3.4 | B30: 桥梁涵洞工程 | D30: 32.9 | E30: 54 | F30: 1 | H30: =ROUND(F30*G30,2) -> 0 | I30: =H30/$H$70 -> 0
A31: 1.3.5 | B31: 交叉工程 | F31: 1 | H31: =ROUND(F31*G31,2) -> 0 | I31: =H31/$H$70 -> 0
A32: 1.3.6 | B32: 隧道工程 | D32: 0 | E32: 0 | F32: 1 | H32: =ROUND(F32*G32,2) -> 0 | I32: =H32/$H$70 -> 0
A33: 1.3.7 | B33: 公路设施及预埋管线工程 | F33: 1 | G33: =SUM(D33:E33) -> 0 | H33: =ROUND(F33*G33,2) -> 0 | I33: =H33/$H$70 -> 0
A34: 1.3.8 | B34: 绿化及环境保护工程 | F34: 1 | G34: =SUM(D34:E34) -> 0 | H34: =ROUND(F34*G34,2) -> 0 | I34: =H34/$H$70 -> 0
A35: 1.3.9 | B35: 管理、养护及服务（建设期） | F35: 1 | G35: =SUM(D35:E35) -> 0 | H35: =ROUND(F35*G35,2) -> 0 | I35: =H35/$H$70 -> 0
A36: 2 | B36: 设备及工具、器具购置费 | G36: 0 | H36: =ROUND(F36*G36,2) -> 0 | I36: =H36/$H$70 -> 0
A37: 二 | B37: 工程建设其他费用 | H37: =SUM(H43,H49:H51,H55:H57,H62:H67)+H38 -> 62952.185 | I37: =H37/$H$70 -> 0.58964435
A38: 0 | B38: 土地费用 | C38: 项 | F38: 0 | H38: =SUM(H39:H42) -> 59832.185 | I38: =H38/$H$70 -> 0.56042074
A39: 0.1 | B39: 土地出让金 | F39: 52770 | G39: 1 | H39: =F39*G39 -> 52770
A40: 0.2 | B40: 契税 | F40: =F39*0.04 -> 2110.8 | G40: 1 | H40: =F40*G40 -> 2110.8
A41: 0.3 | B41: 印花税 | F41: =F39*0.0005 -> 26.385 | G41: 1 | H41: =F41*G41 -> 26.385
A42: 0.4 | B42: 教育配套费 | F42: 4925 | G42: 1 | H42: =F42*G42 -> 4925
A43: 1 | B43: 前期工作费用 | C43: 项 | G43: =SUM(G44:G46) -> 0 | H43: =SUM(H47:H48) -> 3120 | I43: =H43/$H$70 -> 0.029223614
H44: =ROUND(F44*G44,2) -> 0
H45: =ROUND(F45*G45,2) -> 0
H46: =ROUND(F46*G46,2) -> 0
A47: 1.1 | B47: 报批报建费 | F47: 2850 | G47: 1 | H47: =F47*G47 -> 2850
A48: 1.2 | B48: 规划设计费 | F48: 270 | G48: 1 | H48: =F48*G48 -> 270
A49: 2 | B49: 建设单位管理费 | C49: 项 | F49: 1 | I49: =H49/$H$70 -> 0
A50: 3 | B50: 研究试验费 | F50: 1 | G50: 0 | H50: =ROUND(F50*G50,2) -> 0 | I50: =H50/$H$70 -> 0
A51: 4 | B51: 勘察设计费 | C51: 项 | F51: 1 | G51: 0 | H51: =SUM(H52:H54) -> 0 | I51: =H51/$H$70 -> 0
A52: 4.1 | B52: 工程勘察费 | C52: 项 | F52: 1 | G52: 0 | H52: =ROUND(F52*G52,2) -> 0 | I52: =H52/$H$70 -> 0
A53: 4.2 | B53: 工程设计费 | C53: 项 | F53: 1 | G53: 0 | H53: =ROUND(F53*G53,2) -> 0 | I53: =H53/$H$70 -> 0
A54: 4.3 | B54: 勘察、施工图审查费 | C54: 项 | F54: 1 | G54: 0 | H54: =ROUND(F54*G54,2) -> 0 | I54: =H54/$H$70 -> 0
A55: 5 | B55: 环境影响咨询服务费 | C55: 项 | F55: 1 | G55: 0 | H55: =ROUND(F55*G55,2) -> 0 | I55: =H55/$H$70 -> 0
A56: 6 | B56: 工程监理费 | C56: 项 | F56: 1 | G56: 0 | H56: =ROUND(F56*G56,2) -> 0 | I56: =H56/$H$70 -> 0
A57: 7 | B57: 造价咨询服务费 | C57: 项 | F57: 1 | G57: 0 | H57: =SUM(H58:H61) -> 0 | I57: =H57/$H$70 -> 0
A58: 7.1 | B58: 招标代理费 | C58: 项 | F58: 1 | G58: 0 | H58: =ROUND(F58*G58,2) -> 0 | I58: =H58/$H$70 -> 0
A59: 7.2 | B59: 工程量清单及招标控制价编制费 | C59: 项 | F59: 1 | G59: 0 | H59: =ROUND(F59*G59,2) -> 0 | I59: =H59/$H$70 -> 0
A60: 7.3 | B60: 工程跟踪审计服务费 | C60: 项 | F60: 1 | G60: 0 | H60: =ROUND(F60*G60,2) -> 0 | I60: =H60/$H$70 -> 0
A61: 7.4 | B61: 工程结算审核费 | C61: 项 | F61: 1 | G61: 0 | H61: =ROUND(F61*G61,2) -> 0 | I61: =H61/$H$70 -> 0
A62: 8 | B62: 联合试运转费 | C62: 项 | F62: 1 | G62: 0 | H62: =ROUND(F62*G62,2) -> 0 | I62: =H62/$H$70 -> 0
A63: 9 | B63: 工程保险费 | C63: 项 | F63: 1 | H63: =ROUND(F63*G63,2) -> 0 | I63: =H63/$H$70 -> 0
A64: 10 | B64: 场地准备和临时设施 | C64: 项 | F64: 1 | G64: 0 | H64: =ROUND(F64*G64,2) -> 0 | I64: =H64/$H$70 -> 0
A65: 11 | B65: 材料检测试验费 | C65: 项 | F65: 1 | G65: 0 | H65: =ROUND(F65*G65,2) -> 0 | I65: =H65/$H$70 -> 0
A66: 12 | B66: 工程监测费 | C66: 项 | F66: 1 | G66: 0 | H66: =ROUND(F66*G66,2) -> 0 | I66: =H66/$H$70 -> 0
A67: 13 | B67: 移交培训费 | C67: 项 | F67: 1 | G67: 0 | H67: =ROUND(F67*G67,2) -> 0 | I67: =H67/$H$70 -> 0
A68: 三 | B68: 预备费=（一+二）*0% | C68: 项 | F68: 0 | H68: =(H4+H37)*0% -> 0 | I68: =H68/$H$70 -> 0
A69: 四 | B69: 建设期利息 | H69: ='附表2 投资计划与资金筹措平衡表 '!O9 -> 3213.2399 | I69: =H69/$H$70 -> 0.03009695
B70: 项目总投资 | H70: =H4+H37+H68+H69 -> 106762.97 | I70: =H70/$H$70 -> 1
A72: 点击返回目录

Sheet 附表2 投资计划与资金筹措平衡表 
B2: 附表2 投资计划与资金筹措平衡表 (单位：万元)
B3: 序号 | D3: 建设期 | O3: 合计 | P3: 占总投资比例 | R3: 投资进度
C4: 项目 | D4: 第1年Q1 | E4: 第1年Q2 | F4: 第1年Q3 | G4: 第1年Q4 | H4: 第2年Q3 | I4: 第2年Q4 | J4: 第2年Q3 | K4: 第2年Q4 | L4: 第3年Q31 | M4: 第3年Q2 | N4: 第5年 | R4: 第1年Q1 | S4: 第1年Q2 | T4: 第1年Q3 | U4: 第1年Q4 | V4: 第2年Q3 | W4: 第2年Q4 | X4: 第3年Q1 | Y4: 第3年Q2 | Z4: 第3年Q3 | AA4: 第3年Q4 | AB4: 第5年 | AC4: 合计
B5: 1 | C5: 项目总投资 | D5: =D6+D7+D8+D9 -> 59832.185 | E5: =E6+E7+E8+E9 -> 8809.0863 | F5: =F6+F7+F8+F9 -> 4535.6958 | G5: =G6+G7+G8+G9 -> 4601.2721 | H5: =H6+H7+H8+H9 -> 4666.8485 | I5: =I6+I7+I8+I9 -> 4732.4248 | J5: =J6+J7+J8+J9 -> 4798.0011 | K5: =K6+K7+K8+K9 -> 4863.5774 | ... M5: =M6+M7+M8+M9 -> 4994.7301 | O5: =SUM(D5:M5) -> 106762.97 | P5: =O5/$O$5 -> 1 | R5: =D5/$O$5 -> 0.56042074 | S5: =E5/$O$5 -> 0.082510686 | T5: =F5/$O$5 -> 0.04248379 | U5: =G5/$O$5 -> 0.043098014 | V5: =H5/$O$5 -> 0.043712237 | W5: =I5/$O$5 -> 0.04432646 | X5: =J5/$O$5 -> 0.044940684 | Y5: =K5/$O$5 -> 0.045554907 | ... AA5: =M5/$O$5 -> 0.046783354 | AC5: =SUM(R5:AA5) -> 1
B6: 1.1 | C6: 工程费用 | E6: ='附表1.1 总投资估算（明细）'!$H$4*(R12+S12) -> 8119.51 | F6: ='附表1.1 总投资估算（明细）'!$H$4*'附表2 投资计划与资金筹措平衡表 '!T$12 -> 4059.755 | G6: ='附表1.1 总投资估算（明细）'!$H$4*'附表2 投资计划与资金筹措平衡表 '!U$12 -> 4059.755 | H6: ='附表1.1 总投资估算（明细）'!$H$4*'附表2 投资计划与资金筹措平衡表 '!V$12 -> 4059.755 | I6: ='附表1.1 总投资估算（明细）'!$H$4*'附表2 投资计划与资金筹措平衡表 '!W$12 -> 4059.755 | J6: ='附表1.1 总投资估算（明细）'!$H$4*'附表2 投资计划与资金筹措平衡表 '!X$12 -> 4059.755 | K6: ='附表1.1 总投资估算（明细）'!$H$4*'附表2 投资计划与资金筹措平衡表 '!Y$12 -> 4059.755 | L6: ='附表1.1 总投资估算（明细）'!$H$4*'附表2 投资计划与资金筹措平衡表 '!Z$12 -> 4059.755 | M6: ='附表1.1 总投资估算（明细）'!$H$4*'附表2 投资计划与资金筹措平衡表 '!AA$12 -> 4059.755 | O6: =SUM(D6:M6) -> 40597.55 | P6: =O6/$O$5 -> 0.3802587 | R6: 根据工程进度及工程建设其他费进度及预备费的调整后的投资进度如上
B7: 1.2 | C7: 工程建设其他费 | D7: ='附表1.1 总投资估算（明细）'!H38 -> 59832.185 | E7: =('附表1.1 总投资估算（明细）'!$H$37-'附表1.1 总投资估算（明细）'!$H$38)*(R16+S16) -> 624 | F7: =('附表1.1 总投资估算（明细）'!$H$37-'附表1.1 总投资估算（明细）'!$H$38)*T16 -> 312 | G7: =('附表1.1 总投资估算（明细）'!$H$37-'附表1.1 总投资估算（明细）'!$H$38)*U16 -> 312 | H7: =('附表1.1 总投资估算（明细）'!$H$37-'附表1.1 总投资估算（明细）'!$H$38)*V16 -> 312 | I7: =('附表1.1 总投资估算（明细）'!$H$37-'附表1.1 总投资估算（明细）'!$H$38)*W16 -> 312 | J7: =('附表1.1 总投资估算（明细）'!$H$37-'附表1.1 总投资估算（明细）'!$H$38)*X16 -> 312 | K7: =('附表1.1 总投资估算（明细）'!$H$37-'附表1.1 总投资估算（明细）'!$H$38)*Y16 -> 312 | L7: =('附表1.1 总投资估算（明细）'!$H$37-'附表1.1 总投资估算（明细）'!$H$38)*Z16 -> 312 | M7: =('附表1.1 总投资估算（明细）'!$H$37-'附表1.1 总投资估算（明细）'!$H$38)*AA16 -> 312 | N7: ='附表1.1 总投资估算（明细）'!$H$37*AB16 -> 0 | O7: =SUM(D7:M7) -> 62952.185 | P7: =O7/$O$5 -> 0.58964435
B8: 1.3 | C8: 预备费 | D8: =D20+D25 -> 0 | E8: =E20+E25 -> 0 | F8: =F20+F25 -> 0 | G8: =G20+G25 -> 0 | H8: =H20+H25 -> 0 | I8: =I20+I25 -> 0 | J8: =J20+J25 -> 0 | K8: =K20+K25 -> 0 | ... M8: =M20+M25 -> 0 | O8: =SUM(D8:M8) -> 0 | P8: =O8/$O$5 -> 0
B9: 1.4 | C9: 建设期利息 | D9: =D15+D19+D24 -> 0 | E9: =E15+E19+E24 -> 65.576325 | F9: =F15+F19+F24 -> 163.94081 | G9: =G15+G19+G24 -> 229.51714 | H9: =H15+H19+H24 -> 295.09346 | I9: =I15+I19+I24 -> 360.66979 | J9: =J15+J19+J24 -> 426.24611 | K9: =K15+K19+K24 -> 491.82244 | ... M9: =M15+M19+M24 -> 622.97509 | O9: =SUM(D9:M9) -> 3213.2399 | P9: =O9/$O$5 -> 0.03009695 | R9: 工程进度
B10: 1.5 | C10: 流动资金 | M10: =M20 -> 0 | O10: =SUM(D10:M10) -> 0 | P10: =O10/$O$5 -> 0 | R10: 工程进度
B11: 2 | C11: 资金筹措 | D11: =D12+D16+D21 -> 59832.185 | E11: =E12+E16+E21 -> 8809.0863 | F11: =F12+F16+F21 -> 4535.6958 | G11: =G12+G16+G21 -> 4601.2721 | H11: =H12+H16+H21 -> 4666.8485 | I11: =I12+I16+I21 -> 4732.4248 | J11: =J12+J16+J21 -> 4798.0011 | K11: =K12+K16+K21 -> 4863.5774 | ... N11: =N12+N16+N21 -> 0 | O11: =SUM(D11:M11) -> 106762.97 | P11: =O11/$O$5 -> 1 | R11: 第1年Q1 | S11: 第1年Q2 | T11: 第1年Q3 | U11: 第1年Q4 | V11: 第2年Q3 | W11: 第2年Q4 | X11: 第3年Q1 | Y11: 第3年Q2 | Z11: 第3年Q3 | AA11: 第3年Q4 | AB11: 第5年 | AC11: 合计
B12: 2.1 | C12: 项目资本金 | D12: =SUM(D13:D15) -> 59832.185 | E12: =SUM(E13:E15) -> 65.576325 | F12: =SUM(F13:F15) -> 163.94081 | G12: =SUM(G13:G15) -> 229.51714 | H12: =SUM(H13:H15) -> 295.09346 | I12: =SUM(I13:I15) -> 360.66979 | J12: =SUM(J13:J15) -> 426.24611 | K12: =SUM(K13:K15) -> 491.82244 | ... N12: =SUM(N13:N15) -> 0 | O12: =SUM(D12:M12) -> 63045.425 | P12: =O12/$O$5 -> 0.59051769 | R12: 0.1 | S12: 0.1 | T12: 0.1 | U12: 0.1 | V12: 0.1 | W12: 0.1 | X12: 0.1 | Y12: 0.1 | Z12: 0.1 | AA12: 0.1 | AC12: =SUM(R12:AB12) -> 1
B13: 2.1.1 | C13: 用于工程费用 | E13: =E6-E17 -> 0 | F13: =F6-F17 -> 0 | G13: =G6-G17 -> 0 | H13: =H6-H17 -> 0 | I13: =I6-I17 -> 0 | J13: =J6-J17 -> 0 | K13: =K6-K17 -> 0 | L13: =L6-L17 -> 0 | M13: =M6-M17 -> 0 | O13: =SUM(D13:M13) -> 0 | P13: =O13/$O$5 -> 0
B14: 2.1.2 | C14: 用于工程其他费 | D14: ='附表1.1 总投资估算（明细）'!H38 -> 59832.185 | E14: =E7-E18 -> 0 | F14: =F7-F18 -> 0 | G14: =G7-G18 -> 0 | H14: =H7-H18 -> 0 | I14: =I7-I18 -> 0 | J14: =J7-J18 -> 0 | K14: =K7-K18 -> 0 | L14: =L7-L18 -> 0 | M14: =M7-M18 -> 0 | O14: =SUM(D14:M14) -> 59832.185 | P14: =O14/$O$5 -> 0.56042074 | R14: 工程建设其他费及前期费用投资进度
B15: 2.1.3 | C15: 用于建设期利息 | E15: =E29 -> 65.576325 | F15: =F29 -> 163.94081 | G15: =G29 -> 229.51714 | H15: =H29 -> 295.09346 | I15: =I29 -> 360.66979 | J15: =J29 -> 426.24611 | K15: =K29 -> 491.82244 | L15: =L29 -> 557.39876 | M15: =M29 -> 622.97509 | O15: =SUM(D15:M15) -> 3213.2399 | R15: 第1年Q1 | S15: 第1年Q2 | T15: 第1年Q3 | U15: 第1年Q4 | V15: 第2年Q3 | W15: 第2年Q4 | X15: 第3年Q1 | Y15: 第3年Q2 | Z15: 第3年Q3 | AA15: 第3年Q4 | AB15: 第5年 | AC15: 合计
B16: 2.2 | C16: 债务性资金 | D16: =D17+D18+D19+D20 -> 0 | E16: =E17+E18+E19+E20 -> 8743.51 | F16: =F17+F18+F19+F20 -> 4371.755 | G16: =G17+G18+G19+G20 -> 4371.755 | H16: =H17+H18+H19+H20 -> 4371.755 | I16: =I17+I18+I19+I20 -> 4371.755 | J16: =J17+J18+J19+J20 -> 4371.755 | K16: =K17+K18+K19+K20 -> 4371.755 | ... M16: =M17+M18+M19+M20 -> 4371.755 | O16: =SUM(D16:M16) -> 43717.55 | P16: =O16/$O$5 -> 0.40948231 | R16: =R12 -> 0.1 | S16: =S12 -> 0.1 | T16: =T12 -> 0.1 | U16: =U12 -> 0.1 | V16: =V12 -> 0.1 | W16: =W12 -> 0.1 | X16: =X12 -> 0.1 | Y16: =Y12 -> 0.1 | ... AA16: =AA12 -> 0.1 | AC16: =SUM(R16:AA16) -> 1
B17: 2.2.1 | C17: 用于工程费用 | E17: =$R$21*(S12+R12) -> 8119.51 | F17: =$R$21*T12 -> 4059.755 | G17: =$R$21*U12 -> 4059.755 | H17: =$R$21*V12 -> 4059.755 | I17: =$R$21*W12 -> 4059.755 | J17: =$R$21*X12 -> 4059.755 | K17: =$R$21*Y12 -> 4059.755 | L17: =$R$21*Z12 -> 4059.755 | M17: =$R$21*AA12 -> 4059.755 | N17: =$R$23*AB12 -> 0 | O17: =SUM(D17:M17) -> 40597.55 | P17: =O17/$O$5 -> 0.3802587 | R17: 按照项目公司未来筹集计划，土地使用费、城市建设配套费、前期工作咨询费、规划设计费、招标代理费需要第一年支付；其余工程其他费用后续支付
B18: 2.2.2 | C18: 用于工程其他费 | D18: 0 | E18: =$R$22*(S16+R16) -> 624 | F18: =$R$22*T16 -> 312 | G18: =$R$22*U16 -> 312 | H18: =$R$22*V16 -> 312 | I18: =$R$22*W16 -> 312 | J18: =$R$22*X16 -> 312 | K18: =$R$22*Y16 -> 312 | L18: =$R$22*Z16 -> 312 | M18: =$R$22*AA16 -> 312 | O18: =SUM(D18:N18) -> 3120 | P18: =O18/$O$5 -> 0.029223614
B19: 2.2.3 | C19: 用于建设期利息 | D19: 0 | E19: 0 | F19: 0 | G19: 0 | H19: 0 | I19: 0 | J19: 0 | K19: 0 | L19: 0 | M19: 0 | O19: =SUM(D19:N19) -> 0 | P19: =O19/$O$5 -> 0
B20: 2.2.4 | C20: 用于预备费 | O20: =SUM(D20:N20) -> 0 | P20: =O20/$O$5 -> 0
B21: 2.3 | C21: 政府建设拨款 | D21: =D22+D23+D24+D25 -> 0 | E21: =E22+E23+E24+E25 -> 0 | F21: =F22+F23+F24+F25 -> 0 | G21: =G22+G23+G24+G25 -> 0 | H21: =H22+H23+H24+H25 -> 0 | I21: =I22+I23+I24+I25 -> 0 | J21: =J22+J23+J24+J25 -> 0 | K21: =K22+K23+K24+K25 -> 0 | ... N21: =N22+N23+N24+N25 -> 0 | O21: =SUM(D21:N21) -> 0 | P21: =O21/$O$5 -> 0 | R21: ='附表1.1 总投资估算（明细）'!H4 -> 40597.55
B22: 2.2.1 | C22: 用于工程费用 | D22: =D6*'0基本假设 '!$N$29 -> 0 | E22: =E6*'0基本假设 '!$N$29 -> 0 | F22: =F6*'0基本假设 '!$N$29 -> 0 | G22: =G6*'0基本假设 '!$N$29 -> 0 | H22: =H6*'0基本假设 '!$N$29 -> 0 | I22: =I6*'0基本假设 '!$N$29 -> 0 | J22: =J6*'0基本假设 '!$N$29 -> 0 | K22: =K6*'0基本假设 '!$N$29 -> 0 | ... M22: =M6*'0基本假设 '!$N$29 -> 0 | O22: =SUM(D22:N22) -> 0 | P22: =O22/$O$5 -> 0 | R22: ='附表1.1 总投资估算（明细）'!H37-'附表1.1 总投资估算（明细）'!H38 -> 3120
B23: 2.2.2 | C23: 用于工程其他费 | O23: =SUM(D23:N23) -> 0 | P23: =O23/$O$5 -> 0 | R23: ='附表1.1 总投资估算（明细）'!H4+'附表1.1 总投资估算（明细）'!H43 -> 43717.55
B24: 2.2.3 | C24: 用于建设期利息 | O24: =SUM(D24:N24) -> 0 | P24: =O24/$O$5 -> 0
B25: 2.2.4 | C25: 用于预备费 | O25: =SUM(D25:N25) -> 0 | P25: =O25/$O$5 -> 0
D27: 建设期利息计算过程
C28: 借款额 | D28: =D16 -> 0 | E28: =E16 -> 8743.51 | F28: =F16 -> 4371.755 | G28: =G16 -> 4371.755 | H28: =H16 -> 4371.755 | I28: =I16 -> 4371.755 | J28: =J16 -> 4371.755 | K28: =K16 -> 4371.755 | ... N28: =N16 -> 0 | O28: 合计
C29: 借款利息 | D29: =D28*0.5*'0基本假设 '!L34 -> 0 | E29: =D28*'0基本假设 '!L34+E28*'0基本假设 '!L34/2 -> 65.576325 | F29: =SUM($E$28:E28)*'0基本假设 '!$L$34+F28*'0基本假设 '!$L$34/2 -> 163.94081 | G29: =SUM($E$28:F28)*'0基本假设 '!$L$34+G28*'0基本假设 '!$L$34/2 -> 229.51714 | H29: =SUM($E$28:G28)*'0基本假设 '!$L$34+H28*'0基本假设 '!$L$34/2 -> 295.09346 | I29: =SUM($E$28:H28)*'0基本假设 '!$L$34+I28*'0基本假设 '!$L$34/2 -> 360.66979 | J29: =SUM($E$28:I28)*'0基本假设 '!$L$34+J28*'0基本假设 '!$L$34/2 -> 426.24611 | K29: =SUM($E$28:J28)*'0基本假设 '!$L$34+K28*'0基本假设 '!$L$34/2 -> 491.82244 | L29: =SUM($E$28:K28)*'0基本假设 '!$L$34+L28*'0基本假设 '!$L$34/2 -> 557.39876 | M29: =SUM($E$28:L28)*'0基本假设 '!$L$34+M28*'0基本假设 '!$L$34/2 -> 622.97509 | N29: 0 | O29: =SUM(D29:M29) -> 3213.2399
C30: 投资贷款节奏 | D30: =R5 -> 0.56042074 | E30: =S5 -> 0.082510686 | F30: =T5 -> 0.04248379 | G30: =U5 -> 0.043098014 | H30: =V5 -> 0.043712237 | I30: =W5 -> 0.04432646 | J30: =X5 -> 0.044940684 | K30: =Y5 -> 0.045554907 | ... M30: =AA5 -> 0.046783354 | O30: =SUM(D30:M30) -> 1
B31: 点击返回目录

Sheet 附表3营业收入汇总表
A1: 附表4 营业收入明细表 (单位：万元)
A2: 序号 | B2: 项目 | C2: 合计 | D2: 第1年Q1 | E2: 第1年Q2 | F2: 第1年Q3 | G2: 第1年Q4 | H2: 第2年Q1 | I2: 第2年Q2 | J2: 第2年Q3 | K2: 第2年Q4 | L2: 第3年Q1 | M2: 第3年Q2 | N2: 第3年Q3 | O2: 第3年Q4 | P2: 第4年Q1 | Q2: 第4年Q2 | R2: 第4年Q3 | S2: 第4年Q4 | T2: 第5年Q1 | U2: 第5年Q2 | V2: 第5年Q3 | W2: 第5年Q4
A3: 1 | B3: 收入合计 | C3: =SUM(D3:W3) -> 115945.07 | D3: =D4+D6 -> 0 | E3: =E4+E6 -> 0 | F3: =F4+F6 -> 0 | G3: =G4+G6 -> 23989.014 | H3: =H4+H6 -> 9345.6058 | I3: =I4+I6 -> 9345.6058 | J3: =J4+J6 -> 12943.958 | K3: =K4+K6 -> 6946.7043 | ... W3: =W4+W6 -> 26137.916
A4: 1.1 | B4: 销售收入 | C4: =SUM(D4:W4) -> 115945.07 | D4: =D5 -> 0 | E4: =E5 -> 0 | F4: =F5 -> 0 | G4: =G5 -> 23989.014 | H4: =H5 -> 9345.6058 | I4: =I5 -> 9345.6058 | J4: =J5 -> 12943.958 | K4: =K5 -> 6946.7043 | ... W4: =W5 -> 26137.916
B5: 其中：销售收入 | C5: =SUM(D5:W5) -> 115945.07 | D5: ='3.1销售情况分析'!G6 -> 0 | E5: ='3.1销售情况分析'!H6 -> 0 | F5: ='3.1销售情况分析'!I6 -> 0 | G5: ='3.1销售情况分析'!J6 -> 23989.014 | H5: ='3.1销售情况分析'!K6 -> 9345.6058 | I5: ='3.1销售情况分析'!L6 -> 9345.6058 | J5: ='3.1销售情况分析'!M6 -> 12943.958 | K5: ='3.1销售情况分析'!N6 -> 6946.7043 | ... W5: ='3.1销售情况分析'!Z6 -> 26137.916
A6: 1.2 | B6: 土地款返还收入 | C6: =SUM(D6:W6) -> 0 | D6: ='3.2 营业收入汇总表'!D9 -> 0 | E6: ='3.2 营业收入汇总表'!E9 -> 0 | F6: ='3.2 营业收入汇总表'!F9 -> 0 | G6: ='3.2 营业收入汇总表'!G9 -> 0 | H6: ='3.2 营业收入汇总表'!H9 -> 0 | I6: ='3.2 营业收入汇总表'!I9 -> 0 | J6: ='3.2 营业收入汇总表'!J9 -> 0 | K6: ='3.2 营业收入汇总表'!K9 -> 0 | ... W6: ='3.2 营业收入汇总表'!W9 -> 0
A8: 点击返回目录
B9: 项目基础数据
B10: 规划数据 | C10: 数据值 | D10: 备 注
B11: 总用地面积（m²） | C11: 23384.4 | D11: 约35.1亩
B12: 总建筑面积（m²） | C12: 134746.85
B13: 计容建筑面积（m²） | C13: 104467.85
B14: 其中：住宅（m²） | C14: 86949.32
B15: 商业（m²） | C15: 16178.53
B16: 地下建筑面积（m²） | C16: 30279
B17: 其中：车位（个） | C17: 796
B18: 可售物业 | C18: 数 量 | D18: 备 注
B19: 车位（个） | C19: 736 | D19: 共796个，返村60个
B20: 商业（m²） | C20: 6178.53 | D20: 共16178.53平方，返村10000平方
B21: 住宅（m²） | C21: 86949.32
B24: 收入测算
B25: 项 目 | C25: 总物业 | D25: 减返村物业 | E25: 可售物业 | F25: 单 价（元/平米） | G25: 销售收入
B26: 车位（个） | C26: 796 | D26: 60 | E26: 736 | F26: 120000 | G26: =E26*F26 -> 88320000
B27: 商业（m²） | C27: 16178.53 | D27: 10000 | E27: 6178.53 | F27: 20000 | G27: =E27*F27 -> 123570600
B28: 住宅（m²） | C28: 86949.32 | D28: 0 | E28: 86949.32 | F28: 13000 | G28: =E28*F28 -> 1130341160
B29: 合 计 | G29: =SUM(G26:G28) -> 1342231760
B32: 成本测算
B33: 明细项目 | C33: 计算基数 | D33: 单位成本 | E33: 预算总成本（元） | F33: 计算依据
B34: 一、土地费用 | C34: 104467.85 | D34: =E34/C34 -> 5727.4094 | E34: =SUM(E35:E38) -> 598330150 | F34: 1+2+3
B35: 1、土地出让金 | E35: 527700000 | F35: 挂牌起始价52770万
B36: 2、契税 | E36: =E35*0.04 -> 21108000 | F36: 土地出让金的4% | G36: 请提供明细和税率
B37: 3、印花税 | E37: =E35*0.0005 -> 263850 | F37: 土地出让金的0.05%
B38: 4、教育配套费 | E38: 49258300
B39: 二、前期费用 | E39: 31192548 | F39: 4+5 | G39: 请确认
B40: 4、报批报建 | E40: 28497611
B41: 5、规划设计 | E41: 2694937 | F41: 参考同行项目
B42: 三、建安和基础设施配套 | C42: 134746.85 | D42: 3000 | E42: =C42*D42 -> 404240550 | G42: 请提供明细
B46: 四、管理费用 | D46: 0.005 | E46: =G10*0.005 -> 0 | F46: 按总销售收入的0.5%测算
B47: 1、工资 | G47: 请提供明细
B48: 2、其他
B49: 五、财务费用 | E49: =SUM(E50:E53) -> 121500000
B50: 1、信保基金 | C50: 400000000 | D50: 0.15 | E50: =C50*D50*1.5 -> 90000000 | F50: 平均用款1.5年
B51: 2、五江 | C51: 150000000 | F51: 资金成本是否需项目负担？
B52: 3、中信金资 | C52: 150000000 | D52: 0.07 | E52: =C52*D52*3 -> 31500000
B53: 4、其他
B54: 六、销售费用 | D54: 0.035 | E54: =G10*D54 -> 0 | F54: 贝壳代销
B55: 七、代建费用 | D55: 0.015 | E55: =G10*D55 -> 0
B56: 八、税费 | D56: 0.1 | E56: =G10*0.1 -> 0 | F56: 按总销售收入的10%测算 | G56: 请提供明细和税率
B61: 合 计 | E61: =SUM(E34,E39,E42,E46,E49,E54,E55,E56) -> 1.1552632e+09
B64: 收益测算 | C64: 元
B65: 销售收入 | C65: =G10 -> 0 | F65: 5.5
B66: 减：返还村里销售收入（优先） | C66: 40000000
B67: 减：项目成本 | C67: =E61 -> 1.1552632e+09
B68: 开发经营净收益 | C68: =C65-C66-C67 -> -1.1952632e+09
B69: 土地返还款-全额 | C69: =E35*0.8 -> 422160000
B70: 减：返还村里 | C70: 100000000
B71: 土地返还净收益 | C71: =C69-C70 -> 322160000
B72: 净收益合计 | C72: =C68+C71 -> -8.7310325e+08

Sheet 3.1销售情况分析
B1: 附表3.1 销售收入-汇总（万元）
B2: 序号 | C2: 项目 | D2: 备注 | E2: 收入占比 | F2: 合计 | G2: 第1年Q1 | H2: 第1年Q2 | I2: 第1年Q3 | J2: 第1年Q4 | K2: 第2年Q1 | L2: 第2年Q2 | M2: 第2年Q3 | N2: 第2年Q4 | O2: 第3年Q1 | P2: 第3年Q2 | Q2: 第3年Q3 | R2: 第3年Q4 | S2: 第4年Q1 | T2: 第4年Q2 | U2: 第4年Q3 | V2: 第4年Q4 | W2: 第5年Q1 | X2: 第5年Q2 | Y2: 第5年Q3 | Z2: 第5年Q4
B3: 1 | C3: 含税销售收入合计 | F3: =SUM(G3:Z3) -> 115945.07 | G3: =SUM(G6) -> 0 | H3: =SUM(H6) -> 0 | I3: =SUM(I6) -> 0 | J3: =SUM(J6) -> 23989.014 | K3: =SUM(K6) -> 9345.6058 | L3: =SUM(L6) -> 9345.6058 | M3: =SUM(M6) -> 12943.958 | N3: =SUM(N6) -> 6946.7043 | ... Z3: =SUM(Z6) -> 26137.916
B4: 2 | C4: 税金及附加 | F4: =SUM(G4:Z4) -> 921.96832 | G4: =G33+G34+'附表4 税金及附加表'!F6 -> 0 | H4: =H33+H34+'附表4 税金及附加表'!G6 -> 0 | I4: =I33+I34+'附表4 税金及附加表'!H6 -> 0 | J4: =J33+J34+'附表4 税金及附加表'!I6 -> 0 | K4: =K33+K34+'附表4 税金及附加表'!J6 -> 0 | L4: =L33+L34+'附表4 税金及附加表'!K6 -> 0 | M4: =M33+M34+'附表4 税金及附加表'!L6 -> 0 | N4: =N33+N34+'附表4 税金及附加表'!M6 -> 0 | ... Z4: =Z33+Z34+'附表4 税金及附加表'!Y6 -> 921.96832
B5: 3 | C5: 不含税收入 | F5: =SUM(G5:Z5) -> 115023.1 | G5: =G3-G4 -> 0 | H5: =H3-H4 -> 0 | I5: =I3-I4 -> 0 | J5: =J3-J4 -> 23989.014 | K5: =K3-K4 -> 9345.6058 | L5: =L3-L4 -> 9345.6058 | M5: =M3-M4 -> 12943.958 | N5: =N3-N4 -> 6946.7043 | ... Z5: =Z3-Z4 -> 25215.948
B6: 3.1 | C6: 销售收入（缺口承担后） | F6: =SUM(G6:Z6) -> 115945.07 | G6: =SUM(G7:G9) -> 0 | H6: =SUM(H7:H9) -> 0 | I6: =SUM(I7:I9) -> 0 | J6: =SUM(J7:J9) -> 23989.014 | K6: =SUM(K7:K9) -> 9345.6058 | L6: =SUM(L7:L9) -> 9345.6058 | M6: =SUM(M7:M9) -> 12943.958 | N6: =SUM(N7:N9) -> 6946.7043 | ... P6: =SUM(P7:P9) -> 3348.3522 | Q6: =SUM(Q7:Q9)+Q10 -> 2148.9014 | R6: =SUM(R7:R9)+R10 -> 2148.9014 | S6: =SUM(S7:S9)+S10 -> 2148.9014 | T6: =SUM(T7:T9)+T10 -> 2148.9014 | U6: =SUM(U7:U9)+U10 -> 2148.9014 | V6: =SUM(V7:V9)+V10 -> 2148.9014 | W6: =SUM(W7:W9)+W10 -> 2148.9014 | X6: =SUM(X7:X9)+X10 -> 2148.9014 | ... Z6: =SUM(Z7:Z9)+Z10 -> 26137.916
B8: 3.1.1 | C8: 五江项目 | F8: =SUM(G8:Z8) -> 115945.07 | G8: =SUM(G79:G81) -> 0 | H8: =SUM(H79:H81) -> 0 | I8: =SUM(I79:I81) -> 0 | J8: =SUM(J79:J81) -> 23989.014 | K8: =SUM(K79:K81) -> 9345.6058 | L8: =SUM(L79:L81) -> 9345.6058 | M8: =SUM(M79:M81) -> 12943.958 | N8: =SUM(N79:N81) -> 6946.7043 | ... Z8: =SUM(Z79:Z81) -> 26137.916
F9: =SUM(G9:Z9) -> 0
B10: 3.1.2 | C10: 土地款返还收入 | F10: =SUM(G10:Z10) -> 0
C11: 真实经营性收入
B13: 附表3.2 增值税及附加测算（万元）
B14: 序号 | C14: 项目 | D14: 税率 | E14: 合计 | F14: 合计 | G14: 第1年Q1 | H14: 第1年Q2 | I14: 第1年Q3 | J14: 第1年Q4 | K14: 第2年Q3 | L14: 第2年Q4 | M14: 第3年Q1 | N14: 第3年Q2 | O14: 第3年Q3 | P14: 第3年Q4 | Q14: 第4年Q1 | R14: 第4年Q2 | S14: 第4年Q3 | T14: 第4年Q4 | U14: 第6年Q3 | V14: 第6年Q4 | W14: 第7年Q1 | X14: 第7年Q2 | Y14: 第7年Q3 | Z14: 第7年Q4
B15: 1 | C15: 项目公司营业收入 | E15: =SUM(G15:AD15) -> 115945.07 | F15: =SUM(G15:Z15) -> 115945.07 | G15: =G16+G19 -> 0 | H15: =H16+H19 -> 0 | I15: =I16+I19 -> 0 | J15: =J16+J19 -> 23989.014 | K15: =K16+K19 -> 9345.6058 | L15: =L16+L19 -> 9345.6058 | M15: =M16+M19 -> 12943.958 | N15: =N16+N19 -> 6946.7043 | ... Z15: =Z16+Z19 -> 26137.916
B16: 1.1 | C16: 销售收入 | E16: =SUM(G16:AD16) -> 115945.07 | F16: =SUM(G16:Z16) -> 115945.07 | G16: =G6 -> 0 | H16: =H6 -> 0 | I16: =I6 -> 0 | J16: =J6 -> 23989.014 | K16: =K6 -> 9345.6058 | L16: =L6 -> 9345.6058 | M16: =M6 -> 12943.958 | N16: =N6 -> 6946.7043 | ... Z16: =Z6 -> 26137.916
B17: 1.1.1 | C17: 物业管理费 | E17: =SUM(G17:AD17) -> 0 | F17: =SUM(G17:Z17) -> 0 | G17: 0 | H17: 0 | I17: 0 | P17: 0 | Q17: 0 | R17: 0 | S17: 0 | T17: 0 | W17: 0 | X17: 0 | Y17: 0 | Z17: 0
B18: 1.1.2 | C18: 其他合计 | E18: =SUM(G18:AD18) -> 0 | F18: =SUM(G18:Z18) -> 0 | G18: 0 | H18: 0 | I18: 0 | P18: 0 | Q18: 0 | R18: 0 | S18: 0 | T18: 0 | W18: 0 | X18: 0 | Y18: 0 | Z18: 0
B19: 1.2 | C19: 土地款返还收入 | E19: =SUM(G19:AD19) -> 0 | F19: =SUM(G19:Z19) -> 0 | G19: =G10 -> 0 | H19: =H10 -> 0 | I19: =I10 -> 0 | J19: =J10 -> 0 | K19: =K10 -> 0 | L19: =L10 -> 0 | M19: =M10 -> 0 | N19: =N10 -> 0 | ... Z19: =Z10 -> 0
B20: 2 | C20: 增值税-销项税额 | E20: =SUM(G20:AD20) -> 9573.4463 | F20: =SUM(G20:Z20) -> 9573.4463 | G20: =G21+G24 -> 0 | H20: =H21+H24 -> 0 | I20: =I21+I24 -> 0 | J20: =J21+J24 -> 1980.7443 | K20: =K21+K24 -> 771.65552 | L20: =L21+L24 -> 771.65552 | M20: =M21+M24 -> 1068.7672 | N20: =N21+N24 -> 573.58109 | ... Z20: =Z21+Z24 -> 2158.1765
B21: 2.1 | C21: 销售收入 | D21: 0.09 | E21: =SUM(G21:AD21) -> 9573.4463 | F21: =SUM(G21:Z21) -> 9573.4463 | G21: =G16/(1+$D$21)*$D$21 -> 0 | H21: =H16/(1+$D$21)*$D$21 -> 0 | I21: =I16/(1+$D$21)*$D$21 -> 0 | J21: =J16/(1+$D$21)*$D$21 -> 1980.7443 | K21: =K16/(1+$D$21)*$D$21 -> 771.65552 | L21: =L16/(1+$D$21)*$D$21 -> 771.65552 | M21: =M16/(1+$D$21)*$D$21 -> 1068.7672 | N21: =N16/(1+$D$21)*$D$21 -> 573.58109 | ... Z21: =Z16/(1+$D$21)*$D$21 -> 2158.1765
B22: 2.1.1 | C22: 物业管理费 | E22: =SUM(G22:AD22) -> #REF! | F22: =SUM(G22:Z22) -> #REF! | G22: =G17/(1+#REF!)*#REF! -> #REF! | H22: =H17/(1+#REF!)*#REF! -> #REF! | I22: =I17/(1+#REF!)*#REF! -> #REF! | P22: =P17/(1+#REF!)*#REF! -> #REF! | Q22: =Q17/(1+#REF!)*#REF! -> #REF! | R22: =R17/(1+#REF!)*#REF! -> #REF! | S22: =S17/(1+#REF!)*#REF! -> #REF! | T22: =T17/(1+#REF!)*#REF! -> #REF! | W22: =W17/(1+#REF!)*#REF! -> #REF! | X22: =X17/(1+#REF!)*#REF! -> #REF! | Y22: =Y17/(1+#REF!)*#REF! -> #REF! | Z22: =Z17/(1+#REF!)*#REF! -> #REF!
B23: 2.1.2 | C23: 其他合计 | E23: =SUM(G23:AD23) -> #REF! | F23: =SUM(G23:Z23) -> #REF! | G23: =G18/(1+#REF!)*#REF! -> #REF! | H23: =H18/(1+#REF!)*#REF! -> #REF! | I23: =I18/(1+#REF!)*#REF! -> #REF! | P23: =P18/(1+#REF!)*#REF! -> #REF! | Q23: =Q18/(1+#REF!)*#REF! -> #REF! | R23: =R18/(1+#REF!)*#REF! -> #REF! | S23: =S18/(1+#REF!)*#REF! -> #REF! | T23: =T18/(1+#REF!)*#REF! -> #REF! | W23: =W18/(1+#REF!)*#REF! -> #REF! | X23: =X18/(1+#REF!)*#REF! -> #REF! | Y23: =Y18/(1+#REF!)*#REF! -> #REF! | Z23: =Z18/(1+#REF!)*#REF! -> #REF!
B24: 2.2 | C24: 土地款返还收入 | E24: =SUM(G24:AD24) -> 0 | F24: =SUM(G24:Z24) -> 0 | G24: =G19/(1+$D$24)*$D$24 -> 0 | H24: =H19/(1+$D$24)*$D$24 -> 0 | I24: =I19/(1+$D$24)*$D$24 -> 0 | J24: =J19/(1+$D$24)*$D$24 -> 0 | K24: =K19/(1+$D$24)*$D$24 -> 0 | L24: =L19/(1+$D$24)*$D$24 -> 0 | M24: =M19/(1+$D$24)*$D$24 -> 0 | N24: =N19/(1+$D$24)*$D$24 -> 0 | ... Z24: =Z19/(1+$D$24)*$D$24 -> 0
B25: 3 | C25: 增值税-进项税额 | E25: =SUM(G25:AD25) -> 8735.2933 | F25: =SUM(G25:Z25) -> 8735.2933 | G25: =G26+G27+G28+G29 -> 4940.2722 | H25: =H26+H27+H28+H29 -> 721.94119 | I25: =I26+I27+I28+I29 -> 360.9706 | J25: =J26+J27+J28+J29 -> 360.9706 | K25: =K26+K27+K28+K29 -> 360.9706 | L25: =L26+L27+L28+L29 -> 360.9706 | M25: =M26+M27+M28+M29 -> 360.9706 | N25: =N26+N27+N28+N29 -> 360.9706 | ... Z25: =Z26+Z27+Z28+Z29 -> 79.635611
B26: 3.1 | C26: 工程建设 | D26: 0.09 | E26: =SUM(G26:Q26) -> 3352.0913 | F26: =SUM(G26:Z26) -> 3352.0913 | G26: ='附表2 投资计划与资金筹措平衡表 '!D6*'3.1销售情况分析'!$D$26/(1+'3.1销售情况分析'!$D$26) -> 0 | H26: ='附表2 投资计划与资金筹措平衡表 '!E6*'3.1销售情况分析'!$D$26/(1+'3.1销售情况分析'!$D$26) -> 670.41826 | I26: ='附表2 投资计划与资金筹措平衡表 '!F6*'3.1销售情况分析'!$D$26/(1+'3.1销售情况分析'!$D$26) -> 335.20913 | J26: ='附表2 投资计划与资金筹措平衡表 '!G6*'3.1销售情况分析'!$D$26/(1+'3.1销售情况分析'!$D$26) -> 335.20913 | K26: ='附表2 投资计划与资金筹措平衡表 '!H6*'3.1销售情况分析'!$D$26/(1+'3.1销售情况分析'!$D$26) -> 335.20913 | L26: ='附表2 投资计划与资金筹措平衡表 '!I6*'3.1销售情况分析'!$D$26/(1+'3.1销售情况分析'!$D$26) -> 335.20913 | M26: ='附表2 投资计划与资金筹措平衡表 '!J6*'3.1销售情况分析'!$D$26/(1+'3.1销售情况分析'!$D$26) -> 335.20913 | N26: ='附表2 投资计划与资金筹措平衡表 '!K6*'3.1销售情况分析'!$D$26/(1+'3.1销售情况分析'!$D$26) -> 335.20913 | ... P26: ='附表2 投资计划与资金筹措平衡表 '!M6*'3.1销售情况分析'!$D$26/(1+'3.1销售情况分析'!$D$26) -> 335.20913
B27: 3.2 | C27: 工程建设其他费用 | D27: 0.09 | E27: =SUM(G27:Q27) -> 5197.8868 | F27: =SUM(G27:Z27) -> 5197.8868 | G27: ='附表2 投资计划与资金筹措平衡表 '!D7*'3.1销售情况分析'!$D$27/(1+'3.1销售情况分析'!$D$27) -> 4940.2722 | H27: ='附表2 投资计划与资金筹措平衡表 '!E7*'3.1销售情况分析'!$D$27/(1+'3.1销售情况分析'!$D$27) -> 51.522936 | I27: ='附表2 投资计划与资金筹措平衡表 '!F7*'3.1销售情况分析'!$D$27/(1+'3.1销售情况分析'!$D$27) -> 25.761468 | J27: ='附表2 投资计划与资金筹措平衡表 '!G7*'3.1销售情况分析'!$D$27/(1+'3.1销售情况分析'!$D$27) -> 25.761468 | K27: ='附表2 投资计划与资金筹措平衡表 '!H7*'3.1销售情况分析'!$D$27/(1+'3.1销售情况分析'!$D$27) -> 25.761468 | L27: ='附表2 投资计划与资金筹措平衡表 '!I7*'3.1销售情况分析'!$D$27/(1+'3.1销售情况分析'!$D$27) -> 25.761468 | M27: ='附表2 投资计划与资金筹措平衡表 '!J7*'3.1销售情况分析'!$D$27/(1+'3.1销售情况分析'!$D$27) -> 25.761468 | N27: ='附表2 投资计划与资金筹措平衡表 '!K7*'3.1销售情况分析'!$D$27/(1+'3.1销售情况分析'!$D$27) -> 25.761468 | ... P27: ='附表2 投资计划与资金筹措平衡表 '!M7*'3.1销售情况分析'!$D$27/(1+'3.1销售情况分析'!$D$27) -> 25.761468 | T27: ='附表2 投资计划与资金筹措平衡表 '!Q7*'3.1销售情况分析'!$D$27/(1+'3.1销售情况分析'!$D$27) -> 0 | U27: ='附表2 投资计划与资金筹措平衡表 '!X7*'3.1销售情况分析'!$D$27/(1+'3.1销售情况分析'!$D$27) -> 0 | V27: ='附表2 投资计划与资金筹措平衡表 '!Y7*'3.1销售情况分析'!$D$27/(1+'3.1销售情况分析'!$D$27) -> 0 | W27: ='附表2 投资计划与资金筹措平衡表 '!Z7*'3.1销售情况分析'!$D$27/(1+'3.1销售情况分析'!$D$27) -> 0 | X27: ='附表2 投资计划与资金筹措平衡表 '!AA7*'3.1销售情况分析'!$D$27/(1+'3.1销售情况分析'!$D$27) -> 0 | Y27: ='附表2 投资计划与资金筹措平衡表 '!AB7*'3.1销售情况分析'!$D$27/(1+'3.1销售情况分析'!$D$27) -> 0 | Z27: ='附表2 投资计划与资金筹措平衡表 '!AC7*'3.1销售情况分析'!$D$27/(1+'3.1销售情况分析'!$D$27) -> 0
B28: 3.3 | C28: 预备费 | D28: 0.06 | E28: =SUM(G28:Q28) -> 0 | F28: =SUM(G28:Z28) -> 0
B29: 3.4 | C29: 运维经营成本进项税 | D29: 0.06 | E29: =SUM(G29:AD29) -> 185.31518 | F29: =SUM(G29:Z29) -> 185.31518 | Q29: ='5.1运营成本明细表'!Q3/(1+'3.1销售情况分析'!$D$29)*'3.1销售情况分析'!$D$29 -> 11.742174 | R29: ='5.1运营成本明细表'!R3/(1+'3.1销售情况分析'!$D$29)*'3.1销售情况分析'!$D$29 -> 11.742174 | S29: ='5.1运营成本明细表'!S3/(1+'3.1销售情况分析'!$D$29)*'3.1销售情况分析'!$D$29 -> 11.742174 | T29: ='5.1运营成本明细表'!T3/(1+'3.1销售情况分析'!$D$29)*'3.1销售情况分析'!$D$29 -> 11.742174 | U29: ='5.1运营成本明细表'!U3/(1+'3.1销售情况分析'!$D$29)*'3.1销售情况分析'!$D$29 -> 11.742174 | V29: ='5.1运营成本明细表'!V3/(1+'3.1销售情况分析'!$D$29)*'3.1销售情况分析'!$D$29 -> 11.742174 | W29: ='5.1运营成本明细表'!W3/(1+'3.1销售情况分析'!$D$29)*'3.1销售情况分析'!$D$29 -> 11.742174 | X29: ='5.1运营成本明细表'!X3/(1+'3.1销售情况分析'!$D$29)*'3.1销售情况分析'!$D$29 -> 11.742174 | ... Z29: ='5.1运营成本明细表'!Z3/(1+'3.1销售情况分析'!$D$29)*'3.1销售情况分析'!$D$29 -> 79.635611
B30: 4 | C30: 当期留抵进项税额 | E30: =SUM(G30:AD30) -> 6107.6851 | F30: =SUM(G30:Z30) -> 6107.6851 | G30: =IF(G25>G20,G25-G20,0) -> 4940.2722 | H30: =IF(H25>H20,H25-H20,0) -> 721.94119 | I30: =IF(I25>I20,I25-I20,0) -> 360.9706 | J30: =IF(J25>J20,J25-J20,0) -> 0 | K30: =IF(K25>K20,K25-K20,0) -> 0 | L30: =IF(L25>L20,L25-L20,0) -> 0 | M30: =IF(M25>M20,M25-M20,0) -> 0 | N30: =IF(N25>N20,N25-N20,0) -> 0 | ... Z30: =IF(Z25>Z20,Z25-Z20,0) -> 0
B31: 5 | C31: 前期留抵进项税抵扣当期销项税额 | E31: =SUM(G31:AD31) -> 6107.6851 | F31: =SUM(G31:Z31) -> 6107.6851 | J31: =IF(AND(I32>0,J30=0),IF(I32>ABS(J20-J25),ABS(J25-J20),I32),0) -> 1619.7737 | K31: =IF(AND(J32>0,K30=0),IF(J32>ABS(K20-K25),ABS(K25-K20),J32),0) -> 410.68493 | L31: =IF(AND(K32>0,L30=0),IF(K32>ABS(L20-L25),ABS(L25-L20),K32),0) -> 410.68493 | M31: =IF(AND(L32>0,M30=0),IF(L32>ABS(M20-M25),ABS(M25-M20),L32),0) -> 707.79657 | N31: =IF(AND(M32>0,N30=0),IF(M32>ABS(N20-N25),ABS(N25-N20),M32),0) -> 212.61049 | O31: =IF(AND(N32>0,O30=0),IF(N32>ABS(O20-O25),ABS(O25-O20),N32),0) -> 14.536063 | P31: =IF(AND(O32>0,P30=0),IF(O32>ABS(P20-P25),ABS(P25-P20),O32),0) -> 0 | Q31: =IF(AND(P32>0,Q30=0),IF(P32>ABS(Q20-Q25),ABS(Q25-Q20),P32),0) -> 165.69006 | ... Z31: =IF(AND(Y32>0,Z30=0),IF(Y32>ABS(Z20-Z25),ABS(Z25-Z20),Y32),0) -> 1240.3879
B32: 6 | C32: 剩余留抵进项税额 | E32: =SUM(G32:AD32) -> 56646.751 | G32: =G30 -> 4940.2722 | H32: =G32+H30-H31 -> 5662.2133 | I32: =H32+I30-I31 -> 6023.1839 | J32: =I32+J30-J31 -> 4403.4102 | K32: =J32+K30-K31 -> 3992.7253 | L32: =K32+L30-L31 -> 3582.0404 | M32: =L32+M30-M31 -> 2874.2438 | N32: =M32+N30-N31 -> 2661.6333 | O32: =N32+O30-O31 -> 2647.0973 | ... Z32: =Y32+Z30-Z31 -> 0
B33: 7 | C33: 当期缴纳增值税 | E33: =SUM(G33:AD33) -> 838.15302 | F33: =SUM(G33:Z33) -> 838.15302 | G33: =IF(G30>0,0,G20-G25-G31) -> 0 | H33: =IF(H30>0,0,H20-H25-H31) -> 0 | I33: =IF(I30>0,0,I20-I25-I31) -> 0 | J33: =IF(J30>0,0,J20-J25-J31) -> 0 | K33: =IF(K30>0,0,K20-K25-K31) -> 0 | L33: =IF(L30>0,0,L20-L25-L31) -> 0 | M33: =IF(M30>0,0,M20-M25-M31) -> 0 | N33: =IF(N30>0,0,N20-N25-N31) -> 0 | ... Z33: =IF(Z30>0,0,Z20-Z25-Z31) -> 838.15302
B34: 8 | C34: 增值税附加 | E34: =SUM(G34:AD34) -> 83.815302 | F34: =SUM(G34:Z34) -> 83.815302 | G34: =G35+G36 -> 0 | H34: =H35+H36 -> 0 | I34: =I35+I36 -> 0 | J34: =J35+J36 -> 0 | K34: =K35+K36 -> 0 | L34: =L35+L36 -> 0 | M34: =M35+M36 -> 0 | N34: =N35+N36 -> 0 | ... Z34: =Z35+Z36 -> 83.815302
B35: 8.1 | C35: 城建税 | D35: 0.07 | E35: =SUM(G35:AD35) -> 58.670711 | F35: =SUM(G35:Z35) -> 58.670711 | G35: =G34*$D$35 -> 0 | H35: =H33*$D$35 -> 0 | I35: =I33*$D$35 -> 0 | J35: =J33*$D$35 -> 0 | K35: =K33*$D$35 -> 0 | L35: =L33*$D$35 -> 0 | M35: =M33*$D$35 -> 0 | N35: =N33*$D$35 -> 0 | O35: =O33*$D$35 -> 0 | ... Z35: =Z33*$D$35 -> 58.670711
B36: 8.2 | C36: 教育附加费 | D36: 0.03 | E36: =SUM(G36:AD36) -> 25.144591 | F36: =SUM(G36:Z36) -> 25.144591 | G36: 0 | H36: =H33*$D$36 -> 0 | I36: =I33*$D$36 -> 0 | J36: =J33*$D$36 -> 0 | K36: =K33*$D$36 -> 0 | L36: =L33*$D$36 -> 0 | M36: =M33*$D$36 -> 0 | N36: =N33*$D$36 -> 0 | O36: =O33*$D$36 -> 0 | ... Z36: =Z33*$D$36 -> 25.144591
B38: 序号 | C38: 项目 | D38: 备注 | E38: 收入占比 | F38: 合计 | G38: 第1年Q1 | H38: 第1年Q2 | I38: 第1年Q3 | J38: 第1年Q4 | K38: 第2年Q3 | L38: 第2年Q4 | M38: 第3年Q1 | N38: 第3年Q2 | O38: 第3年Q3 | P38: 第3年Q4 | Q38: 第4年Q1 | R38: 第4年Q2 | S38: 第4年Q3 | T38: 第4年Q4 | U38: 第6年Q3 | V38: 第6年Q4 | W38: 第7年Q1 | X38: 第7年Q2 | Y38: 第7年Q3 | Z38: 第7年Q4
B39: 1 | C39: 销售百分比 | F39: =SUM(G39:Z39) -> 1 | G39: ='3.1销售情况分析'!G42/'3.1销售情况分析'!$F$42 -> 0 | H39: ='3.1销售情况分析'!H42/'3.1销售情况分析'!$F$42 -> 0 | I39: ='3.1销售情况分析'!I42/'3.1销售情况分析'!$F$42 -> 0 | J39: ='3.1销售情况分析'!J42/'3.1销售情况分析'!$F$42 -> 0.20689982 | K39: ='3.1销售情况分析'!K42/'3.1销售情况分析'!$F$42 -> 0.080603734 | L39: ='3.1销售情况分析'!L42/'3.1销售情况分析'!$F$42 -> 0.080603734 | M39: ='3.1销售情况分析'!M42/'3.1销售情况分析'!$F$42 -> 0.11163871 | N39: ='3.1销售情况分析'!N42/'3.1销售情况分析'!$F$42 -> 0.059913752 | ... Z39: ='3.1销售情况分析'!Z42/'3.1销售情况分析'!$F$42 -> 0.22543361
B40: 附表3.3 土增税（万元）
B41: 序号 | C41: 项目 | D41: 备注 | E41: 合计 | F41: 合计 | G41: 第1年Q1 | H41: 第1年Q2 | I41: 第1年Q3 | J41: 第1年Q4 | K41: 第2年Q3 | L41: 第2年Q4 | M41: 第3年Q1 | N41: 第3年Q2 | O41: 第3年Q3 | P41: 第3年Q4 | Q41: 第4年Q1 | R41: 第4年Q2 | S41: 第4年Q3 | T41: 第4年Q4 | U41: 第6年Q3 | V41: 第6年Q4 | W41: 第7年Q1 | X41: 第7年Q2 | Y41: 第7年Q3 | Z41: 第7年Q4
B42: 1 | C42: 营业收入合计（不含税） | E42: =SUM(G42:Z42) -> 106371.63 | F42: =SUM(G42:Z42) -> 106371.63 | G42: =G43+G44 -> 0 | H42: =H43+H44 -> 0 | I42: =I43+I44 -> 0 | J42: =J43+J44 -> 22008.27 | K42: =K43+K44 -> 8573.9502 | L42: =L43+L44 -> 8573.9502 | M42: =M43+M44 -> 11875.191 | N42: =N43+N44 -> 6373.1232 | ... Z42: =Z43+Z44 -> 23979.739
B43: 1.1 | C43: 销售收入（不含税） | D43: 不含税 | E43: =SUM(G43:Z43) -> 106371.63 | F43: =SUM(G43:Z43) -> 106371.63 | G43: ='3.1销售情况分析'!G16-'3.1销售情况分析'!G21 -> 0 | H43: ='3.1销售情况分析'!H16-'3.1销售情况分析'!H21 -> 0 | I43: ='3.1销售情况分析'!I16-'3.1销售情况分析'!I21 -> 0 | J43: ='3.1销售情况分析'!J16-'3.1销售情况分析'!J21 -> 22008.27 | K43: ='3.1销售情况分析'!K16-'3.1销售情况分析'!K21 -> 8573.9502 | L43: ='3.1销售情况分析'!L16-'3.1销售情况分析'!L21 -> 8573.9502 | M43: ='3.1销售情况分析'!M16-'3.1销售情况分析'!M21 -> 11875.191 | N43: ='3.1销售情况分析'!N16-'3.1销售情况分析'!N21 -> 6373.1232 | ... Z43: ='3.1销售情况分析'!Z16-'3.1销售情况分析'!Z21 -> 23979.739
B44: 1.2 | C44: 土地款返还收入（不含税） | D44: 不含税 | E44: =SUM(G44:Z44) -> 0 | F44: =SUM(G44:Z44) -> 0 | G44: ='3.1销售情况分析'!G19-'3.1销售情况分析'!G24 -> 0 | H44: ='3.1销售情况分析'!H19-'3.1销售情况分析'!H24 -> 0 | I44: ='3.1销售情况分析'!I19-'3.1销售情况分析'!I24 -> 0 | J44: ='3.1销售情况分析'!J19-'3.1销售情况分析'!J24 -> 0 | K44: ='3.1销售情况分析'!K19-'3.1销售情况分析'!K24 -> 0 | L44: ='3.1销售情况分析'!L19-'3.1销售情况分析'!L24 -> 0 | M44: ='3.1销售情况分析'!M19-'3.1销售情况分析'!M24 -> 0 | N44: ='3.1销售情况分析'!N19-'3.1销售情况分析'!N24 -> 0 | ... Z44: ='3.1销售情况分析'!Z19-'3.1销售情况分析'!Z24 -> 0
B45: 2 | C45: 扣除金额（成本-不含税） | D45: 不含税 | E45: =SUM(G45:Z45) -> 127441.95 | F45: =SUM(G45:Z45) -> 127441.95 | G45: =SUM(G46:G49) -> 0 | H45: =SUM(H46:H49) -> 94.339623 | I45: =SUM(I46:I49) -> 94.339623 | J45: =SUM(J46:J49) -> 25328.313 | K45: =SUM(K46:K49) -> 9924.9548 | L45: =SUM(L46:L49) -> 9924.9548 | M45: =SUM(M46:M49) -> 13710.051 | N45: =SUM(N46:N49) -> 7401.5574 | ... Z45: =SUM(Z46:Z49) -> 27658.793
B46: 2.1 | C46: 土地成本 | D46: 不含税 | E46: =SUM(G46:Z46) -> 59832.185 | F46: =SUM(G46:Z46) -> 59832.185 | G46: =('附表1.1 总投资估算（明细）'!$H$39+'附表1.1 总投资估算（明细）'!$H$40+'附表1.1 总投资估算（明细）'!$H$41+'附表1.1 总投资估算（明细）'!$H$42)*'3.1销售情况分析'!G39 -> 0 | H46: =('附表1.1 总投资估算（明细）'!$H$39+'附表1.1 总投资估算（明细）'!$H$40+'附表1.1 总投资估算（明细）'!$H$41+'附表1.1 总投资估算（明细）'!$H$42)*'3.1销售情况分析'!H39 -> 0 | I46: =('附表1.1 总投资估算（明细）'!$H$39+'附表1.1 总投资估算（明细）'!$H$40+'附表1.1 总投资估算（明细）'!$H$41+'附表1.1 总投资估算（明细）'!$H$42)*'3.1销售情况分析'!I39 -> 0 | J46: =('附表1.1 总投资估算（明细）'!$H$39+'附表1.1 总投资估算（明细）'!$H$40+'附表1.1 总投资估算（明细）'!$H$41+'附表1.1 总投资估算（明细）'!$H$42)*'3.1销售情况分析'!J39 -> 12379.268 | K46: =('附表1.1 总投资估算（明细）'!$H$39+'附表1.1 总投资估算（明细）'!$H$40+'附表1.1 总投资估算（明细）'!$H$41+'附表1.1 总投资估算（明细）'!$H$42)*'3.1销售情况分析'!K39 -> 4822.6975 | L46: =('附表1.1 总投资估算（明细）'!$H$39+'附表1.1 总投资估算（明细）'!$H$40+'附表1.1 总投资估算（明细）'!$H$41+'附表1.1 总投资估算（明细）'!$H$42)*'3.1销售情况分析'!L39 -> 4822.6975 | M46: =('附表1.1 总投资估算（明细）'!$H$39+'附表1.1 总投资估算（明细）'!$H$40+'附表1.1 总投资估算（明细）'!$H$41+'附表1.1 总投资估算（明细）'!$H$42)*'3.1销售情况分析'!M39 -> 6679.5878 | N46: =('附表1.1 总投资估算（明细）'!$H$39+'附表1.1 总投资估算（明细）'!$H$40+'附表1.1 总投资估算（明细）'!$H$41+'附表1.1 总投资估算（明细）'!$H$42)*'3.1销售情况分析'!N39 -> 3584.7707 | ... Z46: =('附表1.1 总投资估算（明细）'!$H$39+'附表1.1 总投资估算（明细）'!$H$40+'附表1.1 总投资估算（明细）'!$H$41+'附表1.1 总投资估算（明细）'!$H$42)*'3.1销售情况分析'!Z39 -> 13488.185
B47: 2.2 | C47: 工程成本 | D47: 不含税 | E47: =SUM(G47:Z47) -> 37245.459 | F47: =SUM(G47:Z47) -> 37245.459 | G47: ='附表2 投资计划与资金筹措平衡表 '!$O$6/(1+'3.1销售情况分析'!$D$26)*'3.1销售情况分析'!G39 -> 0 | H47: ='附表2 投资计划与资金筹措平衡表 '!$O$6/(1+'3.1销售情况分析'!$D$26)*'3.1销售情况分析'!H39 -> 0 | I47: ='附表2 投资计划与资金筹措平衡表 '!$O$6/(1+'3.1销售情况分析'!$D$26)*'3.1销售情况分析'!I39 -> 0 | J47: ='附表2 投资计划与资金筹措平衡表 '!$O$6/(1+'3.1销售情况分析'!$D$26)*'3.1销售情况分析'!J39 -> 7706.0787 | K47: ='附表2 投资计划与资金筹措平衡表 '!$O$6/(1+'3.1销售情况分析'!$D$26)*'3.1销售情况分析'!K39 -> 3002.1231 | L47: ='附表2 投资计划与资金筹措平衡表 '!$O$6/(1+'3.1销售情况分析'!$D$26)*'3.1销售情况分析'!L39 -> 3002.1231 | M47: ='附表2 投资计划与资金筹措平衡表 '!$O$6/(1+'3.1销售情况分析'!$D$26)*'3.1销售情况分析'!M39 -> 4158.0349 | N47: ='附表2 投资计划与资金筹措平衡表 '!$O$6/(1+'3.1销售情况分析'!$D$26)*'3.1销售情况分析'!N39 -> 2231.5152 | ... Z47: ='附表2 投资计划与资金筹措平衡表 '!$O$6/(1+'3.1销售情况分析'!$D$26)*'3.1销售情况分析'!Z39 -> 8396.3781
B48: 2.3 | C48: 开发费用(销售管理、财务费用） | D48: 不含税 | E48: =SUM(G48:Z48) -> 10948.776 | F48: =SUM(G48:Z48) -> 10948.776 | G48: ='附表8 总成本估算表'!E11+'附表8 总成本估算表'!E13 -> 0 | H48: ='附表8 总成本估算表'!F11+'附表8 总成本估算表'!F13 -> 94.339623 | I48: ='附表8 总成本估算表'!G11+'附表8 总成本估算表'!G13 -> 94.339623 | J48: ='附表8 总成本估算表'!H11+'附表8 总成本估算表'!H13 -> 1225.8969 | K48: ='附表8 总成本估算表'!I11+'附表8 总成本估算表'!I13 -> 535.17008 | L48: ='附表8 总成本估算表'!J11+'附表8 总成本估算表'!J13 -> 535.17008 | M48: ='附表8 总成本估算表'!K11+'附表8 总成本估算表'!K13 -> 704.90368 | N48: ='附表8 总成本估算表'!L11+'附表8 总成本估算表'!L13 -> 422.01435 | ... Z48: ='附表8 总成本估算表'!X11+'附表8 总成本估算表'!X13 -> 1397.3165
B49: 2.4 | C49: 加计扣除 | D49: 不含税 | E49: =SUM(G49:Z49) -> 19415.529 | F49: =SUM(G49:Z49) -> 19415.529 | G49: =(G46+G47)*0.2 -> 0 | H49: =(H46+H47)*0.2 -> 0 | I49: =(I46+I47)*0.2 -> 0 | J49: =(J46+J47)*0.2 -> 4017.0694 | K49: =(K46+K47)*0.2 -> 1564.9641 | L49: =(L46+L47)*0.2 -> 1564.9641 | M49: =(M46+M47)*0.2 -> 2167.5245 | N49: =(N46+N47)*0.2 -> 1163.2572 | ... Z49: =(Z46+Z47)*0.2 -> 4376.9127
B50: 3 | C50: 增值额 | D50: 不含税 | E50: =SUM(G50:Z50) -> -21070.323 | F50: =SUM(G50:Z50) -> -21070.323 | G50: =G42-G45 -> 0 | H50: =H42-H45 -> -94.339623 | I50: =I42-I45 -> -94.339623 | J50: =J42-J45 -> -3320.0431 | K50: =K42-K45 -> -1351.0045 | L50: =L42-L45 -> -1351.0045 | M50: =M42-M45 -> -1834.8601 | N50: =N42-N45 -> -1028.4342 | ... Z50: =Z42-Z45 -> -3679.0533
B51: 4 | C51: 增值系数 | D51: 不含税 | H51: =H50/H45 -> -1 | I51: =I50/I45 -> -1 | J51: =J50/J45 -> -0.13108031 | K51: =K50/K45 -> -0.13612199 | L51: =L50/L45 -> -0.13612199 | M51: =M50/M45 -> -0.13383321 | N51: =N50/N45 -> -0.13894835 | O51: =O50/O45 -> -0.14469879 | ... Z51: =Z50/Z45 -> -0.13301569
B52: 5 | C52: 土增税 | D52: 不含税 | E52: =SUM(G52:Z52) -> 0 | F52: =SUM(G52:Z52) -> 0 | G52: =IF(G50>0,G50*0.3,0) -> 0 | H52: =IF(H50>0,H50*0.3,0) -> 0 | I52: =IF(I50>0,I50*0.3,0) -> 0 | J52: =IF(J50>0,J50*0.3,0) -> 0 | K52: =IF(K50>0,K50*0.3,0) -> 0 | L52: =IF(L50>0,L50*0.3,0) -> 0 | M52: =IF(M50>0,M50*0.3,0) -> 0 | N52: =IF(N50>0,N50*0.3,0) -> 0 | ... Z52: =IF(Z50>0,Z50*0.3,0) -> 0
B54: 附表3.4 可售部分概况（万元）
B55: 序号 | C55: 区域 | D55: 户型 | F55: 合计面积（平方米） | G55: 返还面积平方米） | H55: 可销售面积平方米） | I55: 平均尺价（元/平方米） | J55: 预计货值（万元）
B56: 1 | C56: 住宅 | F56: =附表3营业收入汇总表!C28 -> 86949.32 | G56: 0 | H56: =F56-G56 -> 86949.32 | I56: ='0基本假设 '!L55 -> 11500 | J56: =H56*I56/10000 -> 99991.718
B57: 2 | C57: 商业 | F57: =附表3营业收入汇总表!C27 -> 16178.53 | G57: 10000 | H57: =F57-G57 -> 6178.53 | I57: ='0基本假设 '!L56 -> 18000 | J57: =H57*I57/10000 -> 11121.354
B58: 3 | C58: 车位 | F58: =附表3营业收入汇总表!C26 -> 796 | G58: 60 | H58: =F58-G58 -> 736 | I58: ='0基本假设 '!L57 -> 120000 | J58: =H58*I58/10000 -> 8832
H59: 总计 | J59: =SUM(J56:J58) -> 119945.07
B61: 附表3.5 销售进度百分比(单位：万元)
B62: 序号 | C62: 区域 | D62: 户型 | F62: 合计 | G62: 第1年Q1 | H62: 第1年Q2 | I62: 第1年Q3 | J62: 第1年Q4 | K62: 第2年Q3 | L62: 第2年Q4 | M62: 第3年Q1 | N62: 第3年Q2 | O62: 第3年Q3 | P62: 第3年Q4 | Q62: 第4年Q1 | R62: 第4年Q2 | S62: 第4年Q3 | T62: 第4年Q4 | U62: 第6年Q3 | V62: 第6年Q4 | W62: 第7年Q1 | X62: 第7年Q2 | Y62: 第7年Q3 | Z62: 第7年Q4
B63: 1 | C63: 住宅 | F63: =SUM(G63:Z63) -> 1 | J63: 0.4 | K63: 0.08 | L63: 0.08 | M63: 0.11 | N63: 0.06 | O63: 0.04 | P63: 0.03 | Q63: 0.02 | R63: 0.02 | S63: 0.02 | T63: 0.02 | U63: 0.02 | V63: 0.02 | W63: 0.02 | X63: 0.02 | Y63: 0.02 | Z63: 0.02
B64: 2 | C64: 商业 | F64: =SUM(G64:Z64) -> 1 | J64: 0.4 | K64: 0.08 | L64: 0.08 | M64: 0.11 | N64: 0.06 | O64: 0.04 | P64: 0.03 | Q64: 0.02 | R64: 0.02 | S64: 0.02 | T64: 0.02 | U64: 0.02 | V64: 0.02 | W64: 0.02 | X64: 0.02 | Y64: 0.02 | Z64: 0.02
B65: 3 | C65: 车位 | F65: =SUM(G65:Z65) -> 1 | J65: 0.4 | K65: 0.08 | L65: 0.08 | M65: 0.11 | N65: 0.06 | O65: 0.04 | P65: 0.03 | Q65: 0.02 | R65: 0.02 | S65: 0.02 | T65: 0.02 | U65: 0.02 | V65: 0.02 | W65: 0.02 | X65: 0.02 | Y65: 0.02 | Z65: 0.02
B68: 附表3.6 实际收到销售款比例
B69: 序号 | C69: 区域 | D69: 户型 | F69: 合计 | G69: 第1年Q1 | H69: 第1年Q2 | I69: 第1年Q3 | J69: 第1年Q4 | K69: 第2年Q3 | L69: 第2年Q4 | M69: 第3年Q1 | N69: 第3年Q2 | O69: 第3年Q3 | P69: 第3年Q4 | Q69: 第4年Q1 | R69: 第4年Q2 | S69: 第4年Q3 | T69: 第4年Q4 | U69: 第6年Q3 | V69: 第6年Q4 | W69: 第7年Q1 | X69: 第7年Q2 | Y69: 第7年Q3 | Z69: 第7年Q4
B70: 1 | C70: 住宅累积 | G70: =G63 -> 0 | H70: =G70+H63 -> 0 | I70: =H70+I63 -> 0 | J70: =I70+J63 -> 0.4 | K70: =J70+K63 -> 0.48 | L70: =K70+L63 -> 0.56 | M70: =L70+M63 -> 0.67 | N70: =M70+N63 -> 0.73 | O70: =N70+O63 -> 0.77 | ... Z70: =Y70+Z63 -> 1
C71: 实际收到销售款比例 | F71: =SUM(G71:Z71) -> 1 | H71: =IF(AND(H70>=20%,G70<20%),H70-20%,IF(AND(H70>20%,G70>=20%),H63,0)) -> 0 | I71: =IF(AND(I70>=20%,H70<20%),I70-20%,IF(AND(I70>20%,H70>=20%),I63,0)) -> 0 | J71: =IF(AND(J70>=20%,I70<20%),J70-20%,IF(AND(J70>20%,I70>=20%),J63,0)) -> 0.2 | K71: =IF(AND(K70>=20%,J70<20%),K70-20%,IF(AND(K70>20%,J70>=20%),K63,0)) -> 0.08 | L71: =IF(AND(L70>=20%,K70<20%),L70-20%,IF(AND(L70>20%,K70>=20%),L63,0)) -> 0.08 | M71: =IF(AND(M70>=20%,L70<20%),M70-20%,IF(AND(M70>20%,L70>=20%),M63,0)) -> 0.11 | N71: =IF(AND(N70>=20%,M70<20%),N70-20%,IF(AND(N70>20%,M70>=20%),N63,0)) -> 0.06 | O71: =IF(AND(O70>=20%,N70<20%),O70-20%,IF(AND(O70>20%,N70>=20%),O63,0)) -> 0.04 | ... Y71: =IF(AND(Y70>=20%,X70<20%),Y70-20%,IF(AND(Y70>20%,X70>=20%),Y63,0)) -> 0.02 | Z71: =Z63+20% -> 0.22
B72: 2 | C72: 商业 | G72: =G64 -> 0 | H72: =G72+H64 -> 0 | I72: =H72+I64 -> 0 | J72: =I72+J64 -> 0.4 | K72: =J72+K64 -> 0.48 | L72: =K72+L64 -> 0.56 | M72: =L72+M64 -> 0.67 | N72: =M72+N64 -> 0.73 | O72: =N72+O64 -> 0.77 | ... Z72: =Y72+Z64 -> 1
C73: 实际收到销售款比例 | F73: =SUM(G73:Z73) -> 1 | H73: =IF(AND(H72>=20%,G72<20%),H72-20%,IF(AND(H72>20%,G72>=20%),H64,0)) -> 0 | I73: =IF(AND(I72>=20%,H72<20%),I72-20%,IF(AND(I72>20%,H72>=20%),I64,0)) -> 0 | J73: =IF(AND(J72>=20%,I72<20%),J72-20%,IF(AND(J72>20%,I72>=20%),J64,0)) -> 0.2 | K73: =IF(AND(K72>=20%,J72<20%),K72-20%,IF(AND(K72>20%,J72>=20%),K64,0)) -> 0.08 | L73: =IF(AND(L72>=20%,K72<20%),L72-20%,IF(AND(L72>20%,K72>=20%),L64,0)) -> 0.08 | M73: =IF(AND(M72>=20%,L72<20%),M72-20%,IF(AND(M72>20%,L72>=20%),M64,0)) -> 0.11 | N73: =IF(AND(N72>=20%,M72<20%),N72-20%,IF(AND(N72>20%,M72>=20%),N64,0)) -> 0.06 | O73: =IF(AND(O72>=20%,N72<20%),O72-20%,IF(AND(O72>20%,N72>=20%),O64,0)) -> 0.04 | ... Y73: =IF(AND(Y72>=20%,X72<20%),Y72-20%,IF(AND(Y72>20%,X72>=20%),Y64,0)) -> 0.02 | Z73: =Z64+20% -> 0.22
B74: 3 | C74: 车位 | G74: =G65 -> 0 | H74: =G74+H65 -> 0 | I74: =H74+I65 -> 0 | J74: =I74+J65 -> 0.4 | K74: =J74+K65 -> 0.48 | L74: =K74+L65 -> 0.56 | M74: =L74+M65 -> 0.67 | N74: =M74+N65 -> 0.73 | O74: =N74+O65 -> 0.77 | ... Z74: =Y74+Z65 -> 1
C75: 实际收到销售款比例 | F75: =SUM(G75:Z75) -> 1 | H75: =IF(AND(H74>=20%,G74<20%),H74-20%,IF(AND(H74>20%,G74>=20%),H65,0)) -> 0 | I75: =IF(AND(I74>=20%,H74<20%),I74-20%,IF(AND(I74>20%,H74>=20%),I65,0)) -> 0 | J75: =IF(AND(J74>=20%,I74<20%),J74-20%,IF(AND(J74>20%,I74>=20%),J65,0)) -> 0.2 | K75: =IF(AND(K74>=20%,J74<20%),K74-20%,IF(AND(K74>20%,J74>=20%),K65,0)) -> 0.08 | L75: =IF(AND(L74>=20%,K74<20%),L74-20%,IF(AND(L74>20%,K74>=20%),L65,0)) -> 0.08 | M75: =IF(AND(M74>=20%,L74<20%),M74-20%,IF(AND(M74>20%,L74>=20%),M65,0)) -> 0.11 | N75: =IF(AND(N74>=20%,M74<20%),N74-20%,IF(AND(N74>20%,M74>=20%),N65,0)) -> 0.06 | O75: =IF(AND(O74>=20%,N74<20%),O74-20%,IF(AND(O74>20%,N74>=20%),O65,0)) -> 0.04 | ... Y75: =IF(AND(Y74>=20%,X74<20%),Y74-20%,IF(AND(Y74>20%,X74>=20%),Y65,0)) -> 0.02 | Z75: =Z65+20% -> 0.22
B77: 附表3.7 实际销售额(单位：万元)
B78: 序号 | C78: 区域 | D78: 户型 | F78: 合计（万元） | G78: 第1年Q1 | H78: 第1年Q2 | I78: 第1年Q3 | J78: 第1年Q4 | K78: 第2年Q3 | L78: 第2年Q4 | M78: 第3年Q1 | N78: 第3年Q2 | O78: 第3年Q3 | P78: 第3年Q4 | Q78: 第4年Q1 | R78: 第4年Q2 | S78: 第4年Q3 | T78: 第4年Q4 | U78: 第6年Q3 | V78: 第6年Q4 | W78: 第7年Q1 | X78: 第7年Q2 | Y78: 第7年Q3 | Z78: 第7年Q4
B79: 1 | C79: 住宅 | F79: =SUM(G79:Z79) -> 95991.718 | G79: =$J$56*G71 -> 0 | H79: =$J$56*H71 -> 0 | I79: =$J$56*I71 -> 0 | J79: =$J$56*J71 -> 19998.344 | K79: =$J$56*K71-250 -> 7749.3374 | L79: =$J$56*L71-250 -> 7749.3374 | M79: =$J$56*M71-250 -> 10749.089 | N79: =$J$56*N71-250 -> 5749.5031 | O79: =$J$56*O71-250 -> 3749.6687 | P79: =$J$56*P71-250 -> 2749.7515 | Q79: =$J$56*Q71-250 -> 1749.8344 | R79: =$J$56*R71-250 -> 1749.8344 | ... Z79: =$J$56*Z71-250 -> 21748.178
B80: 2 | C80: 商业 | F80: =SUM(G80:Z80) -> 11121.354 | G80: =$J$57*G73 -> 0 | H80: =$J$57*H73 -> 0 | I80: =$J$57*I73 -> 0 | J80: =$J$57*J73 -> 2224.2708 | K80: =$J$57*K73 -> 889.70832 | L80: =$J$57*L73 -> 889.70832 | M80: =$J$57*M73 -> 1223.3489 | N80: =$J$57*N73 -> 667.28124 | ... Z80: =$J$57*Z73 -> 2446.6979
B81: 3 | C81: 车位 | F81: =SUM(G81:Z81) -> 8832 | G81: =$J$58*G75 -> 0 | H81: =$J$58*H75 -> 0 | I81: =$J$58*I75 -> 0 | J81: =$J$58*J75 -> 1766.4 | K81: =$J$58*K75 -> 706.56 | L81: =$J$58*L75 -> 706.56 | M81: =$J$58*M75 -> 971.52 | N81: =$J$58*N75 -> 529.92 | ... Z81: =$J$58*Z75 -> 1943.04
B83: 点击返回目录

Sheet 3.2 营业收入汇总表
A1: 附表4 营业收入汇总表(单位：万元)
A2: 序号 | B2: 项目 | C2: 小计 | D2: 第1年Q1 | E2: 第1年Q2 | F2: 第1年Q3 | G2: 第1年Q4 | H2: 第2年Q1 | I2: 第2年Q2 | J2: 第2年Q3 | K2: 第2年Q4 | L2: 第3年Q1 | M2: 第3年Q2 | N2: 第3年Q3 | O2: 第3年Q4 | P2: 第4年Q1 | Q2: 第4年Q2 | R2: 第4年Q3 | S2: 第4年Q4 | T2: 第5年Q1 | U2: 第5年Q2 | V2: 第5年Q3 | W2: 第5年Q4
A3: 1 | B3: 含税销售收入 | C3: =SUM(D3:W3) -> 115945.07 | D3: ='3.1销售情况分析'!G3 -> 0 | E3: ='3.1销售情况分析'!H3 -> 0 | F3: ='3.1销售情况分析'!I3 -> 0 | G3: ='3.1销售情况分析'!J3 -> 23989.014 | H3: ='3.1销售情况分析'!K3 -> 9345.6058 | I3: ='3.1销售情况分析'!L3 -> 9345.6058 | J3: ='3.1销售情况分析'!M3 -> 12943.958 | K3: ='3.1销售情况分析'!N3 -> 6946.7043 | ... W3: ='3.1销售情况分析'!Z3 -> 26137.916
A4: 2 | B4: 增值税及附加 | C4: =SUM(D4:W4) -> 921.96832 | D4: ='3.1销售情况分析'!G4 -> 0 | E4: ='3.1销售情况分析'!H4 -> 0 | F4: ='3.1销售情况分析'!I4 -> 0 | G4: ='3.1销售情况分析'!J4 -> 0 | H4: ='3.1销售情况分析'!K4 -> 0 | I4: ='3.1销售情况分析'!L4 -> 0 | J4: ='3.1销售情况分析'!M4 -> 0 | K4: ='3.1销售情况分析'!N4 -> 0 | ... W4: ='3.1销售情况分析'!Z4 -> 921.96832
A5: 3 | B5: 不含税收入 | C5: =SUM(D5:W5) -> 115023.1 | D5: ='3.1销售情况分析'!G5 -> 0 | E5: ='3.1销售情况分析'!H5 -> 0 | F5: ='3.1销售情况分析'!I5 -> 0 | G5: ='3.1销售情况分析'!J5 -> 23989.014 | H5: ='3.1销售情况分析'!K5 -> 9345.6058 | I5: ='3.1销售情况分析'!L5 -> 9345.6058 | J5: ='3.1销售情况分析'!M5 -> 12943.958 | K5: ='3.1销售情况分析'!N5 -> 6946.7043 | ... W5: ='3.1销售情况分析'!Z5 -> 25215.948
A6: 5 | B6: 年经营成本 | C6: =SUM(D6:W6) -> 7697.2536 | D6: ='5.1运营成本明细表'!G3 -> 0 | E6: ='5.1运营成本明细表'!H3 -> 100 | F6: ='5.1运营成本明细表'!I3 -> 100 | G6: ='5.1运营成本明细表'!J3 -> 1299.4507 | H6: ='5.1运营成本明细表'!K3 -> 567.28029 | I6: ='5.1运营成本明细表'!L3 -> 567.28029 | J6: ='5.1运营成本明细表'!M3 -> 747.1979 | K6: ='5.1运营成本明细表'!N3 -> 447.33522 | ... W6: ='5.1运营成本明细表'!Z3 -> 1406.8958
A7: 6 | B7: 年经营合理利润 | C7: =SUM(D7:W7) -> 0 | D7: =D6*'0基本假设 '!$L$51 -> 0 | E7: =E6*'0基本假设 '!$L$51 -> 0 | F7: =F6*'0基本假设 '!$L$51 -> 0 | G7: =G6*'0基本假设 '!$L$51 -> 0 | H7: =H6*'0基本假设 '!$L$51 -> 0 | I7: =I6*'0基本假设 '!$L$51 -> 0 | J7: =J6*'0基本假设 '!$L$51 -> 0 | K7: =K6*'0基本假设 '!$L$51 -> 0 | ... W7: =W6*'0基本假设 '!$L$51 -> 0
A8: 7 | B8: 经营成本+经营合理利润 | C8: =SUM(D8:W8) -> 7697.2536 | D8: =D6+D7 -> 0 | E8: =E6+E7 -> 100 | F8: =F6+F7 -> 100 | G8: =G6+G7 -> 1299.4507 | H8: =H6+H7 -> 567.28029 | I8: =I6+I7 -> 567.28029 | J8: =J6+J7 -> 747.1979 | K8: =K6+K7 -> 447.33522 | ... W8: =W6+W7 -> 1406.8958
A9: 8 | B9: 土地出让金返还收入 | C9: =SUM(D9:W9) -> 0 | D9: ='3.1销售情况分析'!G19 -> 0 | E9: ='3.1销售情况分析'!H19 -> 0 | F9: ='3.1销售情况分析'!I19 -> 0 | G9: ='3.1销售情况分析'!J19 -> 0 | H9: ='3.1销售情况分析'!K19 -> 0 | I9: ='3.1销售情况分析'!L19 -> 0 | J9: ='3.1销售情况分析'!M19 -> 0 | K9: ='3.1销售情况分析'!N19 -> 0 | ... W9: ='3.1销售情况分析'!Z19 -> 0
B11: 折旧摊销系数 | C11: =SUM(D11:W11) -> 1 | D11: =D12+D13 -> 0 | E11: =E12+E13 -> 0 | F11: =F12+F13 -> 0 | G11: =G12+G13 -> 0.23689982 | H11: =H12+H13 -> 0.10060373 | I11: =I12+I13 -> 0.10060373 | J11: =J12+J13 -> 0.13163871 | K11: =K12+K13 -> 0.079913752 | ... W11: =W12+W13 -> 0.21043361
B12: 折旧摊销参考 | C12: =SUM(D12:W12) -> 1 | E12: =E3/$C$3 -> 0 | F12: =F3/$C$3 -> 0 | G12: =G3/$C$3 -> 0.20689982 | H12: =H3/$C$3 -> 0.080603734 | I12: =I3/$C$3 -> 0.080603734 | J12: =J3/$C$3 -> 0.11163871 | K12: =K3/$C$3 -> 0.059913752 | L12: =L3/$C$3 -> 0.03922377 | ... W12: =W3/$C$3 -> 0.22543361
B13: 折旧摊销调整系数 | C13: =SUM(D13:W13) -> 1.3877788e-17 | G13: 0.03 | H13: 0.02 | I13: 0.02 | J13: 0.02 | K13: 0.02 | L13: 0.02 | M13: 0.02 | N13: -0.015 | O13: -0.015 | P13: -0.015 | Q13: -0.015 | R13: -0.015 | S13: -0.015 | T13: -0.015 | U13: -0.015 | V13: -0.015 | W13: -0.015

Sheet 附表4 税金及附加表
B2: 附表4 税金及附加 (单位：万元)
B3: 序号 | C3: 项目 | E3: 合计 | F3: 第1年Q1 | G3: 第1年Q2 | H3: 第1年Q3 | I3: 第1年Q4 | J3: 第2年Q1 | K3: 第2年Q2 | L3: 第2年Q3 | M3: 第2年Q4 | N3: 第3年Q1 | O3: 第3年Q2 | P3: 第3年Q3 | Q3: 第3年Q4 | R3: 第4年Q1 | S3: 第4年Q2 | T3: 第4年Q3 | U3: 第4年Q4 | V3: 第5年Q1 | W3: 第5年Q2 | X3: 第5年Q3 | Y3: 第5年Q4
B4: 1.1 | C4: 销售收入（含税） | E4: =SUM(F4:Y4) -> 115945.07 | F4: ='3.1销售情况分析'!G3 -> 0 | G4: ='3.1销售情况分析'!H3 -> 0 | H4: ='3.1销售情况分析'!I3 -> 0 | I4: ='3.1销售情况分析'!J3 -> 23989.014 | J4: ='3.1销售情况分析'!K3 -> 9345.6058 | K4: ='3.1销售情况分析'!L3 -> 9345.6058 | L4: ='3.1销售情况分析'!M3 -> 12943.958 | M4: ='3.1销售情况分析'!N3 -> 6946.7043 | ... Y4: ='3.1销售情况分析'!Z3 -> 26137.916
B5: 2 | C5: 增值税及附加 | E5: =SUM(F5:Y5) -> 921.96832 | F5: ='3.1销售情况分析'!G33+'3.1销售情况分析'!G34 -> 0 | G5: ='3.1销售情况分析'!H33+'3.1销售情况分析'!H34 -> 0 | H5: ='3.1销售情况分析'!I33+'3.1销售情况分析'!I34 -> 0 | I5: ='3.1销售情况分析'!J33+'3.1销售情况分析'!J34 -> 0 | J5: ='3.1销售情况分析'!K33+'3.1销售情况分析'!K34 -> 0 | K5: ='3.1销售情况分析'!L33+'3.1销售情况分析'!L34 -> 0 | L5: ='3.1销售情况分析'!M33+'3.1销售情况分析'!M34 -> 0 | M5: ='3.1销售情况分析'!N33+'3.1销售情况分析'!N34 -> 0 | ... Y5: ='3.1销售情况分析'!Z33+'3.1销售情况分析'!Z34 -> 921.96832
B6: 3 | C6: 土增税 | E6: =SUM(F6:Y6) -> 0 | F6: ='3.1销售情况分析'!G52 -> 0 | G6: ='3.1销售情况分析'!H52 -> 0 | H6: ='3.1销售情况分析'!I52 -> 0 | I6: ='3.1销售情况分析'!J52 -> 0 | J6: ='3.1销售情况分析'!K52 -> 0 | K6: ='3.1销售情况分析'!L52 -> 0 | L6: ='3.1销售情况分析'!M52 -> 0 | M6: ='3.1销售情况分析'!N52 -> 0 | ... Y6: ='3.1销售情况分析'!Z52 -> 0
C43: 税金附加
C44: 实际缴纳与抵扣 | E44: =#REF!+#REF! -> #REF! | F44: =IF(E44=E45,"正确","错误") -> #REF!
C45: 销项税 | E45: =#REF! -> #REF!
C48: 可行性缺口补助（含增值税）
C49: 可用性服务费（扣除使用者付费部分）
C50: 运营绩效服务费（含增值税）
B52: 点击返回目录

Sheet 附表5 运营成本汇总表
A1: 附表5 运营成本费用汇总表 (单位：万元)
A2: 序号 | B2: 项目 | C2: 单位：万元 | D2: 合计 | E2: 第1年Q1 | F2: 第1年Q2 | G2: 第1年Q3 | H2: 第1年Q4 | I2: 第2年Q1 | J2: 第2年Q2 | K2: 第2年Q3 | L2: 第2年Q4 | M2: 第3年Q1 | N2: 第3年Q2 | O2: 第3年Q3 | P2: 第3年Q4 | Q2: 第4年Q1 | R2: 第4年Q2 | S2: 第4年Q3 | T2: 第4年Q4 | U2: 第5年Q1 | V2: 第5年Q2 | W2: 第5年Q3 | X2: 第5年Q4
A3: 1 | B3: 经营成本 | D3: =SUM(E3:X3) -> 7697.2536 | E3: ='5.1运营成本明细表'!G3 -> 0 | F3: ='5.1运营成本明细表'!H3 -> 100 | G3: ='5.1运营成本明细表'!I3 -> 100 | H3: ='5.1运营成本明细表'!J3 -> 1299.4507 | I3: ='5.1运营成本明细表'!K3 -> 567.28029 | J3: ='5.1运营成本明细表'!L3 -> 567.28029 | K3: ='5.1运营成本明细表'!M3 -> 747.1979 | L3: ='5.1运营成本明细表'!N3 -> 447.33522 | ... X3: ='5.1运营成本明细表'!Z3 -> 1406.8958
A9: 点击返回目录

Sheet 5.1运营成本明细表
A1: 附表5.1 运营成本测算表（万元）
A2: 序号 | B2: 项目 | C2: 单价 | D2: 数量 | E2: 备注 | F2: 合计 | G2: 第1年Q1 | H2: 第1年Q2 | I2: 第1年Q3 | J2: 第1年Q4 | K2: 第2年Q1 | L2: 第2年Q2 | M2: 第2年Q3 | N2: 第2年Q4 | O2: 第3年Q1 | P2: 第3年Q2 | Q2: 第3年Q3 | R2: 第3年Q4 | S2: 第4年Q1 | T2: 第4年Q2 | U2: 第4年Q3 | V2: 第4年Q4 | W2: 第5年Q1 | X2: 第5年Q2 | Y2: 第5年Q3 | Z2: 第5年Q4
B3: 合计 | F3: =SUM(G3:Z3) -> 7697.2536 | G3: =G4+G9 -> 0 | H3: =H4+H9 -> 100 | I3: =I4+I9 -> 100 | J3: =J4+J9 -> 1299.4507 | K3: =K4+K9 -> 567.28029 | L3: =L4+L9 -> 567.28029 | M3: =M4+M9 -> 747.1979 | N3: =N4+N9 -> 447.33522 | ... Z3: =Z4+Z9 -> 1406.8958
A4: 1 | B4: 经营维护成本 | F4: =SUM(G4:Z4) -> 5797.2536 | G4: =SUM(G5:G7) -> 0 | H4: =SUM(H5:H7) -> 0 | I4: =SUM(I5:I7) -> 0 | J4: =SUM(J5:J7) -> 1199.4507 | K4: =SUM(K5:K7) -> 467.28029 | L4: =SUM(L5:L7) -> 467.28029 | M4: =SUM(M5:M7) -> 647.1979 | N4: =SUM(N5:N7) -> 347.33522 | ... Z4: =SUM(Z5:Z7) -> 1306.8958
A5: 1.1 | B5: 销售费用 | F5: =SUM(G5:Z5) -> 4058.0775 | G5: =('3.1销售情况分析'!G79+'3.1销售情况分析'!G80+'3.1销售情况分析'!G81)*0.035 -> 0 | H5: =('3.1销售情况分析'!H79+'3.1销售情况分析'!H80+'3.1销售情况分析'!H81)*0.035 -> 0 | I5: =('3.1销售情况分析'!I79+'3.1销售情况分析'!I80+'3.1销售情况分析'!I81)*0.035 -> 0 | J5: =('3.1销售情况分析'!J79+'3.1销售情况分析'!J80+'3.1销售情况分析'!J81)*0.035 -> 839.6155 | K5: =('3.1销售情况分析'!K79+'3.1销售情况分析'!K80+'3.1销售情况分析'!K81)*0.035 -> 327.0962 | L5: =('3.1销售情况分析'!L79+'3.1销售情况分析'!L80+'3.1销售情况分析'!L81)*0.035 -> 327.0962 | M5: =('3.1销售情况分析'!M79+'3.1销售情况分析'!M80+'3.1销售情况分析'!M81)*0.035 -> 453.03853 | N5: =('3.1销售情况分析'!N79+'3.1销售情况分析'!N80+'3.1销售情况分析'!N81)*0.035 -> 243.13465 | ... Z5: =('3.1销售情况分析'!Z79+'3.1销售情况分析'!Z80+'3.1销售情况分析'!Z81)*0.035 -> 914.82705
A6: 1.2 | B6: 代建费用 | F6: =SUM(G6:Z6) -> 1739.1761 | G6: =('3.1销售情况分析'!G79+'3.1销售情况分析'!G80+'3.1销售情况分析'!G81)*0.015 -> 0 | H6: =('3.1销售情况分析'!H79+'3.1销售情况分析'!H80+'3.1销售情况分析'!H81)*0.015 -> 0 | I6: =('3.1销售情况分析'!I79+'3.1销售情况分析'!I80+'3.1销售情况分析'!I81)*0.015 -> 0 | J6: =('3.1销售情况分析'!J79+'3.1销售情况分析'!J80+'3.1销售情况分析'!J81)*0.015 -> 359.83522 | K6: =('3.1销售情况分析'!K79+'3.1销售情况分析'!K80+'3.1销售情况分析'!K81)*0.015 -> 140.18409 | L6: =('3.1销售情况分析'!L79+'3.1销售情况分析'!L80+'3.1销售情况分析'!L81)*0.015 -> 140.18409 | M6: =('3.1销售情况分析'!M79+'3.1销售情况分析'!M80+'3.1销售情况分析'!M81)*0.015 -> 194.15937 | N6: =('3.1销售情况分析'!N79+'3.1销售情况分析'!N80+'3.1销售情况分析'!N81)*0.015 -> 104.20056 | ... Z6: =('3.1销售情况分析'!Z79+'3.1销售情况分析'!Z80+'3.1销售情况分析'!Z81)*0.015 -> 392.06874
A7: 1.3 | B7: 大修费
A9: 2 | B9: 项目公司成本 | F9: =SUM(G9:Z9) -> 1900 | G9: =SUM(G10:G12) -> 0 | H9: =SUM(H10:H12) -> 100 | I9: =SUM(I10:I12) -> 100 | J9: =SUM(J10:J12) -> 100 | K9: =SUM(K10:K12) -> 100 | L9: =SUM(L10:L12) -> 100 | M9: =SUM(M10:M12) -> 100 | N9: =SUM(N10:N12) -> 100 | ... Z9: =SUM(Z10:Z12) -> 100
A10: 2.1 | B10: 工资福利 | F10: =SUM(G10:Z10) -> 1900 | H10: 100 | I10: 100 | J10: 100 | K10: 100 | L10: 100 | M10: 100 | N10: 100 | O10: 100 | P10: 100 | Q10: 100 | R10: 100 | S10: 100 | T10: 100 | U10: 100 | V10: 100 | W10: 100 | X10: 100 | Y10: 100 | Z10: 100
A11: 2.2 | B11: 其他费用支出 | F11: =SUM(G11:Z11) -> 0
A12: 2.3
B14: 经营成本引用数据 | C14: 参数-百万$ | D14: 年增长率 | E14: 备注
B15: 运营养护费用（百万元/年） | C15: ='0基本假设 '!L76 -> 0 | D15: 0.03 | E15: 0.02
B16: 运营管理费用（百万元/年） | C16: ='0基本假设 '!L77 -> 0 | D16: 0.03 | E16: 0.02
B17: 大修费用（倍数*当年养护费用） | C17: ='0基本假设 '!L78 -> 0 | D17: 0.02 | E17: 每10年1次
A19: 点击返回目录

Sheet 附表6 资产折旧摊销表
B2: 附表6 资产折旧与摊销表 (单位：万元)
B3: 序号 | C3: 项目 | D3: 合计 | E3: 第1年Q1 | F3: 第1年Q2 | G3: 第1年Q3 | H3: 第1年Q4 | I3: 第2年Q1 | J3: 第2年Q2 | K3: 第2年Q3 | L3: 第2年Q4 | M3: 第3年Q1 | N3: 第3年Q2 | O3: 第3年Q3 | P3: 第3年Q4 | Q3: 第4年Q1 | R3: 第4年Q2 | S3: 第4年Q3 | T3: 第4年Q4 | U3: 第5年Q1 | V3: 第5年Q2 | W3: 第5年Q3 | X3: 第5年Q4
B4: 1 | C4: 初始投资
B5: 1.1 | C5: 建设投资（当期在建工程） | D5: =SUM(E5:U5) -> 106762.97 | E5: ='附表2 投资计划与资金筹措平衡表 '!D5-'附表2 投资计划与资金筹措平衡表 '!D21 -> 59832.185 | F5: ='附表2 投资计划与资金筹措平衡表 '!E5-'附表2 投资计划与资金筹措平衡表 '!E21 -> 8809.0863 | G5: ='附表2 投资计划与资金筹措平衡表 '!F5-'附表2 投资计划与资金筹措平衡表 '!F21 -> 4535.6958 | H5: ='附表2 投资计划与资金筹措平衡表 '!G5-'附表2 投资计划与资金筹措平衡表 '!G21 -> 4601.2721 | I5: ='附表2 投资计划与资金筹措平衡表 '!H5-'附表2 投资计划与资金筹措平衡表 '!H21 -> 4666.8485 | J5: ='附表2 投资计划与资金筹措平衡表 '!I5-'附表2 投资计划与资金筹措平衡表 '!I21 -> 4732.4248 | K5: ='附表2 投资计划与资金筹措平衡表 '!J5-'附表2 投资计划与资金筹措平衡表 '!J21 -> 4798.0011 | L5: ='附表2 投资计划与资金筹措平衡表 '!K5-'附表2 投资计划与资金筹措平衡表 '!K21 -> 4863.5774 | ... N5: ='附表2 投资计划与资金筹措平衡表 '!M5-'附表2 投资计划与资金筹措平衡表 '!M21 -> 4994.7301
B6: 1.1.1 | C6: 原值 | H6: =SUM($E$5:H5) -> 77778.239 | I6: =SUM($E$5:I5) -> 82445.088 | J6: =SUM($E$5:J5) -> 87177.513 | K6: =SUM($E$5:K5) -> 91975.514 | L6: =SUM($E$5:L5) -> 96839.091 | M6: =SUM($E$5:M5) -> 101768.24 | N6: =SUM($E$5:N5) -> 106762.97 | O6: =SUM($E$5:O5) -> 106762.97 | ... X6: =SUM($E$5:X5) -> 106762.97
B7: 1.1.2 | C7: 当期摊销费 | D7: =SUM(E7:X7) -> 106762.97 | E7: =$D$5*'3.2 营业收入汇总表'!D11 -> 0 | F7: =$D$5*'3.2 营业收入汇总表'!E11 -> 0 | G7: =$D$5*'3.2 营业收入汇总表'!F11 -> 0 | H7: =$D$5*'3.2 营业收入汇总表'!G11 -> 25292.129 | I7: =$D$5*'3.2 营业收入汇总表'!H11 -> 10740.754 | J7: =$D$5*'3.2 营业收入汇总表'!I11 -> 10740.754 | K7: =$D$5*'3.2 营业收入汇总表'!J11 -> 14054.14 | L7: =$D$5*'3.2 营业收入汇总表'!K11 -> 8531.8299 | ... X7: =$D$5*'3.2 营业收入汇总表'!W11 -> 22466.518
B8: 1.1.3 | C8: 净值 | H8: =SUM($E$5:H5)-SUM($E$7:H7) -> 52486.11 | I8: =SUM($E$5:I5)-SUM($E$7:I7) -> 46412.204 | J8: =SUM($E$5:J5)-SUM($E$7:J7) -> 40403.875 | K8: =SUM($E$5:K5)-SUM($E$7:K7) -> 31147.736 | L8: =SUM($E$5:L5)-SUM($E$7:L7) -> 27479.484 | M8: =SUM($E$5:M5)-SUM($E$7:M7) -> 26085.732 | N8: =SUM($E$5:N5)-SUM($E$7:N7) -> 25862.018 | O8: =SUM($E$5:O5)-SUM($E$7:O7) -> 25484.74 | ... X8: =SUM($E$5:X5)-SUM($E$7:X7) -> 0
B9: 1.2 | C9: 设备（当期在建工程）
B10: 1.2.1 | C10: 原值
B11: 1.2.2 | C11: 当期摊销费
B12: 1.2.3 | C12: 净值 | D12: =SUM(E12:X12) -> 0
B13: 1.3 | C13: 初始投资小计（当期固定资产） | D13: =SUM(E13:X13) -> 106762.97 | E13: =E5 -> 59832.185 | F13: =F5 -> 8809.0863 | G13: =G5 -> 4535.6958 | H13: =H5 -> 4601.2721 | I13: =I5 -> 4666.8485 | J13: =J5 -> 4732.4248 | K13: =K5 -> 4798.0011 | L13: =L5 -> 4863.5774 | ... N13: =N5 -> 4994.7301
B14: 1.3.1 | C14: 原值 | E14: =E6 -> 0 | F14: =F6 -> 0 | G14: =G6 -> 0 | H14: =H6 -> 77778.239 | I14: =I6 -> 82445.088 | J14: =J6 -> 87177.513 | K14: =K6 -> 91975.514 | L14: =L6 -> 96839.091 | ... Q14: =Q6 -> 106762.97 | R14: =R6+R10 -> 106762.97 | S14: =S6+S10 -> 106762.97 | T14: =T6 -> 106762.97 | U14: =U6 -> 106762.97 | V14: =V6 -> 106762.97 | W14: =W6 -> 106762.97 | X14: =X6 -> 106762.97
B15: 1.3.2 | C15: 当期摊销费 | D15: =SUM(E15:X15) -> 106762.97 | H15: =H7+H11 -> 25292.129 | I15: =I7+I11 -> 10740.754 | J15: =J7+J11 -> 10740.754 | K15: =K7+K11 -> 14054.14 | L15: =L7+L11 -> 8531.8299 | M15: =M7+M11 -> 6322.9059 | N15: =N7+N11 -> 5218.4439 | O15: =O7+O11 -> 377.27777 | ... X15: =X7+X11 -> 22466.518
B16: 1.3.3 | C16: 净值 | E16: =E8+E12 -> 0 | F16: =F8+F12 -> 0 | G16: =G8+G12 -> 0 | H16: =H8+H12 -> 52486.11 | I16: =I8+I12 -> 46412.204 | J16: =J8+J12 -> 40403.875 | K16: =K8+K12 -> 31147.736 | L16: =L8+L12 -> 27479.484 | ... X16: =X8+X12 -> 0
B18: 点击返回目录

Sheet 附表7 银行贷款还本付息表
B2: 附表7银行贷款还本付息表 (单位：万元)
B3: 序号 | C3: 项目 | D3: 合 计 | E3: 建设期 | O3: 赛事期 | P3: 运营期
E4: 第1年Q1 | F4: 第1年Q2 | G4: 第1年Q3 | H4: 第1年Q4 | I4: 第2年Q1 | J4: 第2年Q2 | K4: 第2年Q3 | L4: 第2年Q4 | M4: 第3年Q1 | N4: 第3年Q2 | O4: 第3年Q3 | P4: 第3年Q4 | Q4: 第4年Q1 | R4: 第4年Q2 | S4: 第4年Q3 | T4: 第4年Q4 | U4: 第5年Q1 | V4: 第5年Q2 | W4: 第5年Q3 | X4: 第5年Q4
B5: 清水湾项目
B6: 1.1 | C6: 期初借款累计 | E6: 0 | F6: =E14 -> 0 | G6: =F14 -> 8743.51 | H6: =G14 -> 13115.265 | I6: =H14 -> 17487.02 | J6: =I14 -> 21858.775 | K6: =J14 -> 26230.53 | L6: =K14 -> 30602.285 | M6: =L14 -> 34974.04 | ... X6: =W14 -> 4670.4203
B7: 1.2 | C7: 当期借款 | D7: =SUM(E7:X7) -> 43717.55 | E7: ='附表2 投资计划与资金筹措平衡表 '!D16 -> 0 | F7: ='附表2 投资计划与资金筹措平衡表 '!E16 -> 8743.51 | G7: ='附表2 投资计划与资金筹措平衡表 '!F16 -> 4371.755 | H7: ='附表2 投资计划与资金筹措平衡表 '!G16 -> 4371.755 | I7: ='附表2 投资计划与资金筹措平衡表 '!H16 -> 4371.755 | J7: ='附表2 投资计划与资金筹措平衡表 '!I16 -> 4371.755 | K7: ='附表2 投资计划与资金筹措平衡表 '!J16 -> 4371.755 | L7: ='附表2 投资计划与资金筹措平衡表 '!K16 -> 4371.755 | ... O7: ='附表2 投资计划与资金筹措平衡表 '!N16 -> 0 | P7: 0 | Q7: 0 | R7: 0 | S7: 0 | T7: 0 | U7: 0 | V7: 0 | W7: 0 | X7: 0
B8: 1.3 | C8: 当期应计建设期利息 | D8: =SUM(E8:X8) -> 3213.2399 | E8: ='附表2 投资计划与资金筹措平衡表 '!D9 -> 0 | F8: ='附表2 投资计划与资金筹措平衡表 '!E9 -> 65.576325 | G8: ='附表2 投资计划与资金筹措平衡表 '!F9 -> 163.94081 | H8: ='附表2 投资计划与资金筹措平衡表 '!G9 -> 229.51714 | I8: ='附表2 投资计划与资金筹措平衡表 '!H9 -> 295.09346 | J8: ='附表2 投资计划与资金筹措平衡表 '!I9 -> 360.66979 | K8: ='附表2 投资计划与资金筹措平衡表 '!J9 -> 426.24611 | L8: ='附表2 投资计划与资金筹措平衡表 '!K9 -> 491.82244 | ... N8: ='附表2 投资计划与资金筹措平衡表 '!M9 -> 622.97509
B9: 1.4 | C9: 当期应计运营期利息 | D9: =SUM(E9:X9) -> 3687.2159 | O9: =O6*'0基本假设 '!$L$34 -> 655.76325 | P9: =P6*'0基本假设 '!$L$34 -> 594.49255 | Q9: =Q6*'0基本假设 '!$L$34 -> 532.30279 | R9: =R6*'0基本假设 '!$L$34 -> 469.18018 | S9: =S6*'0基本假设 '!$L$34 -> 405.11074 | T9: =T6*'0基本假设 '!$L$34 -> 340.08025 | U9: =U6*'0基本假设 '!$L$34 -> 274.0743 | V9: =V6*'0基本假设 '!$L$34 -> 207.07827 | ... X9: =X6*'0基本假设 '!$L$34 -> 70.056304
B10: 1.5 | C10: 当期还本付息 | D10: =SUM(E10:X10) -> 50618.006 | E10: =SUM(E11:E13) -> 0 | F10: =SUM(F11:F13) -> 65.576325 | G10: =SUM(G11:G13) -> 163.94081 | H10: =SUM(H11:H13) -> 229.51714 | I10: =SUM(I11:I13) -> 295.09346 | J10: =SUM(J11:J13) -> 360.66979 | K10: =SUM(K11:K13) -> 426.24611 | L10: =SUM(L11:L13) -> 491.82244 | ... N10: =SUM(N11:N13) -> 622.97509 | O10: =-PMT('0基本假设 '!$L$34,'0基本假设 '!$L$28,'附表7 银行贷款还本付息表'!$O$6) -> 4740.4766 | P10: =-PMT('0基本假设 '!$L$34,'0基本假设 '!$L$28,'附表7 银行贷款还本付息表'!$O$6) -> 4740.4766 | Q10: =-PMT('0基本假设 '!$L$34,'0基本假设 '!$L$28,'附表7 银行贷款还本付息表'!$O$6) -> 4740.4766 | R10: =-PMT('0基本假设 '!$L$34,'0基本假设 '!$L$28,'附表7 银行贷款还本付息表'!$O$6) -> 4740.4766 | S10: =-PMT('0基本假设 '!$L$34,'0基本假设 '!$L$28,'附表7 银行贷款还本付息表'!$O$6) -> 4740.4766 | T10: =-PMT('0基本假设 '!$L$34,'0基本假设 '!$L$28,'附表7 银行贷款还本付息表'!$O$6) -> 4740.4766 | U10: =-PMT('0基本假设 '!$L$34,'0基本假设 '!$L$28,'附表7 银行贷款还本付息表'!$O$6) -> 4740.4766 | V10: =-PMT('0基本假设 '!$L$34,'0基本假设 '!$L$28,'附表7 银行贷款还本付息表'!$O$6) -> 4740.4766 | ... X10: =-PMT('0基本假设 '!$L$34,'0基本假设 '!$L$28,'附表7 银行贷款还本付息表'!$O$6) -> 4740.4766
B11: 1.5.1 | C11: 其中：还本 | D11: =SUM(E11:X11) -> 43717.55 | O11: =O10-O13 -> 4084.7133 | P11: =P10-P13 -> 4145.984 | Q11: =Q10-Q13 -> 4208.1738 | R11: =R10-R13 -> 4271.2964 | S11: =S10-S13 -> 4335.3659 | T11: =T10-T13 -> 4400.3963 | U11: =U10-U13 -> 4466.4023 | V11: =V10-V13 -> 4533.3983 | ... X11: =X10-X13 -> 4670.4203
B12: 1.5.2 | C12: 支付建设期利息 | D12: =SUM(E12:X12) -> 3213.2399 | E12: =E8 -> 0 | F12: =F8 -> 65.576325 | G12: =G8 -> 163.94081 | H12: =H8 -> 229.51714 | I12: =I8 -> 295.09346 | J12: =J8 -> 360.66979 | K12: =K8 -> 426.24611 | L12: =L8 -> 491.82244 | ... N12: =N8 -> 622.97509
B13: 1.5.3 | C13: 支付运营期利息 | D13: =SUM(E13:X13) -> 3687.2159 | O13: =O6*'0基本假设 '!$L$34 -> 655.76325 | P13: =P6*'0基本假设 '!$L$34 -> 594.49255 | Q13: =Q6*'0基本假设 '!$L$34 -> 532.30279 | R13: =R6*'0基本假设 '!$L$34 -> 469.18018 | S13: =S6*'0基本假设 '!$L$34 -> 405.11074 | T13: =T6*'0基本假设 '!$L$34 -> 340.08025 | U13: =U6*'0基本假设 '!$L$34 -> 274.0743 | V13: =V6*'0基本假设 '!$L$34 -> 207.07827 | ... X13: =X6*'0基本假设 '!$L$34 -> 70.056304
B14: 2 | C14: 期末借款余额 | E14: =E6+E7-E11 -> 0 | F14: =F6+F7-F11 -> 8743.51 | G14: =G6+G7-G11 -> 13115.265 | H14: =H6+H7-H11 -> 17487.02 | I14: =I6+I7-I11 -> 21858.775 | J14: =J6+J7-J11 -> 26230.53 | K14: =K6+K7-K11 -> 30602.285 | L14: =L6+L7-L11 -> 34974.04 | ... X14: =X6+X7-X11 -> 0
B18: 合计
B19: 1.1 | C19: 期初借款累计 | D19: =D6 -> 0 | E19: =E6 -> 0 | F19: =F6 -> 0 | G19: =G6 -> 8743.51 | H19: =H6 -> 13115.265 | I19: =I6 -> 17487.02 | J19: =J6 -> 21858.775 | K19: =K6 -> 26230.53 | ... X19: =X6 -> 4670.4203
B20: 1.2 | C20: 当期借款 | D20: =D7 -> 43717.55 | E20: =E7 -> 0 | F20: =F7 -> 8743.51 | G20: =G7 -> 4371.755 | H20: =H7 -> 4371.755 | I20: =I7 -> 4371.755 | J20: =J7 -> 4371.755 | K20: =K7 -> 4371.755 | ... X20: =X7 -> 0
B21: 1.3 | C21: 当期应计建设期利息 | D21: =D8 -> 3213.2399 | E21: =E8 -> 0 | F21: =F8 -> 65.576325 | G21: =G8 -> 163.94081 | H21: =H8 -> 229.51714 | I21: =I8 -> 295.09346 | J21: =J8 -> 360.66979 | K21: =K8 -> 426.24611 | ... X21: =X8 -> 0
B22: 1.4 | C22: 当期应计运营期利息 | D22: =D9 -> 3687.2159 | E22: =E9 -> 0 | F22: =F9 -> 0 | G22: =G9 -> 0 | H22: =H9 -> 0 | I22: =I9 -> 0 | J22: =J9 -> 0 | K22: =K9 -> 0 | ... X22: =X9 -> 70.056304
B23: 1.5 | C23: 当期还本付息 | D23: =D10 -> 50618.006 | E23: =E10 -> 0 | F23: =F10 -> 65.576325 | G23: =G10 -> 163.94081 | H23: =H10 -> 229.51714 | I23: =I10 -> 295.09346 | J23: =J10 -> 360.66979 | K23: =K10 -> 426.24611 | ... X23: =X10 -> 4740.4766
B24: 1.5.1 | C24: 其中：还本 | D24: =D11 -> 43717.55 | E24: =E11 -> 0 | F24: =F11 -> 0 | G24: =G11 -> 0 | H24: =H11 -> 0 | I24: =I11 -> 0 | J24: =J11 -> 0 | K24: =K11 -> 0 | ... X24: =X11 -> 4670.4203
B25: 1.5.2 | C25: 支付建设期利息 | D25: =D12 -> 3213.2399 | E25: =E12 -> 0 | F25: =F12 -> 65.576325 | G25: =G12 -> 163.94081 | H25: =H12 -> 229.51714 | I25: =I12 -> 295.09346 | J25: =J12 -> 360.66979 | K25: =K12 -> 426.24611 | ... X25: =X12 -> 0
B26: 1.5.3 | C26: 支付运营期利息 | D26: =D13 -> 3687.2159 | E26: =E13 -> 0 | F26: =F13 -> 0 | G26: =G13 -> 0 | H26: =H13 -> 0 | I26: =I13 -> 0 | J26: =J13 -> 0 | K26: =K13 -> 0 | ... X26: =X13 -> 70.056304
B27: 2 | C27: 期末借款余额 | D27: =D14 -> 0 | E27: =E14 -> 0 | F27: =F14 -> 8743.51 | G27: =G14 -> 13115.265 | H27: =H14 -> 17487.02 | I27: =I14 -> 21858.775 | J27: =J14 -> 26230.53 | K27: =K14 -> 30602.285 | ... X27: =X14 -> 0
C29: 提前还本 | O29: ='附表11 财务计划现金流量表'!O34 -> -19622.722 | P29: ='附表11 财务计划现金流量表'!P34 -> 474.24638 | Q29: ='附表11 财务计划现金流量表'!Q34 -> 480.46535 | R29: ='附表11 财务计划现金流量表'!R34 -> 486.77761 | T29: ='附表11 财务计划现金流量表'!#REF! -> #REF! | U29: ='附表11 财务计划现金流量表'!#REF! -> #REF!
C31: 偿债备付率EBITDA/ | D31: =附表9利润表!C50/'附表7 银行贷款还本付息表'!D23 -> 2.1203097 | I31: =附表9利润表!I50/'附表7 银行贷款还本付息表'!I23 -> 29.747611 | J31: =附表9利润表!J50/'附表7 银行贷款还本付息表'!J23 -> 33.816972 | K31: =附表9利润表!K50/'附表7 银行贷款还本付息表'!K23 -> 15.247926 | L31: =附表9利润表!L50/'附表7 银行贷款还本付息表'!L23 -> 8.5811716 | M31: =附表9利润表!M50/'附表7 银行贷款还本付息表'!M23 -> 5.5273437 | N31: =附表9利润表!M50/'附表7 银行贷款还本付息表'!N23 -> 4.9455181 | O31: =附表9利润表!N50/'附表7 银行贷款还本付息表'!O23 -> 0.40954877 | P31: =附表9利润表!O50/'附表7 银行贷款还本付息表'!P23 -> 0.40954877 | Q31: =附表9利润表!P50/'附表7 银行贷款还本付息表'!Q23 -> 0.40954877 | R31: =附表9利润表!Q50/'附表7 银行贷款还本付息表'!R23 -> 0.40954877 | S31: =附表9利润表!R50/'附表7 银行贷款还本付息表'!S23 -> 0.40954877 | T31: =附表9利润表!S50/'附表7 银行贷款还本付息表'!T23 -> 0.40954877 | U31: =附表9利润表!T50/'附表7 银行贷款还本付息表'!U23 -> 0.40954877 | ... X31: =附表9利润表!W50/'附表7 银行贷款还本付息表'!X23 -> 5.0225017
C32: 利息备付率 | D32: =附表9利润表!C19/D26 -> 0.15265587 | E32: =附表9利润表!D19/E26 -> #DIV/0! | F32: =附表9利润表!E19/F26 -> #DIV/0! | G32: =附表9利润表!F19/G26 -> #DIV/0! | H32: =附表9利润表!G19/H26 -> #DIV/0! | I32: =附表9利润表!H19/I26 -> #DIV/0! | J32: =附表9利润表!I19/J26 -> #DIV/0! | K32: =附表9利润表!J19/K26 -> #DIV/0! | ... X32: =附表9利润表!W19/X26 -> 19.16364
B34: 点击返回目录

Sheet 附表8 总成本估算表
B1: 附表8.1 总成本估算表（含税）(单位：万元)
B2: 序号 | C2: 项目 | D2: 合计 | E2: 第1年Q1 | F2: 第1年Q2 | G2: 第1年Q3 | H2: 第1年Q4 | I2: 第2年Q1 | J2: 第2年Q2 | K2: 第2年Q3 | L2: 第2年Q4 | M2: 第3年Q1 | N2: 第3年Q2 | O2: 第3年Q3 | P2: 第3年Q4 | Q2: 第4年Q1 | R2: 第4年Q2 | S2: 第4年Q3 | T2: 第4年Q4 | U2: 第5年Q1 | V2: 第5年Q2 | W2: 第5年Q3 | X2: 第5年Q4
B3: 1 | C3: 经营成本 | D3: =SUM(E3:X3) -> 7697.2536 | E3: ='附表5 运营成本汇总表'!E3 -> 0 | F3: ='附表5 运营成本汇总表'!F3 -> 100 | G3: ='附表5 运营成本汇总表'!G3 -> 100 | H3: ='附表5 运营成本汇总表'!H3 -> 1299.4507 | I3: ='附表5 运营成本汇总表'!I3 -> 567.28029 | J3: ='附表5 运营成本汇总表'!J3 -> 567.28029 | K3: ='附表5 运营成本汇总表'!K3 -> 747.1979 | L3: ='附表5 运营成本汇总表'!L3 -> 447.33522 | ... X3: ='附表5 运营成本汇总表'!X3 -> 1406.8958
B4: 2 | C4: 资产折旧摊销费 | D4: =SUM(E4:X4) -> 106762.97 | E4: ='附表6 资产折旧摊销表'!E15 -> 0 | F4: ='附表6 资产折旧摊销表'!F15 -> 0 | G4: ='附表6 资产折旧摊销表'!G15 -> 0 | H4: ='附表6 资产折旧摊销表'!H15 -> 25292.129 | I4: ='附表6 资产折旧摊销表'!I15 -> 10740.754 | J4: ='附表6 资产折旧摊销表'!J15 -> 10740.754 | K4: ='附表6 资产折旧摊销表'!K15 -> 14054.14 | L4: ='附表6 资产折旧摊销表'!L15 -> 8531.8299 | ... X4: ='附表6 资产折旧摊销表'!X15 -> 22466.518
B5: 3 | C5: 财务费用 | D5: =SUM(E5:X5) -> 3687.2159 | E5: =SUM(E6:E6) -> 0 | F5: =SUM(F6:F6) -> 0 | G5: =SUM(G6:G6) -> 0 | H5: =SUM(H6:H6) -> 0 | I5: =SUM(I6:I6) -> 0 | J5: =SUM(J6:J6) -> 0 | K5: =SUM(K6:K6) -> 0 | L5: =SUM(L6:L6) -> 0 | ... X5: =SUM(X6:X6) -> 70.056304
B6: 3.1 | C6: 利息支出 | D6: =SUM(E6:X6) -> 3687.2159 | E6: ='附表7 银行贷款还本付息表'!E26 -> 0 | F6: ='附表7 银行贷款还本付息表'!F26 -> 0 | G6: ='附表7 银行贷款还本付息表'!G26 -> 0 | H6: ='附表7 银行贷款还本付息表'!H26 -> 0 | I6: ='附表7 银行贷款还本付息表'!I26 -> 0 | J6: ='附表7 银行贷款还本付息表'!J26 -> 0 | K6: ='附表7 银行贷款还本付息表'!K26 -> 0 | L6: ='附表7 银行贷款还本付息表'!L26 -> 0 | ... X6: ='附表7 银行贷款还本付息表'!X26 -> 70.056304
B7: 4 | C7: 总成本费用 | D7: =SUM(E7:X7) -> 118147.44 | E7: =SUM(E3,E4,E5) -> 0 | F7: =SUM(F3,F4,F5) -> 100 | G7: =SUM(G3,G4,G5) -> 100 | H7: =SUM(H3,H4,H5) -> 26591.58 | I7: =SUM(I3,I4,I5) -> 11308.034 | J7: =SUM(J3,J4,J5) -> 11308.034 | K7: =SUM(K3,K4,K5) -> 14801.338 | L7: =SUM(L3,L4,L5) -> 8979.1651 | ... X7: =SUM(X3,X4,X5) -> 23943.47
B9: 附表8.2 总成本估算表（不含税）(单位：万元)
B10: 序号 | C10: 项目 | D10: 合计 | E10: 第1年Q1 | F10: 第1年Q2 | G10: 第1年Q3 | H10: 第1年Q4 | I10: 第2年Q3 | J10: 第2年Q4 | K10: 第3年Q1 | L10: 第3年Q2 | M10: 第3年Q3 | N10: 第3年Q4 | O10: 第4年Q1 | P10: 第4年Q2 | Q10: 第4年Q3 | R10: 第4年Q4 | S10: 第6年Q3 | T10: 第6年Q4 | U10: 第7年Q1 | V10: 第7年Q2 | W10: 第7年Q3 | X10: 第7年Q4
B11: 1 | C11: 经营成本 | D11: =SUM(E11:X11) -> 7261.56 | E11: ='5.1运营成本明细表'!G3/(1+'3.1销售情况分析'!$D$29) -> 0 | F11: ='5.1运营成本明细表'!H3/(1+'3.1销售情况分析'!$D$29) -> 94.339623 | G11: ='5.1运营成本明细表'!I3/(1+'3.1销售情况分析'!$D$29) -> 94.339623 | H11: ='5.1运营成本明细表'!J3/(1+'3.1销售情况分析'!$D$29) -> 1225.8969 | I11: ='5.1运营成本明细表'!K3/(1+'3.1销售情况分析'!$D$29) -> 535.17008 | J11: ='5.1运营成本明细表'!L3/(1+'3.1销售情况分析'!$D$29) -> 535.17008 | K11: ='5.1运营成本明细表'!M3/(1+'3.1销售情况分析'!$D$29) -> 704.90368 | L11: ='5.1运营成本明细表'!N3/(1+'3.1销售情况分析'!$D$29) -> 422.01435 | ... X11: ='5.1运营成本明细表'!Z3/(1+'3.1销售情况分析'!$D$29) -> 1327.2602
B12: 2 | C12: 资产折旧摊销费 | D12: =SUM(E12:X12) -> 106762.97 | E12: ='附表6 资产折旧摊销表'!E15 -> 0 | F12: ='附表6 资产折旧摊销表'!F15 -> 0 | G12: ='附表6 资产折旧摊销表'!G15 -> 0 | H12: ='附表6 资产折旧摊销表'!H15 -> 25292.129 | I12: ='附表6 资产折旧摊销表'!I15 -> 10740.754 | J12: ='附表6 资产折旧摊销表'!J15 -> 10740.754 | K12: ='附表6 资产折旧摊销表'!K15 -> 14054.14 | L12: ='附表6 资产折旧摊销表'!L15 -> 8531.8299 | ... X12: ='附表6 资产折旧摊销表'!X15 -> 22466.518
B13: 3 | C13: 财务费用 | D13: =SUM(E13:X13) -> 3687.2159 | E13: =E5 -> 0 | F13: =F5 -> 0 | G13: =G5 -> 0 | H13: =H5 -> 0 | I13: =I5 -> 0 | J13: =J5 -> 0 | K13: =K5 -> 0 | L13: =L5 -> 0 | ... X13: =X5 -> 70.056304
B14: 3.1 | C14: 利息支出 | D14: =SUM(E14:X14) -> 3687.2159 | E14: =E6 -> 0 | F14: =F6 -> 0 | G14: =G6 -> 0 | H14: =H6 -> 0 | I14: =I6 -> 0 | J14: =J6 -> 0 | K14: =K6 -> 0 | L14: =L6 -> 0 | ... X14: =X6 -> 70.056304
B15: 4 | C15: 总成本费用 | D15: =SUM(E15:X15) -> 117711.75 | E15: =SUM(E11,E12,E13) -> 0 | F15: =SUM(F11,F12,F13) -> 94.339623 | G15: =SUM(G11,G12,G13) -> 94.339623 | H15: =SUM(H11,H12,H13) -> 26518.026 | I15: =SUM(I11,I12,I13) -> 11275.924 | J15: =SUM(J11,J12,J13) -> 11275.924 | K15: =SUM(K11,K12,K13) -> 14759.044 | L15: =SUM(L11,L12,L13) -> 8953.8443 | ... X15: =SUM(X11,X12,X13) -> 23863.834
B17: 点击返回目录

Sheet 附表9利润表
B2: 附表9.1 利润表 (单位：万元)
B3: 项目 | C3: 合计 | D3: 第1年Q1 | E3: 第1年Q2 | F3: 第1年Q3 | G3: 第1年Q4 | H3: 第2年Q1 | I3: 第2年Q2 | J3: 第2年Q3 | K3: 第2年Q4 | L3: 第3年Q1 | M3: 第3年Q2 | N3: 第3年Q3 | O3: 第3年Q4 | P3: 第4年Q1 | Q3: 第4年Q2 | R3: 第4年Q3 | S3: 第4年Q4 | T3: 第5年Q1 | U3: 第5年Q2 | V3: 第5年Q3 | W3: 第5年Q4
B4: 销售收入（1） | C4: =SUM(D4:W4) -> 115945.07 | D4: ='3.1销售情况分析'!G3 -> 0 | E4: ='3.1销售情况分析'!H3 -> 0 | F4: ='3.1销售情况分析'!I3 -> 0 | G4: ='3.1销售情况分析'!J3 -> 23989.014 | H4: ='3.1销售情况分析'!K3 -> 9345.6058 | I4: ='3.1销售情况分析'!L3 -> 9345.6058 | J4: ='3.1销售情况分析'!M3 -> 12943.958 | K4: ='3.1销售情况分析'!N3 -> 6946.7043 | ... W4: ='3.1销售情况分析'!Z3 -> 26137.916
B5: 税金及附加（2） | C5: =SUM(D5:W5) -> 921.96832 | D5: ='3.1销售情况分析'!G4 -> 0 | E5: ='3.1销售情况分析'!H4 -> 0 | F5: ='3.1销售情况分析'!I4 -> 0 | G5: ='3.1销售情况分析'!J4 -> 0 | H5: ='3.1销售情况分析'!K4 -> 0 | I5: ='3.1销售情况分析'!L4 -> 0 | J5: ='3.1销售情况分析'!M4 -> 0 | K5: ='3.1销售情况分析'!N4 -> 0 | ... W5: ='3.1销售情况分析'!Z4 -> 921.96832
B6: 总成本费用（3） | C6: =SUM(D6:W6) -> 118147.44 | D6: ='附表8 总成本估算表'!E7 -> 0 | E6: ='附表8 总成本估算表'!F7 -> 100 | F6: ='附表8 总成本估算表'!G7 -> 100 | G6: ='附表8 总成本估算表'!H7 -> 26591.58 | H6: ='附表8 总成本估算表'!I7 -> 11308.034 | I6: ='附表8 总成本估算表'!J7 -> 11308.034 | J6: ='附表8 总成本估算表'!K7 -> 14801.338 | K6: ='附表8 总成本估算表'!L7 -> 8979.1651 | ... W6: ='附表8 总成本估算表'!X7 -> 23943.47
B7: 其他收入（4） | C7: =SUM(D7:W7) -> 0 | D7: =附表3营业收入汇总表!D6 -> 0 | E7: =附表3营业收入汇总表!E6 -> 0 | F7: =附表3营业收入汇总表!F6 -> 0 | G7: =附表3营业收入汇总表!G6 -> 0 | H7: =附表3营业收入汇总表!H6 -> 0 | I7: =附表3营业收入汇总表!I6 -> 0 | J7: =附表3营业收入汇总表!J6 -> 0 | K7: =附表3营业收入汇总表!K6 -> 0 | ... W7: =附表3营业收入汇总表!W6 -> 0
B8: 利润总额(5) （1-2-3+4） | C8: =SUM(D8:W8) -> -3124.3408 | D8: =D4-D5-D6+D7 -> 0 | E8: =E4-E5-E6+E7 -> -100 | F8: =F4-F5-F6+F7 -> -100 | G8: =G4-G5-G6+G7 -> -2602.5657 | H8: =H4-H5-H6+H7 -> -1962.4285 | I8: =I4-I5-I6+I7 -> -1962.4285 | J8: =J4-J5-J6+J7 -> -1857.3799 | K8: =K4-K5-K6+K7 -> -2032.4608 | ... W8: =W4-W5-W6+W7 -> 1272.4775
B9: 弥补前年度亏损额（6） | C9: =SUM(D9:W9) -> 11732.925 | F9: =IF(F8<0,0,IF(AND(SUM($D$8:E8)<0,ABS(SUM($D$8:E8))>F8),F8,IF(AND(SUM($D$8:E8)<0,ABS(SUM($D$8:E8))<F8),ABS(SUM($D$8:E8)),0))) -> 0 | G9: =IF(G8<0,0,IF(AND(SUM($D$8:F8)<0,ABS(SUM($D$8:F8))>G8),G8,IF(AND(SUM($D$8:F8)<0,ABS(SUM($D$8:F8))<G8),ABS(SUM($D$8:F8)),0))) -> 0 | H9: =IF(H8<0,0,IF(AND(SUM($D$8:G8)<0,ABS(SUM($D$8:G8))>H8),H8,IF(AND(SUM($D$8:G8)<0,ABS(SUM($D$8:G8))<H8),ABS(SUM($D$8:G8)),0))) -> 0 | I9: =IF(I8<0,0,IF(AND(SUM($D$8:H8)<0,ABS(SUM($D$8:H8))>I8),I8,IF(AND(SUM($D$8:H8)<0,ABS(SUM($D$8:H8))<I8),ABS(SUM($D$8:H8)),0))) -> 0 | J9: =IF(J8<0,0,IF(AND(SUM($D$8:I8)<0,ABS(SUM($D$8:I8))>J8),J8,IF(AND(SUM($D$8:I8)<0,ABS(SUM($D$8:I8))<J8),ABS(SUM($D$8:I8)),0))) -> 0 | K9: =IF(K8<0,0,IF(AND(SUM($D$8:J8)<0,ABS(SUM($D$8:J8))>K8),K8,IF(AND(SUM($D$8:J8)<0,ABS(SUM($D$8:J8))<K8),ABS(SUM($D$8:J8)),0))) -> 0 | L9: =IF(L8<0,0,IF(AND(SUM($D$8:K8)<0,ABS(SUM($D$8:K8))>L8),L8,IF(AND(SUM($D$8:K8)<0,ABS(SUM($D$8:K8))<L8),ABS(SUM($D$8:K8)),0))) -> 0 | M9: =IF(M8<0,0,IF(AND(SUM($D$8:L8)<0,ABS(SUM($D$8:L8))>M8),M8,IF(AND(SUM($D$8:L8)<0,ABS(SUM($D$8:L8))<M8),ABS(SUM($D$8:L8)),0))) -> 0 | ... W9: =IF(W8<0,0,IF(AND(SUM($D$8:V8)<0,ABS(SUM($D$8:V8))>W8),W8,IF(AND(SUM($D$8:V8)<0,ABS(SUM($D$8:V8))<W8),ABS(SUM($D$8:V8)),0))) -> 1272.4775
B10: 应纳所得税额(7) （5-6） | C10: =SUM(D10:W10) -> 0 | D10: =IF(D8-D9>0,D8-D9,0) -> 0 | E10: =IF(E8-E9>0,E8-E9,0) -> 0 | F10: =IF(F8-F9>0,F8-F9,0) -> 0 | G10: =IF(G8-G9>0,G8-G9,0) -> 0 | H10: =IF(H8-H9>0,H8-H9,0) -> 0 | I10: =IF(I8-I9>0,I8-I9,0) -> 0 | J10: =IF(J8-J9>0,J8-J9,0) -> 0 | K10: =IF(K8-K9>0,K8-K9,0) -> 0 | ... W10: =IF(W8-W9>0,W8-W9,0) -> 0
B11: 所得税(8) （7）*15% | C11: =SUM(D11:W11) -> 0 | D11: =IF(D10>0,D10*'0基本假设 '!$L$41,0) -> 0 | E11: =IF(E10>0,E10*'0基本假设 '!$L$41,0) -> 0 | F11: =IF(F10>0,F10*'0基本假设 '!$L$41,0) -> 0 | G11: =IF(G10>0,G10*'0基本假设 '!$L$41,0) -> 0 | H11: =IF(H10>0,H10*'0基本假设 '!$L$41,0) -> 0 | I11: =IF(I10>0,I10*'0基本假设 '!$L$41,0) -> 0 | J11: =IF(J10>0,J10*'0基本假设 '!$L$41,0) -> 0 | K11: =IF(K10>0,K10*'0基本假设 '!$L$41,0) -> 0 | ... W11: =IF(W10>0,W10*'0基本假设 '!$L$41,0) -> 0
B12: 净利润(9) （5）-（8） | C12: =SUM(D12:W12) -> -3124.3408 | D12: =D8-D11 -> 0 | E12: =E8-E11 -> -100 | F12: =F8-F11 -> -100 | G12: =G8-G11 -> -2602.5657 | H12: =H8-H11 -> -1962.4285 | I12: =I8-I11 -> -1962.4285 | J12: =J8-J11 -> -1857.3799 | K12: =K8-K11 -> -2032.4608 | ... W12: =W8-W11 -> 1272.4775
B13: 期初未分配利润(10) | C13: =SUM(D13:W13) -> 0 | D13: 0 | E13: =D18 -> 0 | F13: =E18 -> 0 | G13: =F18 -> 0 | H13: =G18 -> 0 | I13: =H18 -> 0 | J13: =I18 -> 0 | K13: =J18 -> 0 | L13: =K18 -> 0 | ... W13: =V18 -> 0
B14: 可供分配利润(9+10) （利润的10%提作公积金） | C14: =SUM(D14:W14) -> 11732.925 | D14: =IF(D12+D13>0,D12+D13,0) -> 0 | E14: =IF(E12+E13>0,E12+E13,0) -> 0 | F14: =IF(F12+F13>0,F12+F13,0) -> 0 | G14: =IF(G12+G13>0,G12+G13,0) -> 0 | H14: =IF(H12+H13>0,H12+H13,0) -> 0 | I14: =IF(I12+I13>0,I12+I13,0) -> 0 | J14: =IF(J12+J13>0,J12+J13,0) -> 0 | K14: =IF(K12+K13>0,K12+K13,0) -> 0 | ... W14: =IF(W12+W13>0,W12+W13,0) -> 1272.4775
B15: 提取法定盈余公积金 暂按中国法规定，不少于50% | C15: =SUM(D15:W15) -> 500 | D15: 0 | E15: =IF(D16+(IF(E14>0,E14*0.1,0))>'0基本假设 '!$L$13*50%,'0基本假设 '!$L$13*50%-D16,IF(E14>0,E14*0.1,0)) -> 0 | F15: =IF(E16+(IF(F14>0,F14*0.1,0))>'0基本假设 '!$L$13*50%,'0基本假设 '!$L$13*50%-E16,IF(F14>0,F14*0.1,0)) -> 0 | G15: =IF(F16+(IF(G14>0,G14*0.1,0))>'0基本假设 '!$L$13*50%,'0基本假设 '!$L$13*50%-F16,IF(G14>0,G14*0.1,0)) -> 0 | H15: =IF(G16+(IF(H14>0,H14*0.1,0))>'0基本假设 '!$L$13*50%,'0基本假设 '!$L$13*50%-G16,IF(H14>0,H14*0.1,0)) -> 0 | I15: =IF(H16+(IF(I14>0,I14*0.1,0))>'0基本假设 '!$L$13*50%,'0基本假设 '!$L$13*50%-H16,IF(I14>0,I14*0.1,0)) -> 0 | J15: =IF(I16+(IF(J14>0,J14*0.1,0))>'0基本假设 '!$L$13*50%,'0基本假设 '!$L$13*50%-I16,IF(J14>0,J14*0.1,0)) -> 0 | K15: =IF(J16+(IF(K14>0,K14*0.1,0))>'0基本假设 '!$L$13*50%,'0基本假设 '!$L$13*50%-J16,IF(K14>0,K14*0.1,0)) -> 0 | L15: =IF(K16+(IF(L14>0,L14*0.1,0))>'0基本假设 '!$L$13*50%,'0基本假设 '!$L$13*50%-K16,IF(L14>0,L14*0.1,0)) -> 0 | ... W15: =IF(V16+(IF(W14>0,W14*0.1,0))>'0基本假设 '!$L$13*50%,'0基本假设 '!$L$13*50%-V16,IF(W14>0,W14*0.1,0)) -> 0
B16: 累计法定盈余公积 （如果累计公积金达到注册资本金的50%，则无需再提盈余公积金，累计公积金小于等于50%） | D16: =D15 -> 0 | E16: =D16+E15 -> 0 | F16: =E16+F15 -> 0 | G16: =F16+G15 -> 0 | H16: =G16+H15 -> 0 | I16: =H16+I15 -> 0 | J16: =I16+J15 -> 0 | K16: =J16+K15 -> 0 | L16: =K16+L15 -> 0 | ... W16: =V16+W15 -> 500
B17: 投资方利润分配 | C17: =SUM(D17:W17) -> -3624.3408 | D17: =D12+D13-D15 -> 0 | E17: =E12+E13-E15 -> -100 | F17: =F12+F13-F15 -> -100 | G17: =G12+G13-G15 -> -2602.5657 | H17: =H12+H13-H15 -> -1962.4285 | I17: =I12+I13-I15 -> -1962.4285 | J17: =J12+J13-J15 -> -1857.3799 | K17: =K12+K13-K15 -> -2032.4608 | ... W17: =W12+W13-W15 -> 1272.4775
B18: 期末未分配利润 | C18: =SUM(D18:W18) -> 0 | D18: =D12+D13-D15-D17 -> 0 | E18: =E12+E13-E15-E17 -> 0 | F18: =F12+F13-F15-F17 -> 0 | G18: =G12+G13-G15-G17 -> 0 | H18: =H12+H13-H15-H17 -> 0 | I18: =I12+I13-I15-I17 -> 0 | J18: =J12+J13-J15-J17 -> 0 | K18: =K12+K13-K15-K17 -> 0 | ... W18: =W12+W13-W15-W17 -> 0
B19: 息税前利润EBIT | C19: =SUM(D19:W19) -> 562.87516 | D19: ='附表7 银行贷款还本付息表'!E26+D8 -> 0 | E19: ='附表7 银行贷款还本付息表'!F26+E8 -> -100 | F19: ='附表7 银行贷款还本付息表'!G26+F8 -> -100 | G19: ='附表7 银行贷款还本付息表'!H26+G8 -> -2602.5657 | H19: ='附表7 银行贷款还本付息表'!I26+H8 -> -1962.4285 | I19: ='附表7 银行贷款还本付息表'!J26+I8 -> -1962.4285 | J19: ='附表7 银行贷款还本付息表'!K26+J8 -> -1857.3799 | K19: ='附表7 银行贷款还本付息表'!L26+K8 -> -2032.4608 | ... W19: ='附表7 银行贷款还本付息表'!X26+W8 -> 1342.5338
B20: 息税折旧前利润EBITDA | C20: =SUM(D20:W20) -> 107325.85 | D20: =D19+'附表6 资产折旧摊销表'!E15 -> 0 | E20: =E19+'附表6 资产折旧摊销表'!F15 -> -100 | F20: =F19+'附表6 资产折旧摊销表'!G15 -> -100 | G20: =G19+'附表6 资产折旧摊销表'!H15 -> 22689.564 | H20: =H19+'附表6 资产折旧摊销表'!I15 -> 8778.3255 | I20: =I19+'附表6 资产折旧摊销表'!J15 -> 8778.3255 | J20: =J19+'附表6 资产折旧摊销表'!K15 -> 12196.76 | K20: =K19+'附表6 资产折旧摊销表'!L15 -> 6499.3691 | ... W20: =W19+'附表6 资产折旧摊销表'!X15 -> 23809.052
B22: 弥补以前年度亏损额的计算过程 | C22: 当期留抵弥补亏损额 | N22: =IF(N8<0,N8,0) -> 0 | O22: =IF(O8<0,O8,0) -> 0 | P22: =IF(P8<0,P8,0) -> 0 | Q22: =IF(Q8<0,Q8,0) -> 0
C23: 前期留抵弥补亏损额抵扣当期应纳所得额 | N23: =N9 -> 908.41535 | O23: =O9 -> 969.68605 | P23: =P9 -> 1031.8758 | Q23: =Q9 -> 1094.9984
C24: 5年内抵扣应纳所得额 | N24: =IF(N22<0,SUMIF(O8:Q8,">0"),0) -> 0 | O24: =IF(O22<0,SUMIF(P8:Q8,">0"),0) -> 0 | P24: =IF(P22<0,SUMIF(Q8:Q8,">0"),0) -> 0 | Q24: =IF(Q22<0,SUMIF(#REF!,">0"),0) -> 0
C25: 重复抵扣额度
C26: 实际抵扣额度 | N26: =IF(N24-N25<=ABS(N22),N24-N25,ABS(N22)) -> 0 | O26: =IF(O24-O25<=ABS(O22),O24-O25,ABS(O22)) -> 0 | P26: =IF(P24-P25<=ABS(P22),P24-P25,ABS(P22)) -> 0 | Q26: =IF(Q24-Q25<=ABS(Q22),Q24-Q25,ABS(Q22)) -> 0
C27: 5年内未弥补的亏损额 | N27: =N22+N26 -> 0 | O27: =O22+O26 -> 0 | P27: =P22+P26 -> 0 | Q27: =Q22+Q26 -> 0
C28: 剩余留抵弥补亏损额 | N28: =M28+N22+N23 -> 908.41535 | O28: =N28+O22+O23 -> 1878.1014 | P28: =O28+P22+P23 -> 2909.9772 | Q28: =P28+Q22+Q23 -> 4004.9756
B30: 注释：项目全投资现金流量表调整所得税采用融资前利润表所得税
B31: 附表9.2 利润表（融资前）(单位：万元)
B32: 项目 | C32: 合计 | D32: 第1年Q1 | E32: 第1年Q2 | F32: 第1年Q3 | G32: 第1年Q4 | H32: 第2年Q3 | I32: 第2年Q4 | J32: 第3年Q1 | K32: 第3年Q2 | L32: 第3年Q3 | M32: 第3年Q4 | N32: 第4年Q1 | O32: 第4年Q2 | P32: 第4年Q3 | Q32: 第4年Q4 | R32: 第6年Q3 | S32: 第6年Q4 | T32: 第7年Q1 | U32: 第7年Q2 | V32: 第7年Q3 | W32: 第7年Q4
B33: 营运收入（1） | C33: =SUM(D33:W33) -> 115945.07 | D33: ='3.1销售情况分析'!G3 -> 0 | E33: ='3.1销售情况分析'!H3 -> 0 | F33: ='3.1销售情况分析'!I3 -> 0 | G33: ='3.1销售情况分析'!J3 -> 23989.014 | H33: ='3.1销售情况分析'!K3 -> 9345.6058 | I33: ='3.1销售情况分析'!L3 -> 9345.6058 | J33: ='3.1销售情况分析'!M3 -> 12943.958 | K33: ='3.1销售情况分析'!N3 -> 6946.7043 | ... W33: ='3.1销售情况分析'!Z3 -> 26137.916
B34: 税金及附加（2） | C34: =SUM(D34:W34) -> 921.96832 | D34: =D5 -> 0 | E34: =E5 -> 0 | F34: =F5 -> 0 | G34: =G5 -> 0 | H34: =H5 -> 0 | I34: =I5 -> 0 | J34: =J5 -> 0 | K34: =K5 -> 0 | ... W34: =W5 -> 921.96832
B35: 总成本费用（3） | C35: =SUM(D35:W35) -> 114460.23 | D35: ='附表8 总成本估算表'!E7-'附表8 总成本估算表'!E5 -> 0 | E35: ='附表8 总成本估算表'!F7-'附表8 总成本估算表'!F5 -> 100 | F35: ='附表8 总成本估算表'!G7-'附表8 总成本估算表'!G5 -> 100 | G35: ='附表8 总成本估算表'!H7-'附表8 总成本估算表'!H5 -> 26591.58 | H35: ='附表8 总成本估算表'!I7-'附表8 总成本估算表'!I5 -> 11308.034 | I35: ='附表8 总成本估算表'!J7-'附表8 总成本估算表'!J5 -> 11308.034 | J35: ='附表8 总成本估算表'!K7-'附表8 总成本估算表'!K5 -> 14801.338 | K35: ='附表8 总成本估算表'!L7-'附表8 总成本估算表'!L5 -> 8979.1651 | ... W35: ='附表8 总成本估算表'!X7-'附表8 总成本估算表'!X5 -> 23873.414
B36: 可行性缺口补助（4） | C36: =SUM(D36:W36) -> 0 | D36: =附表3营业收入汇总表!D6 -> 0 | E36: =附表3营业收入汇总表!E6 -> 0 | F36: =附表3营业收入汇总表!F6 -> 0 | G36: =附表3营业收入汇总表!G6 -> 0 | H36: =附表3营业收入汇总表!H6 -> 0 | I36: =附表3营业收入汇总表!I6 -> 0 | J36: =附表3营业收入汇总表!J6 -> 0 | K36: =附表3营业收入汇总表!K6 -> 0 | ... W36: =附表3营业收入汇总表!W6 -> 0
B37: 利润总额(5) （1-2-3+4） | C37: =SUM(D37:W37) -> 562.87516 | D37: =D33-D34-D35+D36 -> 0 | E37: =E33-E34-E35+E36 -> -100 | F37: =F33-F34-F35+F36 -> -100 | G37: =G33-G34-G35+G36 -> -2602.5657 | H37: =H33-H34-H35+H36 -> -1962.4285 | I37: =I33-I34-I35+I36 -> -1962.4285 | J37: =J33-J34-J35+J36 -> -1857.3799 | K37: =K33-K34-K35+K36 -> -2032.4608 | ... W37: =W33-W34-W35+W36 -> 1342.5338
B38: 弥补前年度亏损额（6） | C38: =SUM(D38:W38) -> 14857.266 | D38: =IF(D37<0,0,IF(AND(SUM( C$37:$D37)<0,ABS(SUM( C$37:$D37))>D37),D37,IF(AND(SUM( C$37:$D37)<0,ABS(SUM( C$37:$D37))<D37),ABS(SUM( C$37:$D37)),0))) -> 0 | E38: =IF(E37<0,0,IF(AND(SUM( $D$37:D37)<0,ABS(SUM( $D$37:D37))>E37),E37,IF(AND(SUM( $D$37:D37)<0,ABS(SUM( $D$37:D37))<E37),ABS(SUM( $D$37:D37)),0))) -> 0 | F38: =IF(F37<0,0,IF(AND(SUM( $D$37:E37)<0,ABS(SUM( $D$37:E37))>F37),F37,IF(AND(SUM( $D$37:E37)<0,ABS(SUM( $D$37:E37))<F37),ABS(SUM( $D$37:E37)),0))) -> 0 | G38: =IF(G37<0,0,IF(AND(SUM( $D$37:F37)<0,ABS(SUM( $D$37:F37))>G37),G37,IF(AND(SUM( $D$37:F37)<0,ABS(SUM( $D$37:F37))<G37),ABS(SUM( $D$37:F37)),0))) -> 0 | H38: =IF(H37<0,0,IF(AND(SUM( $D$37:G37)<0,ABS(SUM( $D$37:G37))>H37),H37,IF(AND(SUM( $D$37:G37)<0,ABS(SUM( $D$37:G37))<H37),ABS(SUM( $D$37:G37)),0))) -> 0 | I38: =IF(I37<0,0,IF(AND(SUM( $D$37:H37)<0,ABS(SUM( $D$37:H37))>I37),I37,IF(AND(SUM( $D$37:H37)<0,ABS(SUM( $D$37:H37))<I37),ABS(SUM( $D$37:H37)),0))) -> 0 | J38: =IF(J37<0,0,IF(AND(SUM( $D$37:I37)<0,ABS(SUM( $D$37:I37))>J37),J37,IF(AND(SUM( $D$37:I37)<0,ABS(SUM( $D$37:I37))<J37),ABS(SUM( $D$37:I37)),0))) -> 0 | K38: =IF(K37<0,0,IF(AND(SUM( $D$37:J37)<0,ABS(SUM( $D$37:J37))>K37),K37,IF(AND(SUM( $D$37:J37)<0,ABS(SUM( $D$37:J37))<K37),ABS(SUM( $D$37:J37)),0))) -> 0 | L38: =IF(L37<0,0,IF(AND(SUM( $D$37:K37)<0,ABS(SUM( $D$37:K37))>L37),L37,IF(AND(SUM( $D$37:K37)<0,ABS(SUM( $D$37:K37))<L37),ABS(SUM( $D$37:K37)),0))) -> 0 | ... W38: =IF(W37<0,0,IF(AND(SUM( $D$37:V37)<0,ABS(SUM( $D$37:V37))>W37),W37,IF(AND(SUM( $D$37:V37)<0,ABS(SUM( $D$37:V37))<W37),ABS(SUM( $D$37:V37)),0))) -> 779.65862
B39: 应纳所得税额(7) （5-6） | C39: =SUM(D39:W39) -> -14294.391 | D39: =D37-D38 -> 0 | E39: =E37-E38 -> -100 | F39: =F37-F38 -> -100 | G39: =G37-G38 -> -2602.5657 | H39: =H37-H38 -> -1962.4285 | I39: =I37-I38 -> -1962.4285 | J39: =J37-J38 -> -1857.3799 | K39: =K37-K38 -> -2032.4608 | ... W39: =W37-W38 -> 562.87516
B40: 所得税(8) （7）*15% | C40: =SUM(D40:W40) -> 140.71879 | D40: =IF(D39>0,D39*'0基本假设 '!$L$41,0) -> 0 | E40: =IF(E39>0,E39*'0基本假设 '!$L$41,0) -> 0 | F40: =IF(F39>0,F39*'0基本假设 '!$L$41,0) -> 0 | G40: =IF(G39>0,G39*'0基本假设 '!$L$41,0) -> 0 | H40: =IF(H39>0,H39*'0基本假设 '!$L$41,0) -> 0 | I40: =IF(I39>0,I39*'0基本假设 '!$L$41,0) -> 0 | J40: =IF(J39>0,J39*'0基本假设 '!$L$41,0) -> 0 | K40: =IF(K39>0,K39*'0基本假设 '!$L$41,0) -> 0 | ... W40: =IF(W39>0,W39*'0基本假设 '!$L$41,0) -> 140.71879
B41: 净利润(9) （5）-（7） | C41: =SUM(D41:W41) -> 422.15637 | D41: =D37-D40 -> 0 | E41: =E37-E40 -> -100 | F41: =F37-F40 -> -100 | G41: =G37-G40 -> -2602.5657 | H41: =H37-H40 -> -1962.4285 | I41: =I37-I40 -> -1962.4285 | J41: =J37-J40 -> -1857.3799 | K41: =K37-K40 -> -2032.4608 | ... W41: =W37-W40 -> 1201.815
B42: 期初未分配利润(10) | C42: =SUM(D42:W42) -> 0 | E42: =D48 -> 0 | F42: =E48 -> 0 | G42: =F48 -> 0 | H42: =G48 -> 0 | I42: =H48 -> 0 | J42: =I48 -> 0 | K42: =J48 -> 0 | L42: =K48 -> 0 | ... W42: =V48 -> 0
B43: 可供分配利润(9+10) | C43: =SUM(D43:W43) -> 422.15637 | D43: =D41+D42 -> 0 | E43: =E41+E42 -> -100 | F43: =F41+F42 -> -100 | G43: =G41+G42 -> -2602.5657 | H43: =H41+H42 -> -1962.4285 | I43: =I41+I42 -> -1962.4285 | J43: =J41+J42 -> -1857.3799 | K43: =K41+K42 -> -2032.4608 | ... W43: =W41+W42 -> 1201.815
B44: 提取法定盈余公积金（10） | C44: =SUM(D44:W44) -> 500 | D44: =IF(D43>0,D41*0.1,0) -> 0 | E44: =IF(D45+(IF(E43>0,E43*0.1,0))>'0基本假设 '!$L$13*50%,'0基本假设 '!$L$13*50%-D45,IF(E43>0,E43*0.1,0)) -> 0 | F44: =IF(E45+(IF(F43>0,F43*0.1,0))>'0基本假设 '!$L$13*50%,'0基本假设 '!$L$13*50%-E45,IF(F43>0,F43*0.1,0)) -> 0 | G44: =IF(F45+(IF(G43>0,G43*0.1,0))>'0基本假设 '!$L$13*50%,'0基本假设 '!$L$13*50%-F45,IF(G43>0,G43*0.1,0)) -> 0 | H44: =IF(G45+(IF(H43>0,H43*0.1,0))>'0基本假设 '!$L$13*50%,'0基本假设 '!$L$13*50%-G45,IF(H43>0,H43*0.1,0)) -> 0 | I44: =IF(H45+(IF(I43>0,I43*0.1,0))>'0基本假设 '!$L$13*50%,'0基本假设 '!$L$13*50%-H45,IF(I43>0,I43*0.1,0)) -> 0 | J44: =IF(I45+(IF(J43>0,J43*0.1,0))>'0基本假设 '!$L$13*50%,'0基本假设 '!$L$13*50%-I45,IF(J43>0,J43*0.1,0)) -> 0 | K44: =IF(J45+(IF(K43>0,K43*0.1,0))>'0基本假设 '!$L$13*50%,'0基本假设 '!$L$13*50%-J45,IF(K43>0,K43*0.1,0)) -> 0 | L44: =IF(K45+(IF(L43>0,L43*0.1,0))>'0基本假设 '!$L$13*50%,'0基本假设 '!$L$13*50%-K45,IF(L43>0,L43*0.1,0)) -> 0 | ... W44: =IF(V45+(IF(W43>0,W43*0.1,0))>'0基本假设 '!$L$13*50%,'0基本假设 '!$L$13*50%-V45,IF(W43>0,W43*0.1,0)) -> 0
B45: 累计法定盈余公积 （如果累计公积金达到注册资本金的50%，则无需再提盈余公积金，累计公积金小于等于50%） | D45: =D44 -> 0 | E45: =D45+E44 -> 0 | F45: =E45+F44 -> 0 | G45: =F45+G44 -> 0 | H45: =G45+H44 -> 0 | I45: =H45+I44 -> 0 | J45: =I45+J44 -> 0 | K45: =J45+K44 -> 0 | L45: =K45+L44 -> 0 | ... W45: =V45+W44 -> 500
B46: 可供投资者分配利润(8-9) | C46: =SUM(D46:W46) -> -77.843633 | D46: =D43-D44 -> 0 | E46: =E43-E44 -> -100 | F46: =F43-F44 -> -100 | G46: =G43-G44 -> -2602.5657 | H46: =H43-H44 -> -1962.4285 | I46: =I43-I44 -> -1962.4285 | J46: =J43-J44 -> -1857.3799 | K46: =K43-K44 -> -2032.4608 | ... W46: =W43-W44 -> 1201.815
B47: 应付利润 | C47: =SUM(D47:W47) -> 0
B48: 未分配利润 | C48: =SUM(D48:W48) -> 0 | D48: =D41+D42-D44-D46 -> 0 | E48: =E41+E42-E44-E46 -> 0 | F48: =F41+F42-F44-F46 -> 0 | G48: =G41+G42-G44-G46 -> 0 | H48: =H41+H42-H44-H46 -> 0 | I48: =I41+I42-I44-I46 -> 0 | J48: =J41+J42-J44-J46 -> 0 | K48: =K41+K42-K44-K46 -> 0 | ... W48: =W41+W42-W44-W46 -> 0
B49: 息税前利润 | C49: =SUM(D49:W49) -> 562.87516 | D49: =D41+D40 -> 0 | E49: =E41+E40 -> -100 | F49: =F41+F40 -> -100 | G49: =G41+G40 -> -2602.5657 | H49: =H41+H40 -> -1962.4285 | I49: =I41+I40 -> -1962.4285 | J49: =J41+J40 -> -1857.3799 | K49: =K41+K40 -> -2032.4608 | ... W49: =W41+W40 -> 1342.5338
B50: 息税折旧前利润 | C50: =SUM(D50:W50) -> 107325.85 | D50: =D49+'附表6 资产折旧摊销表'!E15 -> 0 | E50: =E49+'附表6 资产折旧摊销表'!F15 -> -100 | F50: =F49+'附表6 资产折旧摊销表'!G15 -> -100 | G50: =G49+'附表6 资产折旧摊销表'!H15 -> 22689.564 | H50: =H49+'附表6 资产折旧摊销表'!I15 -> 8778.3255 | I50: =I49+'附表6 资产折旧摊销表'!J15 -> 8778.3255 | J50: =J49+'附表6 资产折旧摊销表'!K15 -> 12196.76 | K50: =K49+'附表6 资产折旧摊销表'!L15 -> 6499.3691 | ... W50: =W49+'附表6 资产折旧摊销表'!X15 -> 23809.052
B53: 点击返回目录

Sheet 附表10 资金来源与运用表
A1: 附表10 资金来源与运用表 (单位：万元)
A2: 序号 | B2: 项目 | C2: 合计 | D2: 第1年Q1 | E2: 第1年Q2 | F2: 第1年Q3 | G2: 第1年Q4 | H2: 第2年Q1 | I2: 第2年Q2 | J2: 第2年Q3 | K2: 第2年Q4 | L2: 第3年Q1 | M2: 第3年Q2 | N2: 第3年Q3 | O2: 第3年Q4 | P2: 第4年Q1 | Q2: 第4年Q2 | R2: 第4年Q3 | S2: 第4年Q4 | T2: 第5年Q1 | U2: 第5年Q2 | V2: 第5年Q3 | W2: 第5年Q4
A3: 1 | B3: 现金来源 | C3: =SUM(D3:W3) -> 222708.05 | D3: =SUM(D4:D11) -> 59832.185 | E3: =SUM(E4:E11) -> 8809.0863 | F3: =SUM(F4:F11) -> 4535.6958 | G3: =SUM(G4:G11) -> 28590.287 | H3: =SUM(H4:H11) -> 14012.454 | I3: =SUM(I4:I11) -> 14078.031 | J3: =SUM(J4:J11) -> 17741.959 | K3: =SUM(K4:K11) -> 11810.282 | ... W3: =SUM(W4:W11) -> 26137.916
A4: 1.1 | B4: 销售收入（含税） | C4: =SUM(D4:W4) -> 115945.07 | D4: ='3.1销售情况分析'!G3 -> 0 | E4: ='3.1销售情况分析'!H3 -> 0 | F4: ='3.1销售情况分析'!I3 -> 0 | G4: ='3.1销售情况分析'!J3 -> 23989.014 | H4: ='3.1销售情况分析'!K3 -> 9345.6058 | I4: ='3.1销售情况分析'!L3 -> 9345.6058 | J4: ='3.1销售情况分析'!M3 -> 12943.958 | K4: ='3.1销售情况分析'!N3 -> 6946.7043 | ... W4: ='3.1销售情况分析'!Z3 -> 26137.916
A5: 1.2 | B5: 其他收入 | C5: =SUM(D5:W5) -> 0 | D5: =附表3营业收入汇总表!D6 -> 0 | E5: =附表3营业收入汇总表!E6 -> 0 | F5: =附表3营业收入汇总表!F6 -> 0 | G5: =附表3营业收入汇总表!G6 -> 0 | H5: =附表3营业收入汇总表!H6 -> 0 | I5: =附表3营业收入汇总表!I6 -> 0 | J5: =附表3营业收入汇总表!J6 -> 0 | K5: =附表3营业收入汇总表!K6 -> 0 | ... W5: =附表3营业收入汇总表!W6 -> 0
A6: 1.3 | B6: 贷款 | C6: =SUM(D6:W6) -> 43717.55 | D6: ='附表2 投资计划与资金筹措平衡表 '!D16 -> 0 | E6: ='附表2 投资计划与资金筹措平衡表 '!E16 -> 8743.51 | F6: ='附表2 投资计划与资金筹措平衡表 '!F16 -> 4371.755 | G6: ='附表2 投资计划与资金筹措平衡表 '!G16 -> 4371.755 | H6: ='附表2 投资计划与资金筹措平衡表 '!H16 -> 4371.755 | I6: ='附表2 投资计划与资金筹措平衡表 '!I16 -> 4371.755 | J6: ='附表2 投资计划与资金筹措平衡表 '!J16 -> 4371.755 | K6: ='附表2 投资计划与资金筹措平衡表 '!K16 -> 4371.755 | ... M6: ='附表2 投资计划与资金筹措平衡表 '!M16 -> 4371.755
A7: 1.4 | B7: 项目资本金 | C7: =SUM(D7:W7) -> 63045.425 | D7: ='附表2 投资计划与资金筹措平衡表 '!D12 -> 59832.185 | E7: ='附表2 投资计划与资金筹措平衡表 '!E12 -> 65.576325 | F7: ='附表2 投资计划与资金筹措平衡表 '!F12 -> 163.94081 | G7: ='附表2 投资计划与资金筹措平衡表 '!G12 -> 229.51714 | H7: ='附表2 投资计划与资金筹措平衡表 '!H12 -> 295.09346 | I7: ='附表2 投资计划与资金筹措平衡表 '!I12 -> 360.66979 | J7: ='附表2 投资计划与资金筹措平衡表 '!J12 -> 426.24611 | K7: ='附表2 投资计划与资金筹措平衡表 '!K12 -> 491.82244 | ... M7: ='附表2 投资计划与资金筹措平衡表 '!M12 -> 622.97509
A8: 1.5 | B8: 政府建设拨款 | C8: =SUM(D8:W8) -> 0 | D8: ='附表2 投资计划与资金筹措平衡表 '!D21 -> 0 | E8: ='附表2 投资计划与资金筹措平衡表 '!E21 -> 0 | F8: ='附表2 投资计划与资金筹措平衡表 '!F21 -> 0 | G8: ='附表2 投资计划与资金筹措平衡表 '!G21 -> 0 | H8: ='附表2 投资计划与资金筹措平衡表 '!H21 -> 0 | I8: ='附表2 投资计划与资金筹措平衡表 '!I21 -> 0 | J8: ='附表2 投资计划与资金筹措平衡表 '!J21 -> 0 | K8: ='附表2 投资计划与资金筹措平衡表 '!K21 -> 0 | ... M8: ='附表2 投资计划与资金筹措平衡表 '!M21 -> 0
A9: 1.6 | B9: 流动资金借款 | C9: =SUM(D9:W9) -> 0
A10: 1.7 | B10: 回收流动资金 | C10: =SUM(D10:W10) -> 0
A11: 1.8 | B11: 回收资产处置余值 | C11: =SUM(D11:W11) -> 0 | W11: ='附表6 资产折旧摊销表'!X16 -> 0
A12: 2 | B12: 资金运用 | C12: =SUM(D12:W12) -> 222708.05 | D12: =SUM(D13:D22) -> 59832.185 | E12: =SUM(E13:E22) -> 8809.0863 | F12: =SUM(F13:F22) -> 4535.6958 | G12: =SUM(G13:G22) -> 28360.769 | H12: =SUM(H13:H22) -> 13946.878 | I12: =SUM(I13:I22) -> 12637.277 | J12: =SUM(J13:J22) -> 3687.8191 | K12: =SUM(K13:K22) -> 3278.4518 | ... W12: =SUM(W13:W22) -> 26849.453
A13: 2.1 | B13: 建设投资 | C13: =SUM(D13:W13) -> 103549.74 | D13: =SUM('附表2 投资计划与资金筹措平衡表 '!D6:D8) -> 59832.185 | E13: =SUM('附表2 投资计划与资金筹措平衡表 '!E6:E8) -> 8743.51 | F13: =SUM('附表2 投资计划与资金筹措平衡表 '!F6:F8) -> 4371.755 | G13: =SUM('附表2 投资计划与资金筹措平衡表 '!G6:G8) -> 4371.755 | H13: =SUM('附表2 投资计划与资金筹措平衡表 '!H6:H8) -> 4371.755 | I13: =SUM('附表2 投资计划与资金筹措平衡表 '!I6:I8) -> 4371.755 | J13: =SUM('附表2 投资计划与资金筹措平衡表 '!J6:J8) -> 4371.755 | K13: =SUM('附表2 投资计划与资金筹措平衡表 '!K6:K8) -> 4371.755 | ... M13: =SUM('附表2 投资计划与资金筹措平衡表 '!M6:M8) -> 4371.755
A14: 2.2 | B14: 大修费用 | C14: =SUM(D14:W14) -> 0
A15: 2.3 | B15: 营业税及附加 | C15: =SUM(D15:W15) -> 921.96832 | D15: =附表9利润表!D5 -> 0 | E15: =附表9利润表!E5 -> 0 | F15: =附表9利润表!F5 -> 0 | G15: =附表9利润表!G5 -> 0 | H15: =附表9利润表!H5 -> 0 | I15: =附表9利润表!I5 -> 0 | J15: =附表9利润表!J5 -> 0 | K15: =附表9利润表!K5 -> 0 | ... W15: =附表9利润表!W5 -> 921.96832
A16: 2.4 | B16: 流动资产 | C16: =SUM(D16:W16) -> 0
A17: 2.5 | B17: 经营成本（含税） | C17: =SUM(D17:W17) -> 7697.2536 | D17: ='5.1运营成本明细表'!G3 -> 0 | E17: ='5.1运营成本明细表'!H3 -> 100 | F17: ='5.1运营成本明细表'!I3 -> 100 | G17: ='5.1运营成本明细表'!J3 -> 1299.4507 | H17: ='5.1运营成本明细表'!K3 -> 567.28029 | I17: ='5.1运营成本明细表'!L3 -> 567.28029 | J17: ='5.1运营成本明细表'!M3 -> 747.1979 | K17: ='5.1运营成本明细表'!N3 -> 447.33522 | ... W17: ='5.1运营成本明细表'!Z3 -> 1406.8958
A18: 2.6 | B18: 利息支出 | C18: =SUM(D18:W18) -> 6900.4559 | D18: ='附表7 银行贷款还本付息表'!E25 -> 0 | E18: ='附表7 银行贷款还本付息表'!F25 -> 65.576325 | F18: ='附表7 银行贷款还本付息表'!G25 -> 163.94081 | G18: ='附表7 银行贷款还本付息表'!H25 -> 229.51714 | H18: ='附表7 银行贷款还本付息表'!I25 -> 295.09346 | I18: ='附表7 银行贷款还本付息表'!J25 -> 360.66979 | J18: ='附表7 银行贷款还本付息表'!K25 -> 426.24611 | K18: ='附表7 银行贷款还本付息表'!L25 -> 491.82244 | ... M18: ='附表7 银行贷款还本付息表'!N25 -> 622.97509 | N18: ='附表7 银行贷款还本付息表'!O26 -> 655.76325 | O18: ='附表7 银行贷款还本付息表'!P26 -> 594.49255 | P18: ='附表7 银行贷款还本付息表'!Q26 -> 532.30279 | Q18: ='附表7 银行贷款还本付息表'!R26 -> 469.18018 | R18: ='附表7 银行贷款还本付息表'!S26 -> 405.11074 | S18: ='附表7 银行贷款还本付息表'!T26 -> 340.08025 | T18: ='附表7 银行贷款还本付息表'!U26 -> 274.0743 | U18: ='附表7 银行贷款还本付息表'!V26 -> 207.07827 | ... W18: ='附表7 银行贷款还本付息表'!X26 -> 70.056304
A19: 2.7 | B19: 偿还债务本金 | C19: =SUM(D19:W19) -> 43717.55 | D19: ='附表7 银行贷款还本付息表'!E24 -> 0 | E19: ='附表7 银行贷款还本付息表'!F24 -> 0 | F19: ='附表7 银行贷款还本付息表'!G24 -> 0 | G19: ='附表7 银行贷款还本付息表'!H24 -> 0 | H19: ='附表7 银行贷款还本付息表'!I24 -> 0 | I19: ='附表7 银行贷款还本付息表'!J24 -> 0 | J19: ='附表7 银行贷款还本付息表'!K24 -> 0 | K19: ='附表7 银行贷款还本付息表'!L24 -> 0 | ... W19: ='附表7 银行贷款还本付息表'!X24 -> 4670.4203
A20: 2.8 | B20: 所得税 | C20: =SUM(D20:W20) -> 0 | D20: =附表9利润表!D11 -> 0 | E20: =附表9利润表!E11 -> 0 | F20: =附表9利润表!F11 -> 0 | G20: =附表9利润表!G11 -> 0 | H20: =附表9利润表!H11 -> 0 | I20: =附表9利润表!I11 -> 0 | J20: =附表9利润表!J11 -> 0 | K20: =附表9利润表!K11 -> 0 | ... W20: =附表9利润表!W11 -> 0
A21: 2.9 | B21: 应付利润 | C21: =SUM(D21:W21) -> -3624.3408 | D21: =附表9利润表!D17 -> 0 | E21: =附表9利润表!E17 -> -100 | F21: =附表9利润表!F17 -> -100 | G21: =附表9利润表!G17 -> -2602.5657 | H21: =附表9利润表!H17 -> -1962.4285 | I21: =附表9利润表!I17 -> -1962.4285 | J21: =附表9利润表!J17 -> -1857.3799 | K21: =附表9利润表!K17 -> -2032.4608 | ... W21: =附表9利润表!W17 -> 1272.4775
A22: 2.1 | B22: 减资 | C22: =SUM(D22:W22) -> 63545.425 | E22: =IF(E27>0,E27,0) -> 0 | F22: =IF(F27>0,F27,0) -> 0 | G22: =IF(G27>0,G27,0) -> 25062.612 | H22: =IF(H27>0,H27,0) -> 10675.178 | I22: 9300 | W22: =W27 -> 18507.635
A23: 3 | B23: 当年资金盈余 | D23: =D3-D12 -> 0 | E23: =E3-E12 -> 0 | F23: =F3-F12 -> 0 | G23: =G3-G12 -> 229.51714 | H23: =H3-H12 -> 65.576325 | I23: =I3-I12 -> 1440.7539 | J23: =J3-J12 -> 14054.14 | K23: =K3-K12 -> 8531.8299 | ... W23: =W3-W12 -> -711.53735
A24: 4 | B24: 累计资金盈余 | D24: =D23 -> 0 | E24: =D24+E23 -> 0 | F24: =E24+F23 -> 0 | G24: =F24+G23 -> 229.51714 | H24: =G24+H23 -> 295.09346 | I24: =H24+I23 -> 1735.8474 | J24: =I24+J23 -> 15789.987 | K24: =J24+K23 -> 24321.817 | L24: =K24+L23 -> 30644.723 | ... W24: =V24+W23 -> 0
A25: 参照辅助 计算 | B25: 项目是否正常运作 （累计资金盈余大于0） | C25: =IF(COUNTIF(D25:W25,"否")=0,"正确","错误") -> 正确 | D25: =IF(ROUND(D24,0)>=0,"是","否") -> 是 | E25: =IF(ROUND(E24,0)>=0,"是","否") -> 是 | F25: =IF(ROUND(F24,0)>=0,"是","否") -> 是 | G25: =IF(ROUND(G24,0)>=0,"是","否") -> 是 | H25: =IF(ROUND(H24,0)>=0,"是","否") -> 是 | I25: =IF(ROUND(I24,0)>=0,"是","否") -> 是 | J25: =IF(ROUND(J24,0)>=0,"是","否") -> 是 | K25: =IF(ROUND(K24,0)>=0,"是","否") -> 是 | ... W25: =IF(ROUND(W24,0)>=0,"是","否") -> 是
B26: 可用于还本及注册资本减资资金 | E26: =E3-SUM(E13:E18)-E20-E21-20000 -> -20000 | F26: =F3-SUM(F13:F18)-F20-F21-20000 -> -20000 | G26: =G3-SUM(G13:G18)-G20-G21-20000 -> 5292.1294 | H26: =H3-SUM(H13:H18)-H20-H21-20000 -> -9259.2461 | I26: =I3-SUM(I13:I18)-I20-I21-20000 -> -9259.2461 | J26: =J3-SUM(J13:J18)-J20-J21-20000 -> -5945.86 | K26: =K3-SUM(K13:K18)-K20-K21-20000 -> -11468.17 | L26: =L3-SUM(L13:L18)-L20-L21-20000 -> -13677.094 | ... N26: =N3-SUM(N13:N18)-N20-N21-20000 -> -19531.881 | O26: =O3-SUM(O13:O18)-O20-O21 -> 474.24638 | P26: =P3-SUM(P13:P18)-P20-P21 -> 480.46535 | Q26: =Q3-SUM(Q13:Q18)-Q20-Q21 -> 486.77761 | R26: =R3-SUM(R13:R18)-R20-R21 -> 476.78021 | S26: =S3-SUM(S13:S18)-S20-S21 -> 377.27777 | T26: =T3-SUM(T13:T18)-T20-T21 -> 377.27777 | U26: =U3-SUM(U13:U18)-U20-U21 -> 377.27777 | V26: =V3-SUM(V13:V18)-V20-V21 -> 377.27777 | W26: =W3-SUM(W13:W18)-W20-W21 -> 22466.518
B27: 注册资本减资参考值 | F27: =E24+F4+F11+F5-F15-F17-F18-F19-F20-F21 -> -163.94081 | G27: =F24+G4+G11+G5-G15-G17-G18-G19-G20-G21 -> 25062.612 | H27: =G24+H4+H11+H5-H15-H17-H18-H19-H20-H21 -> 10675.178 | I27: =H24+I4+I11+I5-I15-I17-I18-I19-I20-I21 -> 10675.178 | J27: =I24+J4+J11+J5-J15-J17-J18-J19-J20-J21 -> 15363.741 | K27: =J24+K4+K11+K5-K15-K17-K18-K19-K20-K21 -> 23829.995 | L27: =K24+L4+L11+L5-L15-L17-L18-L19-L20-L21 -> 30087.324 | M27: =L24+M4+M11+M5-M15-M17-M18-M19-M20-M21 -> 35240.192 | ... W27: =V24+W4+W11+W5-W15-W17-W18-W19-W20-W21 -> 18507.635
B28: 清算参考值 | W28: =C7+附表9利润表!C15 -> 63545.425
A29: 序号 | B29: 项目 | C29: 合计 | D29: 第1年Q1 | E29: 第1年Q2 | F29: 第1年Q3 | G29: 第1年Q4 | H29: 第2年Q1 | I29: 第2年Q2 | J29: 第2年Q3 | K29: 第2年Q4 | L29: 第3年Q1 | M29: 第3年Q2 | N29: 第3年Q3 | O29: 第3年Q4 | P29: 第4年Q1 | Q29: 第4年Q2 | R29: 第4年Q3 | S29: 第4年Q4 | T29: 第5年Q1 | U29: 第5年Q2 | V29: 第5年Q3 | W29: 第5年Q4
A30: 1 | B30: 减资额 | C30: =SUM(D30:W30) -> 63545.425 | D30: =D22 -> 0 | E30: =E22 -> 0 | F30: =F22 -> 0 | G30: =G22 -> 25062.612 | H30: =H22 -> 10675.178 | I30: =I22 -> 9300 | J30: =J22 -> 0 | K30: =K22 -> 0 | ... W30: =W22 -> 18507.635
A31: 2 | B31: 资本金剩余 | D31: =C22-附表9利润表!C15 -> 63045.425 | E31: =D31-E30 -> 63045.425 | F31: =E31-F30 -> 63045.425 | G31: =F31-G30 -> 37982.813 | H31: =G31-H30 -> 27307.635 | I31: =H31-I30 -> 18007.635 | J31: =I31-J30 -> 18007.635 | K31: =J31-K30 -> 18007.635 | L31: =K31-L30 -> 18007.635 | ... V31: =U31-V30 -> 18007.635 | W31: =V31-W30+附表9利润表!C15 -> 0
A33: 点击返回目录

Sheet 附表11 财务计划现金流量表
B2: 附表11 财务计划现金流量表 (单位：万元)
B3: 序号 | C3: 项目 | E3: 第1年Q1 | F3: 第1年Q2 | G3: 第1年Q3 | H3: 第1年Q4 | I3: 第2年Q1 | J3: 第2年Q2 | K3: 第2年Q3 | L3: 第2年Q4 | M3: 第3年Q1 | N3: 第3年Q2 | O3: 第3年Q3 | P3: 第3年Q4 | Q3: 第4年Q1 | R3: 第4年Q2 | S3: 第4年Q3 | T3: 第4年Q4 | U3: 第5年Q1 | V3: 第5年Q2 | W3: 第5年Q3 | X3: 第5年Q4
B4: 1 | C4: 经营活动净现金流量 | D4: =SUM(E4:X4) -> 107325.85 | E4: =E5-E7 -> 0 | F4: =F5-F7 -> -100 | G4: =G5-G7 -> -100 | H4: =H5-H7 -> 22689.564 | I4: =I5-I7 -> 8778.3255 | J4: =J5-J7 -> 8778.3255 | K4: =K5-K7 -> 12196.76 | L4: =L5-L7 -> 6499.3691 | ... X4: =X5-X7 -> 23809.052
B5: 1.1 | C5: 现金流入 | D5: =SUM(E5:X5) -> 115945.07 | E5: =SUM(E6:E6) -> 0 | F5: =SUM(F6:F6) -> 0 | G5: =SUM(G6:G6) -> 0 | H5: =SUM(H6:H6) -> 23989.014 | I5: =SUM(I6:I6) -> 9345.6058 | J5: =SUM(J6:J6) -> 9345.6058 | K5: =SUM(K6:K6) -> 12943.958 | L5: =SUM(L6:L6) -> 6946.7043 | ... X5: =SUM(X6:X6) -> 26137.916
B6: 1.1.1 | C6: 收入合计 | D6: =SUM(E6:X6) -> 115945.07 | E6: =附表3营业收入汇总表!D3 -> 0 | F6: =附表3营业收入汇总表!E3 -> 0 | G6: =附表3营业收入汇总表!F3 -> 0 | H6: =附表3营业收入汇总表!G3 -> 23989.014 | I6: =附表3营业收入汇总表!H3 -> 9345.6058 | J6: =附表3营业收入汇总表!I3 -> 9345.6058 | K6: =附表3营业收入汇总表!J3 -> 12943.958 | L6: =附表3营业收入汇总表!K3 -> 6946.7043 | ... X6: =附表3营业收入汇总表!W3 -> 26137.916
B7: 1.2 | C7: 现金流出 | D7: =SUM(E7:X7) -> 8619.2219 | E7: =SUM(E8:E11) -> 0 | F7: =SUM(F8:F11) -> 100 | G7: =SUM(G8:G11) -> 100 | H7: =SUM(H8:H11) -> 1299.4507 | I7: =SUM(I8:I11) -> 567.28029 | J7: =SUM(J8:J11) -> 567.28029 | K7: =SUM(K8:K11) -> 747.1979 | L7: =SUM(L8:L11) -> 447.33522 | ... X7: =SUM(X8:X11) -> 2328.8641
B8: 1.2.1 | C8: 运营成本 | D8: =SUM(E8:X8) -> 7697.2536 | E8: ='附表5 运营成本汇总表'!E3 -> 0 | F8: ='附表5 运营成本汇总表'!F3 -> 100 | G8: ='附表5 运营成本汇总表'!G3 -> 100 | H8: ='附表5 运营成本汇总表'!H3 -> 1299.4507 | I8: ='附表5 运营成本汇总表'!I3 -> 567.28029 | J8: ='附表5 运营成本汇总表'!J3 -> 567.28029 | K8: ='附表5 运营成本汇总表'!K3 -> 747.1979 | L8: ='附表5 运营成本汇总表'!L3 -> 447.33522 | ... X8: ='附表5 运营成本汇总表'!X3 -> 1406.8958
B9: 1.2.2
B10: 1.2.3 | C10: 税金及附加 | D10: =SUM(E10:X10) -> 921.96832 | E10: =附表9利润表!D5 -> 0 | F10: =附表9利润表!E5 -> 0 | G10: =附表9利润表!F5 -> 0 | H10: =附表9利润表!G5 -> 0 | I10: =附表9利润表!H5 -> 0 | J10: =附表9利润表!I5 -> 0 | K10: =附表9利润表!J5 -> 0 | L10: =附表9利润表!K5 -> 0 | ... X10: =附表9利润表!W5 -> 921.96832
B11: 1.2.4 | C11: 所得税 | D11: =SUM(E11:X11) -> 0 | E11: =附表9利润表!D11 -> 0 | F11: =附表9利润表!E11 -> 0 | G11: =附表9利润表!F11 -> 0 | H11: =附表9利润表!G11 -> 0 | I11: =附表9利润表!H11 -> 0 | J11: =附表9利润表!I11 -> 0 | K11: =附表9利润表!J11 -> 0 | L11: =附表9利润表!K11 -> 0 | ... X11: =附表9利润表!W11 -> 0
B12: 2 | C12: 投资活动净现金流量 | D12: =SUM(E12:X12) -> -106762.97 | E12: =E13-E14 -> -59832.185 | F12: =F13-F14 -> -8809.0863 | G12: =G13-G14 -> -4535.6958 | H12: =H13-H14 -> -4601.2721 | I12: =I13-I14 -> -4666.8485 | J12: =J13-J14 -> -4732.4248 | K12: =K13-K14 -> -4798.0011 | L12: =L13-L14 -> -4863.5774 | ... X12: =X13-X14 -> 0
B13: 2.1 | C13: 现金流入 | D13: =SUM(E13:X13) -> 0 | T13: ='附表10 资金来源与运用表'!S11 -> 0 | U13: ='附表10 资金来源与运用表'!T11 -> 0 | V13: ='附表10 资金来源与运用表'!U11 -> 0 | W13: ='附表10 资金来源与运用表'!V11 -> 0 | X13: ='附表10 资金来源与运用表'!W11 -> 0
B14: 2.2 | C14: 现金流出 | D14: =SUM(E14:X14) -> 106762.97 | E14: =SUM(E15:E17) -> 59832.185 | F14: =SUM(F15:F17) -> 8809.0863 | G14: =SUM(G15:G17) -> 4535.6958 | H14: =SUM(H15:H17) -> 4601.2721 | I14: =SUM(I15:I17) -> 4666.8485 | J14: =SUM(J15:J17) -> 4732.4248 | K14: =SUM(K15:K17) -> 4798.0011 | L14: =SUM(L15:L17) -> 4863.5774 | ... X14: =SUM(X15:X17) -> 0
B15: 2.2.1 | C15: 建设投资 | D15: =SUM(E15:X15) -> 103549.74 | E15: =SUM('附表2 投资计划与资金筹措平衡表 '!D6:D8) -> 59832.185 | F15: =SUM('附表2 投资计划与资金筹措平衡表 '!E6:E8) -> 8743.51 | G15: =SUM('附表2 投资计划与资金筹措平衡表 '!F6:F8) -> 4371.755 | H15: =SUM('附表2 投资计划与资金筹措平衡表 '!G6:G8) -> 4371.755 | I15: =SUM('附表2 投资计划与资金筹措平衡表 '!H6:H8) -> 4371.755 | J15: =SUM('附表2 投资计划与资金筹措平衡表 '!I6:I8) -> 4371.755 | K15: =SUM('附表2 投资计划与资金筹措平衡表 '!J6:J8) -> 4371.755 | L15: =SUM('附表2 投资计划与资金筹措平衡表 '!K6:K8) -> 4371.755 | ... N15: =SUM('附表2 投资计划与资金筹措平衡表 '!M6:M8) -> 4371.755
B16: 2.2.2 | C16: 建设期利息 | D16: =SUM(E16:X16) -> 3213.2399 | E16: ='附表2 投资计划与资金筹措平衡表 '!D9 -> 0 | F16: ='附表2 投资计划与资金筹措平衡表 '!E9 -> 65.576325 | G16: ='附表2 投资计划与资金筹措平衡表 '!F9 -> 163.94081 | H16: ='附表2 投资计划与资金筹措平衡表 '!G9 -> 229.51714 | I16: ='附表2 投资计划与资金筹措平衡表 '!H9 -> 295.09346 | J16: ='附表2 投资计划与资金筹措平衡表 '!I9 -> 360.66979 | K16: ='附表2 投资计划与资金筹措平衡表 '!J9 -> 426.24611 | L16: ='附表2 投资计划与资金筹措平衡表 '!K9 -> 491.82244 | ... N16: ='附表2 投资计划与资金筹措平衡表 '!M9 -> 622.97509
B17: 2.2.3 | C17: 流动资金 （运营成本已含） | D17: =SUM(E17:X17) -> 0
B18: 3 | C18: 筹资活动净现金流量 | D18: =SUM(E18:X18) -> -562.87516 | E18: =E19-E24 -> 59832.185 | F18: =F19-F24 -> 8909.0863 | G18: =G19-G24 -> 4635.6958 | H18: =H19-H24 -> -17858.774 | I18: =I19-I24 -> -4045.9007 | J18: =J19-J24 -> -2605.1467 | K18: =K19-K24 -> 6655.3811 | L18: =L19-L24 -> 6896.0383 | ... X18: =X19-X24 -> -24520.589
B19: 3.1 | C19: 现金流入 | D19: =SUM(E19:X19) -> 106762.97 | E19: =SUM(E20:E23) -> 59832.185 | F19: =SUM(F20:F23) -> 8809.0863 | G19: =SUM(G20:G23) -> 4535.6958 | H19: =SUM(H20:H23) -> 4601.2721 | I19: =SUM(I20:I23) -> 4666.8485 | J19: =SUM(J20:J23) -> 4732.4248 | K19: =SUM(K20:K23) -> 4798.0011 | L19: =SUM(L20:L23) -> 4863.5774 | ... X19: =SUM(X20:X23) -> 0
B20: 3.1.1 | C20: 资本金 | D20: =SUM(E20:X20) -> 63045.425 | E20: ='附表2 投资计划与资金筹措平衡表 '!D12 -> 59832.185 | F20: ='附表2 投资计划与资金筹措平衡表 '!E12 -> 65.576325 | G20: ='附表2 投资计划与资金筹措平衡表 '!F12 -> 163.94081 | H20: ='附表2 投资计划与资金筹措平衡表 '!G12 -> 229.51714 | I20: ='附表2 投资计划与资金筹措平衡表 '!H12 -> 295.09346 | J20: ='附表2 投资计划与资金筹措平衡表 '!I12 -> 360.66979 | K20: ='附表2 投资计划与资金筹措平衡表 '!J12 -> 426.24611 | L20: ='附表2 投资计划与资金筹措平衡表 '!K12 -> 491.82244 | ... N20: ='附表2 投资计划与资金筹措平衡表 '!M12 -> 622.97509
B21: 3.1.2 | C21: 项目融资 | D21: =SUM(E21:X21) -> 43717.55 | E21: ='附表2 投资计划与资金筹措平衡表 '!D16 -> 0 | F21: ='附表2 投资计划与资金筹措平衡表 '!E16 -> 8743.51 | G21: ='附表2 投资计划与资金筹措平衡表 '!F16 -> 4371.755 | H21: ='附表2 投资计划与资金筹措平衡表 '!G16 -> 4371.755 | I21: ='附表2 投资计划与资金筹措平衡表 '!H16 -> 4371.755 | J21: ='附表2 投资计划与资金筹措平衡表 '!I16 -> 4371.755 | K21: ='附表2 投资计划与资金筹措平衡表 '!J16 -> 4371.755 | L21: ='附表2 投资计划与资金筹措平衡表 '!K16 -> 4371.755 | ... N21: ='附表2 投资计划与资金筹措平衡表 '!M16 -> 4371.755
B22: 3.1.3 | C22: 股东借款 | D22: =SUM(E22:X22) -> 0
B23: 3.1.4 | C23: 政府建设拨款 | D23: =SUM(E23:X23) -> 0 | E23: ='附表2 投资计划与资金筹措平衡表 '!D21 -> 0 | F23: ='附表2 投资计划与资金筹措平衡表 '!E21 -> 0 | G23: ='附表2 投资计划与资金筹措平衡表 '!F21 -> 0 | H23: ='附表2 投资计划与资金筹措平衡表 '!G21 -> 0 | I23: ='附表2 投资计划与资金筹措平衡表 '!H21 -> 0 | J23: ='附表2 投资计划与资金筹措平衡表 '!I21 -> 0 | K23: ='附表2 投资计划与资金筹措平衡表 '!J21 -> 0 | L23: ='附表2 投资计划与资金筹措平衡表 '!K21 -> 0 | ... N23: ='附表2 投资计划与资金筹措平衡表 '!M21 -> 0
B24: 3.2 | C24: 现金流出 | D24: =SUM(E24:X24) -> 107325.85 | E24: =SUM(E25:E29) -> 0 | F24: =SUM(F25:F29) -> -100 | G24: =SUM(G25:G29) -> -100 | H24: =SUM(H25:H29) -> 22460.047 | I24: =SUM(I25:I29) -> 8712.7491 | J24: =SUM(J25:J29) -> 7337.5715 | K24: =SUM(K25:K29) -> -1857.3799 | L24: =SUM(L25:L29) -> -2032.4608 | ... X24: =SUM(X25:X29) -> 24520.589
B25: 3.2.1 | C25: 各种利息支出 | D25: =SUM(E25:X25) -> 3687.2159 | E25: ='附表7 银行贷款还本付息表'!E26 -> 0 | F25: ='附表7 银行贷款还本付息表'!F26 -> 0 | G25: ='附表7 银行贷款还本付息表'!G26 -> 0 | H25: ='附表7 银行贷款还本付息表'!H26 -> 0 | I25: ='附表7 银行贷款还本付息表'!I26 -> 0 | J25: ='附表7 银行贷款还本付息表'!J26 -> 0 | K25: ='附表7 银行贷款还本付息表'!K26 -> 0 | L25: ='附表7 银行贷款还本付息表'!L26 -> 0 | ... X25: ='附表7 银行贷款还本付息表'!X26 -> 70.056304
B26: 3.2.2 | C26: 偿还长期贷款本金 | D26: =SUM(E26:X26) -> 43717.55 | E26: ='附表7 银行贷款还本付息表'!E24 -> 0 | F26: ='附表7 银行贷款还本付息表'!F24 -> 0 | G26: ='附表7 银行贷款还本付息表'!G24 -> 0 | H26: ='附表7 银行贷款还本付息表'!H24 -> 0 | I26: ='附表7 银行贷款还本付息表'!I24 -> 0 | J26: ='附表7 银行贷款还本付息表'!J24 -> 0 | K26: ='附表7 银行贷款还本付息表'!K24 -> 0 | L26: ='附表7 银行贷款还本付息表'!L24 -> 0 | ... X26: ='附表7 银行贷款还本付息表'!X24 -> 4670.4203
B27: 3.2.3 | C27: 偿还短期贷款本金 | D27: =SUM(E27:X27) -> 0
B28: 3.2.4 | C28: 应付利润 | D28: =SUM(E28:X28) -> -3624.3408 | E28: =附表9利润表!D17 -> 0 | F28: =附表9利润表!E17 -> -100 | G28: =附表9利润表!F17 -> -100 | H28: =附表9利润表!G17 -> -2602.5657 | I28: =附表9利润表!H17 -> -1962.4285 | J28: =附表9利润表!I17 -> -1962.4285 | K28: =附表9利润表!J17 -> -1857.3799 | L28: =附表9利润表!K17 -> -2032.4608 | ... X28: =附表9利润表!W17 -> 1272.4775
B29: 3.2.5 | C29: 减资退出 | D29: =SUM(E29:X29) -> 63545.425 | E29: ='附表10 资金来源与运用表'!D22 -> 0 | F29: ='附表10 资金来源与运用表'!E22 -> 0 | G29: ='附表10 资金来源与运用表'!F22 -> 0 | H29: ='附表10 资金来源与运用表'!G22 -> 25062.612 | I29: ='附表10 资金来源与运用表'!H22 -> 10675.178 | J29: ='附表10 资金来源与运用表'!I22 -> 9300 | K29: ='附表10 资金来源与运用表'!J22 -> 0 | L29: ='附表10 资金来源与运用表'!K22 -> 0 | ... X29: ='附表10 资金来源与运用表'!W22 -> 18507.635
B30: 4 | C30: 净现金流量 | D30: =SUM(E30:X30) -> -6.3664629e-12 | E30: =E4+E12+E18 -> 0 | F30: =F4+F12+F18 -> 0 | G30: =G4+G12+G18 -> 0 | H30: =H4+H12+H18 -> 229.51714 | I30: =I4+I12+I18 -> 65.576325 | J30: =J4+J12+J18 -> 1440.7539 | K30: =K4+K12+K18 -> 14054.14 | L30: =L4+L12+L18 -> 8531.8299 | ... X30: =X4+X12+X18 -> -711.53735
B31: 5 | C31: 累计盈余资金 | E31: =E30 -> 0 | F31: =F30+E31 -> 0 | G31: =G30+F31 -> 0 | H31: =H30+G31 -> 229.51714 | I31: =I30+H31 -> 295.09346 | J31: =J30+I31 -> 1735.8474 | K31: =K30+J31 -> 15789.987 | L31: =L30+K31 -> 24321.817 | M31: =M30+L31 -> 30644.723 | ... X31: =X30+W31 -> -6.3664629e-12
B32: 验证 | C32: 现金净流量是否与资金来源与运用表一致 | E32: ='附表10 资金来源与运用表'!D24 -> 0 | F32: ='附表10 资金来源与运用表'!E24 -> 0 | G32: ='附表10 资金来源与运用表'!F24 -> 0 | H32: ='附表10 资金来源与运用表'!G24 -> 229.51714 | I32: ='附表10 资金来源与运用表'!H24 -> 295.09346 | J32: ='附表10 资金来源与运用表'!I24 -> 1735.8474 | K32: ='附表10 资金来源与运用表'!J24 -> 15789.987 | L32: ='附表10 资金来源与运用表'!K24 -> 24321.817 | ... X32: ='附表10 资金来源与运用表'!W24 -> 0
C34: 可用于提前还本(预留2亿元作为周转资金) | O34: =O4+O12+O19-O25-O28-附表9利润表!N15-20000 -> -19622.722 | P34: =P4+P12+P19-P25-P28 -> 474.24638 | Q34: =Q4+Q12+Q19-Q25-Q28 -> 480.46535 | R34: =R4+R12+R19-R25-R28 -> 486.77761
B35: 点击返回目录
E37: =D29*'0基本假设 '!N15 -> 20158.616

Sheet 附表12 项目全投资现金流量表
B1: 附表12 项目全投资现金流量表(单位：万元)
B2: 序号 | C2: 项目 | D2: 合计 | E2: 第1年Q1 | F2: 第1年Q2 | G2: 第1年Q3 | H2: 第1年Q4 | I2: 第2年Q1 | J2: 第2年Q2 | K2: 第2年Q3 | L2: 第2年Q4 | M2: 第3年Q1 | N2: 第3年Q2 | O2: 第3年Q3 | P2: 第3年Q4 | Q2: 第4年Q1 | R2: 第4年Q2 | S2: 第4年Q3 | T2: 第4年Q4 | U2: 第5年Q1 | V2: 第5年Q2 | W2: 第5年Q3 | X2: 第5年Q4
B3: 1 | C3: 现金流入 | D3: =SUM(E3:X3) -> 115945.07 | E3: =E4+E5+E6+E7 -> 0 | F3: =F4+F5+F6+F7 -> 0 | G3: =G4+G5+G6+G7 -> 0 | H3: =H4+H5+H6+H7 -> 23989.014 | I3: =I4+I5+I6+I7 -> 9345.6058 | J3: =J4+J5+J6+J7 -> 9345.6058 | K3: =K4+K5+K6+K7 -> 12943.958 | L3: =L4+L5+L6+L7 -> 6946.7043 | ... O3: =O4+O5+O6+O7 -> 2148.9014 | P3: =P4+P5+P6+P7+$P$19 -> 2148.9014 | Q3: =Q4+Q5+Q6+Q7+$P$19 -> 2148.9014 | R3: =R4+R5+R6+R7+$P$19 -> 2148.9014 | S3: =S4+S5+S6+S7+$P$19 -> 2148.9014 | T3: =T4+T5+T6+T7+$P$19 -> 2148.9014 | U3: =U4+U5+U6+U7+$P$19 -> 2148.9014 | V3: =V4+V5+V6+V7+$P$19 -> 2148.9014 | W3: =W4+W5+W6+W7+$P$19 -> 2148.9014 | X3: =X4+X5+X6+X7+$P$19 -> 26137.916
B4: 1.1 | C4: 收入合计 | D4: =SUM(E4:X4) -> 115945.07 | E4: =附表3营业收入汇总表!D3 -> 0 | F4: =附表3营业收入汇总表!E3 -> 0 | G4: =附表3营业收入汇总表!F3 -> 0 | H4: =附表3营业收入汇总表!G3 -> 23989.014 | I4: =附表3营业收入汇总表!H3 -> 9345.6058 | J4: =附表3营业收入汇总表!I3 -> 9345.6058 | K4: =附表3营业收入汇总表!J3 -> 12943.958 | L4: =附表3营业收入汇总表!K3 -> 6946.7043 | ... X4: =附表3营业收入汇总表!W3 -> 26137.916
B5: 1.2 | C5: 政府建设拨款 | D5: =SUM(E5:X5) -> 0 | E5: ='附表2 投资计划与资金筹措平衡表 '!D21 -> 0 | F5: ='附表2 投资计划与资金筹措平衡表 '!E21 -> 0 | G5: ='附表2 投资计划与资金筹措平衡表 '!F21 -> 0 | H5: ='附表2 投资计划与资金筹措平衡表 '!G21 -> 0 | I5: ='附表2 投资计划与资金筹措平衡表 '!H21 -> 0 | J5: ='附表2 投资计划与资金筹措平衡表 '!I21 -> 0 | K5: ='附表2 投资计划与资金筹措平衡表 '!J21 -> 0 | L5: ='附表2 投资计划与资金筹措平衡表 '!K21 -> 0 | ... N5: ='附表2 投资计划与资金筹措平衡表 '!M21 -> 0
B6: 1.3 | C6: 回收资产余值 | D6: =SUM(E6:X6) -> 0 | X6: ='附表6 资产折旧摊销表'!X16 -> 0
B7: 1.4 | C7: 回收流动资金 | D7: =SUM(E7:X7) -> 0
B8: 2 | C8: 现金流出 | D8: =SUM(E8:X8) -> 112168.96 | E8: =E9+E10+E11+E12 -> 59832.185 | F8: =F9+F10+F11+F12 -> 8843.51 | G8: =G9+G10+G11+G12 -> 4471.755 | H8: =H9+H10+H11+H12 -> 5671.2057 | I8: =I9+I10+I11+I12 -> 4939.0353 | J8: =J9+J10+J11+J12 -> 4939.0353 | K8: =K9+K10+K11+K12 -> 5118.9529 | L8: =L9+L10+L11+L12 -> 4819.0902 | ... X8: =X9+X10+X11+X12 -> 2328.8641
B9: 2.1 | C9: 建设投资 | D9: =SUM(E9:X9) -> 103549.74 | E9: =SUM('附表2 投资计划与资金筹措平衡表 '!D6:D8) -> 59832.185 | F9: =SUM('附表2 投资计划与资金筹措平衡表 '!E6:E8) -> 8743.51 | G9: =SUM('附表2 投资计划与资金筹措平衡表 '!F6:F8) -> 4371.755 | H9: =SUM('附表2 投资计划与资金筹措平衡表 '!G6:G8) -> 4371.755 | I9: =SUM('附表2 投资计划与资金筹措平衡表 '!H6:H8) -> 4371.755 | J9: =SUM('附表2 投资计划与资金筹措平衡表 '!I6:I8) -> 4371.755 | K9: =SUM('附表2 投资计划与资金筹措平衡表 '!J6:J8) -> 4371.755 | L9: =SUM('附表2 投资计划与资金筹措平衡表 '!K6:K8) -> 4371.755 | ... N9: =SUM('附表2 投资计划与资金筹措平衡表 '!M6:M8) -> 4371.755
B10: 2.2 | C10: 流动资金（建设期流动资金用于经营成本） | D10: =SUM(E10:X10) -> 0
B11: 2.3 | C11: 经营成本 | D11: =SUM(E11:X11) -> 7697.2536 | E11: ='附表5 运营成本汇总表'!E3 -> 0 | F11: ='附表5 运营成本汇总表'!F3 -> 100 | G11: ='附表5 运营成本汇总表'!G3 -> 100 | H11: ='附表5 运营成本汇总表'!H3 -> 1299.4507 | I11: ='附表5 运营成本汇总表'!I3 -> 567.28029 | J11: ='附表5 运营成本汇总表'!J3 -> 567.28029 | K11: ='附表5 运营成本汇总表'!K3 -> 747.1979 | L11: ='附表5 运营成本汇总表'!L3 -> 447.33522 | ... X11: ='附表5 运营成本汇总表'!X3 -> 1406.8958
B12: 2.4 | C12: 营业税及附加 | D12: =SUM(E12:X12) -> 921.96832 | E12: ='3.1销售情况分析'!G4 -> 0 | F12: ='3.1销售情况分析'!H4 -> 0 | G12: ='3.1销售情况分析'!I4 -> 0 | H12: ='3.1销售情况分析'!J4 -> 0 | I12: ='3.1销售情况分析'!K4 -> 0 | J12: ='3.1销售情况分析'!L4 -> 0 | K12: ='3.1销售情况分析'!M4 -> 0 | L12: ='3.1销售情况分析'!N4 -> 0 | ... X12: ='3.1销售情况分析'!Z4 -> 921.96832
B13: 3 | C13: 所得税前净现金流量 | D13: =SUM(E13:X13) -> 3776.1151 | E13: =E3-E8 -> -59832.185 | F13: =F3-F8 -> -8843.51 | G13: =G3-G8 -> -4471.755 | H13: =H3-H8 -> 18317.809 | I13: =I3-I8 -> 4406.5705 | J13: =J3-J8 -> 4406.5705 | K13: =K3-K8 -> 7825.005 | L13: =L3-L8 -> 2127.6141 | ... X13: =X3-X8 -> 23809.052
B14: 4 | C14: 所得税前累计净现金流量 | E14: =E13 -> -59832.185 | F14: =E14+F13 -> -68675.695 | G14: =F14+G13 -> -73147.45 | H14: =G14+H13 -> -54829.641 | I14: =H14+I13 -> -50423.071 | J14: =I14+J13 -> -46016.5 | K14: =J14+K13 -> -38191.495 | L14: =K14+L13 -> -36063.881 | M14: =L14+M13 -> -36215.224 | ... X14: =W14+X13 -> 3776.1151
B15: 5 | C15: 调整所得税 | D15: =SUM(E15:X15) -> 140.71879 | E15: =附表9利润表!D40 -> 0 | F15: =附表9利润表!E40 -> 0 | G15: =附表9利润表!F40 -> 0 | H15: =附表9利润表!G40 -> 0 | I15: =附表9利润表!H40 -> 0 | J15: =附表9利润表!I40 -> 0 | K15: =附表9利润表!J40 -> 0 | L15: =附表9利润表!K40 -> 0 | ... X15: =附表9利润表!W40 -> 140.71879
B16: 6 | C16: 所得税后净现金流量 | D16: =SUM(E16:X16) -> 3635.3963 | E16: =E13-E15 -> -59832.185 | F16: =F13-F15 -> -8843.51 | G16: =G13-G15 -> -4471.755 | H16: =H13-H15 -> 18317.809 | I16: =I13-I15 -> 4406.5705 | J16: =J13-J15 -> 4406.5705 | K16: =K13-K15 -> 7825.005 | L16: =L13-L15 -> 2127.6141 | ... X16: =X13-X15 -> 23668.333
B17: 7 | C17: 所得税后累计净现金流量 | E17: =E16 -> -59832.185 | F17: =E17+F16 -> -68675.695 | G17: =F17+G16 -> -73147.45 | H17: =G17+H16 -> -54829.641 | I17: =H17+I16 -> -50423.071 | J17: =I17+J16 -> -46016.5 | K17: =J17+K16 -> -38191.495 | L17: =K17+L16 -> -36063.881 | M17: =L17+M16 -> -36215.224 | ... X17: =W17+X16 -> 3635.3963
B19: 项目全投资税前收益率 | D19: =(1+IRR(E13:X13))^4-1 -> 0.019221046 | E19: 项目投资回收期（税前） | F19: =(COUNTIF(E14:X14,"<0")+ABS(INDEX(E14:X14,1,COUNTIF(E14:X14,"<0")))/(INDEX(E14:X14,1,COUNTIF(E14:X14,"<0")+1)+ABS(INDEX(E14:X14,1,COUNTIF(E14:X14,"<0")))))/4 -> 4.96035
B20: 项目全投资税后收益率 | D20: =(1+IRR(E16:X16))^4-1 -> 0.018534589 | E20: 项目投资回收期（税后） | F20: =(COUNTIF(E17:X17,"<0")+ABS(INDEX(E17:X17,1,COUNTIF(E17:X17,"<0")))/(INDEX(E17:X17,1,COUNTIF(E17:X17,"<0")+1)+ABS(INDEX(E17:X17,1,COUNTIF(E17:X17,"<0")))))/4 -> 4.9616006
B22: 点击返回目录

Sheet 附表13 项目资本金现金流量
B1: 附表13 项目自有资金现金流量表 (单位：万元)
B2: 序号 | C2: 项目 | D2: 合计 | E2: 第1年Q1 | F2: 第1年Q2 | G2: 第1年Q3 | H2: 第1年Q4 | I2: 第2年Q1 | J2: 第2年Q2 | K2: 第2年Q3 | L2: 第2年Q4 | M2: 第3年Q1 | N2: 第3年Q2 | O2: 第3年Q3 | P2: 第3年Q4 | Q2: 第4年Q1 | R2: 第4年Q2 | S2: 第4年Q3 | T2: 第4年Q4 | U2: 第5年Q1 | V2: 第5年Q2 | W2: 第5年Q3 | X2: 第5年Q4
B3: 1 | C3: 现金流入 | D3: =SUM(E3:X3) -> 115945.07 | E3: =SUM(E4:E7) -> 0 | F3: =SUM(F4:F7) -> 0 | G3: =SUM(G4:G7) -> 0 | H3: =SUM(H4:H7) -> 23989.014 | I3: =SUM(I4:I7) -> 9345.6058 | J3: =SUM(J4:J7) -> 9345.6058 | K3: =SUM(K4:K7) -> 12943.958 | L3: =SUM(L4:L7) -> 6946.7043 | ... X3: =SUM(X4:X7) -> 26137.916
B4: 1.1 | C4: 收入合计 | D4: =SUM(E4:X4) -> 115945.07 | E4: =附表3营业收入汇总表!D3 -> 0 | F4: =附表3营业收入汇总表!E3 -> 0 | G4: =附表3营业收入汇总表!F3 -> 0 | H4: =附表3营业收入汇总表!G3 -> 23989.014 | I4: =附表3营业收入汇总表!H3 -> 9345.6058 | J4: =附表3营业收入汇总表!I3 -> 9345.6058 | K4: =附表3营业收入汇总表!J3 -> 12943.958 | L4: =附表3营业收入汇总表!K3 -> 6946.7043 | ... X4: =附表3营业收入汇总表!W3 -> 26137.916
B5: 1.2 | C5: 政府建设期拨款 | D5: =SUM(E5:X5) -> 0 | E5: ='附表12 项目全投资现金流量表'!E5 -> 0 | F5: ='附表12 项目全投资现金流量表'!F5 -> 0 | G5: ='附表12 项目全投资现金流量表'!G5 -> 0 | H5: ='附表12 项目全投资现金流量表'!H5 -> 0 | I5: ='附表12 项目全投资现金流量表'!I5 -> 0 | J5: ='附表12 项目全投资现金流量表'!J5 -> 0 | K5: ='附表12 项目全投资现金流量表'!K5 -> 0 | L5: ='附表12 项目全投资现金流量表'!L5 -> 0 | ... X5: ='附表12 项目全投资现金流量表'!X5 -> 0
B6: 1.3 | C6: 回收资产余值 | D6: =SUM(E6:X6) -> 0 | E6: ='附表12 项目全投资现金流量表'!E6 -> 0 | F6: ='附表12 项目全投资现金流量表'!F6 -> 0 | G6: ='附表12 项目全投资现金流量表'!G6 -> 0 | H6: ='附表12 项目全投资现金流量表'!H6 -> 0 | I6: ='附表12 项目全投资现金流量表'!I6 -> 0 | J6: ='附表12 项目全投资现金流量表'!J6 -> 0 | K6: ='附表12 项目全投资现金流量表'!K6 -> 0 | L6: ='附表12 项目全投资现金流量表'!L6 -> 0 | ... X6: ='附表12 项目全投资现金流量表'!X6 -> 0
B7: 1.4 | C7: 回收流动资金 | D7: =SUM(E7:X7) -> 0 | E7: ='附表12 项目全投资现金流量表'!E7 -> 0 | F7: ='附表12 项目全投资现金流量表'!F7 -> 0 | G7: ='附表12 项目全投资现金流量表'!G7 -> 0 | H7: ='附表12 项目全投资现金流量表'!H7 -> 0 | I7: ='附表12 项目全投资现金流量表'!I7 -> 0 | J7: ='附表12 项目全投资现金流量表'!J7 -> 0 | K7: ='附表12 项目全投资现金流量表'!K7 -> 0 | L7: ='附表12 项目全投资现金流量表'!L7 -> 0 | ... X7: ='附表12 项目全投资现金流量表'!X7 -> 0
B8: 2 | C8: 现金流出 | D8: =SUM(E8:X8) -> 119069.41 | E8: =SUM(E9:E16) -> 59832.185 | F8: =SUM(F9:F16) -> 165.57632 | G8: =SUM(G9:G16) -> 263.94081 | H8: =SUM(H9:H16) -> 1528.9679 | I8: =SUM(I9:I16) -> 862.37375 | J8: =SUM(J9:J16) -> 927.95008 | K8: =SUM(K9:K16) -> 1173.444 | L8: =SUM(L9:L16) -> 939.15765 | ... X8: =SUM(X9:X16) -> 7069.3407
B9: 2.1 | C9: 项目资本金 | D9: =SUM(E9:X9) -> 63045.425 | E9: ='附表2 投资计划与资金筹措平衡表 '!D12 -> 59832.185 | F9: ='附表2 投资计划与资金筹措平衡表 '!E12 -> 65.576325 | G9: ='附表2 投资计划与资金筹措平衡表 '!F12 -> 163.94081 | H9: ='附表2 投资计划与资金筹措平衡表 '!G12 -> 229.51714 | I9: ='附表2 投资计划与资金筹措平衡表 '!H12 -> 295.09346 | J9: ='附表2 投资计划与资金筹措平衡表 '!I12 -> 360.66979 | K9: ='附表2 投资计划与资金筹措平衡表 '!J12 -> 426.24611 | L9: ='附表2 投资计划与资金筹措平衡表 '!K12 -> 491.82244 | ... N9: ='附表2 投资计划与资金筹措平衡表 '!M12 -> 622.97509
B10: 2.2 | C10: 政府建设拨款投入 | D10: =SUM(E10:X10) -> 0 | E10: =E5 -> 0 | F10: =F5 -> 0 | G10: =G5 -> 0 | H10: =H5 -> 0 | I10: =I5 -> 0 | J10: =J5 -> 0 | K10: =K5 -> 0 | L10: =L5 -> 0 | ... N10: =N5 -> 0
B11: 2.3 | C11: 借款本金偿还 | D11: =SUM(E11:X11) -> 43717.55 | E11: ='附表7 银行贷款还本付息表'!E24 -> 0 | F11: ='附表7 银行贷款还本付息表'!F24 -> 0 | G11: ='附表7 银行贷款还本付息表'!G24 -> 0 | H11: ='附表7 银行贷款还本付息表'!H24 -> 0 | I11: ='附表7 银行贷款还本付息表'!I24 -> 0 | J11: ='附表7 银行贷款还本付息表'!J24 -> 0 | K11: ='附表7 银行贷款还本付息表'!K24 -> 0 | L11: ='附表7 银行贷款还本付息表'!L24 -> 0 | ... X11: ='附表7 银行贷款还本付息表'!X24 -> 4670.4203
B12: 2.4 | C12: 借款利息支付 | D12: =SUM(E12:X12) -> 3687.2159 | E12: ='附表7 银行贷款还本付息表'!E26 -> 0 | F12: ='附表7 银行贷款还本付息表'!F26 -> 0 | G12: ='附表7 银行贷款还本付息表'!G26 -> 0 | H12: ='附表7 银行贷款还本付息表'!H26 -> 0 | I12: ='附表7 银行贷款还本付息表'!I26 -> 0 | J12: ='附表7 银行贷款还本付息表'!J26 -> 0 | K12: ='附表7 银行贷款还本付息表'!K26 -> 0 | L12: ='附表7 银行贷款还本付息表'!L26 -> 0 | ... X12: ='附表7 银行贷款还本付息表'!X26 -> 70.056304
B13: 2.5 | C13: 经营成本 | D13: =SUM(E13:X13) -> 7697.2536 | E13: ='附表5 运营成本汇总表'!E3 -> 0 | F13: ='附表5 运营成本汇总表'!F3 -> 100 | G13: ='附表5 运营成本汇总表'!G3 -> 100 | H13: ='附表5 运营成本汇总表'!H3 -> 1299.4507 | I13: ='附表5 运营成本汇总表'!I3 -> 567.28029 | J13: ='附表5 运营成本汇总表'!J3 -> 567.28029 | K13: ='附表5 运营成本汇总表'!K3 -> 747.1979 | L13: ='附表5 运营成本汇总表'!L3 -> 447.33522 | ... X13: ='附表5 运营成本汇总表'!X3 -> 1406.8958
B14: 2.6 | C14: 营业税及附加 | D14: =SUM(E14:X14) -> 921.96832 | E14: ='3.1销售情况分析'!G4 -> 0 | F14: ='3.1销售情况分析'!H4 -> 0 | G14: ='3.1销售情况分析'!I4 -> 0 | H14: ='3.1销售情况分析'!J4 -> 0 | I14: ='3.1销售情况分析'!K4 -> 0 | J14: ='3.1销售情况分析'!L4 -> 0 | K14: ='3.1销售情况分析'!M4 -> 0 | L14: ='3.1销售情况分析'!N4 -> 0 | ... X14: ='3.1销售情况分析'!Z4 -> 921.96832
B15: 2.7 | C15: 所得税 | D15: =SUM(E15:X15) -> 0 | E15: =附表9利润表!D11 -> 0 | F15: =附表9利润表!E11 -> 0 | G15: =附表9利润表!F11 -> 0 | H15: =附表9利润表!G11 -> 0 | I15: =附表9利润表!H11 -> 0 | J15: =附表9利润表!I11 -> 0 | K15: =附表9利润表!J11 -> 0 | L15: =附表9利润表!K11 -> 0 | ... X15: =附表9利润表!W11 -> 0
B16: 2.8 | C16: 维持运营投资 | D16: =SUM(E16:X16) -> 0
B17: 3 | C17: 税后净现金流量 | D17: =SUM(E17:X17) -> -3124.3408 | E17: =E3-E8 -> -59832.185 | F17: =F3-F8 -> -165.57632 | G17: =G3-G8 -> -263.94081 | H17: =H3-H8 -> 22460.047 | I17: =I3-I8 -> 8483.232 | J17: =J3-J8 -> 8417.6557 | K17: =K3-K8 -> 11770.514 | L17: =L3-L8 -> 6007.5467 | ... X17: =X3-X8 -> 19068.575
B18: 4 | C18: 税前净现金流量 | D18: =SUM(E18:X18) -> -3124.3408 | E18: =E17+E15 -> -59832.185 | F18: =F17+F15 -> -165.57632 | G18: =G17+G15 -> -263.94081 | H18: =H17+H15 -> 22460.047 | I18: =I17+I15 -> 8483.232 | J18: =J17+J15 -> 8417.6557 | K18: =K17+K15 -> 11770.514 | L18: =L17+L15 -> 6007.5467 | ... X18: =X17+X15 -> 19068.575
B19: 5 | C19: 税后累计净现金流 | E19: =E17 -> -59832.185 | F19: =E19+F17 -> -59997.761 | G19: =F19+G17 -> -60261.702 | H19: =G19+H17 -> -37801.656 | I19: =H19+I17 -> -29318.424 | J19: =I19+J17 -> -20900.768 | K19: =J19+K17 -> -9130.254 | L19: =K19+L17 -> -3122.7073 | M19: =L19+M17 -> 540.30665 | ... X19: =W19+X17 -> -3124.3408
B20: 6 | C20: 税前累计净现金流 | E20: =E18 -> -59832.185 | F20: =E20+F18 -> -59997.761 | G20: =F20+G18 -> -60261.702 | H20: =G20+H18 -> -37801.656 | I20: =H20+I18 -> -29318.424 | J20: =I20+J18 -> -20900.768 | K20: =J20+K18 -> -9130.254 | L20: =K20+L18 -> -3122.7073 | M20: =L20+M18 -> 540.30665 | ... X20: =W20+X18 -> -3124.3408
B22: 自有资金税前收益率 | D22: =(1+IRR(E18:X18))^4-1 -> -0.036756886 | E22: 项目投资回收期（税前） | F22: =(COUNTIF(E20:X20,"<0")+ABS(INDEX(E20:X20,1,COUNTIF(E20:X20,"<0")))/(INDEX(E20:X20,1,COUNTIF(E20:X20,"<0")+1)+ABS(INDEX(E20:X20,1,COUNTIF(E20:X20,"<0")))))/4 -> 2.767796
B23: 自有资金税后内部收益率 | D23: =(1+IRR(E17:X17))^4-1 -> -0.036756886 | E23: 项目投资回收期（税后） | F23: =(COUNTIF(E19:X19,"<0")+ABS(INDEX(E19:X19,1,COUNTIF(E19:X19,"<0")))/(INDEX(E19:X19,1,COUNTIF(E19:X19,"<0")+1)+ABS(INDEX(E19:X19,1,COUNTIF(E19:X19,"<0")))))/4 -> 2.767796
C26: 劣后利润分配 | D26: =SUM(E26:X26) -> 48.273184 | E26: -68 | F26: -0.039345 | G26: -0.0983625 | H26: -0.1377075 | I26: 2.3613619 | J26: 0.79745648 | K26: 0.75811148 | L26: 0.71876648 | M26: 0.11803852 | N26: 0.078693518 | O26: 5.0228402 | P26: 2.6676119 | Q26: 4.4589007 | R26: 3.2115267 | S26: 1.3243872 | T26: 1.3674393 | U26: 2.3091075 | V26: 1.4551646 | W26: 8.3962774 | X26: 81.502915
C27: 根据现金流量表复星应分配的税后现金流 | D27: =SUM(E27:X27) -> -2499.4726 | E27: =E17*0.8 -> -47865.748 | F27: =F17*0.8 -> -132.46106 | G27: =G17*0.8 -> -211.15265 | H27: =H17*0.8 -> 17968.037 | I27: =I17*0.8 -> 6786.5856 | J27: =J17*0.8 -> 6734.1245 | K27: =K17*0.8 -> 9416.4111 | L27: =L17*0.8 -> 4806.0373 | ... X27: =X17*0.8 -> 15254.86
B28: 点击返回目录

Sheet 附表14 中信建设现金流量表（优先级）
B2: 附表14 中信建设层面现金流量表(含总包管理费，不计提折旧，(单位：万元)）
B3: 序号 | C3: 项目 | D3: 合计 | E3: 第1年Q1 | F3: 第1年Q2 | G3: 第1年Q3 | H3: 第1年Q4 | I3: 第2年Q1 | J3: 第2年Q2 | K3: 第2年Q3 | L3: 第2年Q4 | M3: 第3年Q1 | N3: 第3年Q2 | O3: 第3年Q3 | P3: 第3年Q4 | Q3: 第4年Q1 | R3: 第4年Q2 | S3: 第4年Q3 | T3: 第4年Q4 | U3: 第5年Q1 | V3: 第5年Q2 | W3: 第5年Q3 | X3: 第5年Q4
B4: 1 | C4: 现金流入 | D4: =SUM(E4:X4) -> 27834.252 | E4: =SUM(E5:E7) -> 750 | F4: =SUM(F5:F7) -> 1037.1761 | G4: =SUM(G5:G7) -> 893.55265 | H4: =SUM(H5:H7) -> 8546.0554 | I4: =SUM(I5:I7) -> 3854.9128 | J4: =SUM(J5:J7) -> 3308.0285 | K4: =SUM(K5:K7) -> 357.7748 | L4: =SUM(L5:L7) -> 357.7748 | ... X4: =SUM(X5:X7) -> 6085.4285
B5: 1.1 | C5: 优先级收益 | D5: =SUM(E5:X5) -> 6240.0394 | E5: ='附表10 资金来源与运用表'!D31*'0基本假设 '!$N$15*'0基本假设 '!$L$36 -> 750 | F5: ='附表10 资金来源与运用表'!E31*'0基本假设 '!$N$15*'0基本假设 '!$L$36 -> 750 | G5: ='附表10 资金来源与运用表'!F31*'0基本假设 '!$N$15*'0基本假设 '!$L$36 -> 750 | H5: ='附表10 资金来源与运用表'!G31*'0基本假设 '!$N$15*'0基本假设 '!$L$36 -> 451.85054 | I5: ='附表10 资金来源与运用表'!H31*'0基本假设 '!$N$15*'0基本假设 '!$L$36 -> 324.85666 | J5: ='附表10 资金来源与运用表'!I31*'0基本假设 '!$N$15*'0基本假设 '!$L$36 -> 214.22215 | K5: ='附表10 资金来源与运用表'!J31*'0基本假设 '!$N$15*'0基本假设 '!$L$36 -> 214.22215 | L5: ='附表10 资金来源与运用表'!K31*'0基本假设 '!$N$15*'0基本假设 '!$L$36 -> 214.22215 | ... W5: ='附表10 资金来源与运用表'!V31*'0基本假设 '!$N$15*'0基本假设 '!$L$36 -> 214.22215 | X5: =W5 -> 214.22215
B6: 1.2 | C6: 减资退出 | D6: =SUM(E6:X6) -> 20158.616 | E6: ='附表11 财务计划现金流量表'!E29*'0基本假设 '!$N$15 -> 0 | F6: ='附表11 财务计划现金流量表'!F29*'0基本假设 '!$N$15 -> 0 | G6: ='附表11 财务计划现金流量表'!G29*'0基本假设 '!$N$15 -> 0 | H6: ='附表11 财务计划现金流量表'!H29*'0基本假设 '!$N$15 -> 7950.6522 | I6: ='附表11 财务计划现金流量表'!I29*'0基本假设 '!$N$15 -> 3386.5035 | J6: ='附表11 财务计划现金流量表'!J29*'0基本假设 '!$N$15 -> 2950.2537 | K6: ='附表11 财务计划现金流量表'!K29*'0基本假设 '!$N$15 -> 0 | L6: ='附表11 财务计划现金流量表'!L29*'0基本假设 '!$N$15 -> 0 | ... X6: ='附表11 财务计划现金流量表'!X29*'0基本假设 '!$N$15 -> 5871.2064
B7: 1.3 | C7: 总包管理费净收入（1.3.=1.3.1-1.3.2-1.3.3) | D7: =SUM(E7:X7) -> 1435.5973 | E7: =E8-E9-E10-E11 -> 0 | F7: =F8-F9-F10-F11 -> 287.17606 | G7: =G8-G9-G10-G11 -> 143.55265 | H7: =H8-H9-H10-H11 -> 143.55265 | I7: =I8-I9-I10-I11 -> 143.55265 | J7: =J8-J9-J10-J11 -> 143.55265 | K7: =K8-K9-K10-K11 -> 143.55265 | L7: =L8-L9-L10-L11 -> 143.55265 | ... N7: =N8-N9-N10-N11 -> 143.55265
B8: 1.3.1 | C8: 总包管理费毛收入 | D8: =SUM(E8:X8) -> 2029.8775 | E8: ='附表2 投资计划与资金筹措平衡表 '!D6*$D$22*'附表14 中信建设现金流量表（优先级）'!$D$21 -> 0 | F8: ='附表2 投资计划与资金筹措平衡表 '!E6*$D$22*'附表14 中信建设现金流量表（优先级）'!$D$21 -> 405.9755 | G8: ='附表2 投资计划与资金筹措平衡表 '!F6*$D$22*'附表14 中信建设现金流量表（优先级）'!$D$21 -> 202.98775 | H8: ='附表2 投资计划与资金筹措平衡表 '!G6*$D$22*'附表14 中信建设现金流量表（优先级）'!$D$21 -> 202.98775 | I8: ='附表2 投资计划与资金筹措平衡表 '!H6*$D$22*'附表14 中信建设现金流量表（优先级）'!$D$21 -> 202.98775 | J8: ='附表2 投资计划与资金筹措平衡表 '!I6*$D$22*'附表14 中信建设现金流量表（优先级）'!$D$21 -> 202.98775 | K8: ='附表2 投资计划与资金筹措平衡表 '!J6*$D$22*'附表14 中信建设现金流量表（优先级）'!$D$21 -> 202.98775 | L8: ='附表2 投资计划与资金筹措平衡表 '!K6*$D$22*'附表14 中信建设现金流量表（优先级）'!$D$21 -> 202.98775 | ... N8: ='附表2 投资计划与资金筹措平衡表 '!M6*$D$22*'附表14 中信建设现金流量表（优先级）'!$D$21 -> 202.98775
B9: 1.3.2 | C9: 总包管理成本 | D9: =SUM(E9:X9) -> 0.9 | F9: 0.1 | G9: 0.1 | H9: 0.1 | I9: 0.1 | J9: 0.1 | K9: 0.1 | L9: 0.1 | M9: 0.1 | N9: 0.1
B10: 1.3.3 | C10: 总包管理费营业税及附加 | D10: =SUM(E10:X10) -> 114.84778 | E10: =(E8-E9)*'0基本假设 '!$L$40/(1+'0基本假设 '!$L$40) -> 0 | F10: =(F8-F9)*'0基本假设 '!$L$40/(1+'0基本假设 '!$L$40) -> 22.974085 | G10: =(G8-G9)*'0基本假设 '!$L$40/(1+'0基本假设 '!$L$40) -> 11.484212 | H10: =(H8-H9)*'0基本假设 '!$L$40/(1+'0基本假设 '!$L$40) -> 11.484212 | I10: =(I8-I9)*'0基本假设 '!$L$40/(1+'0基本假设 '!$L$40) -> 11.484212 | J10: =(J8-J9)*'0基本假设 '!$L$40/(1+'0基本假设 '!$L$40) -> 11.484212 | K10: =(K8-K9)*'0基本假设 '!$L$40/(1+'0基本假设 '!$L$40) -> 11.484212 | L10: =(L8-L9)*'0基本假设 '!$L$40/(1+'0基本假设 '!$L$40) -> 11.484212 | ... N10: =(N8-N9)*'0基本假设 '!$L$40/(1+'0基本假设 '!$L$40) -> 11.484212
B11: 1.3.4 | C11: 总包所得税 | D11: =SUM(E11:X11) -> 478.53243 | E11: =(E8-E9-E10)*'0基本假设 '!$L$41 -> 0 | F11: =(F8-F9-F10)*'0基本假设 '!$L$41 -> 95.725354 | G11: =(G8-G9-G10)*'0基本假设 '!$L$41 -> 47.850884 | H11: =(H8-H9-H10)*'0基本假设 '!$L$41 -> 47.850884 | I11: =(I8-I9-I10)*'0基本假设 '!$L$41 -> 47.850884 | J11: =(J8-J9-J10)*'0基本假设 '!$L$41 -> 47.850884 | K11: =(K8-K9-K10)*'0基本假设 '!$L$41 -> 47.850884 | L11: =(L8-L9-L10)*'0基本假设 '!$L$41 -> 47.850884 | ... N11: =(N8-N9-N10)*'0基本假设 '!$L$41 -> 47.850884
B12: 2 | C12: 现金流出 | D12: =SUM(E12:X12) -> 20215.34 | E12: =SUM(E13,E15:E16) -> 18980.659 | F12: =SUM(F13,F15:F16) -> 63.879291 | G12: =SUM(G13,G15:G16) -> 73.540102 | H12: =SUM(H13,H15:H16) -> 94.342983 | I12: =SUM(I13,I15:I16) -> 115.14586 | J12: =SUM(J13,J15:J16) -> 135.94875 | K12: =SUM(K13,K15:K16) -> 156.75163 | L12: =SUM(L13,L15:L16) -> 177.55451 | ... X12: =SUM(X13,X15:X16) -> 0
B13: 2.1 | C13: 实际出资额 | D13: =SUM(E13:X13) -> 20000 | E13: =SUM(E14:E14) -> 18980.659 | F13: =SUM(F14:F14) -> 20.802881 | G13: =SUM(G14:G14) -> 52.007204 | H13: =SUM(H14:H14) -> 72.810085 | I13: =SUM(I14:I14) -> 93.612966 | J13: =SUM(J14:J14) -> 114.41585 | K13: =SUM(K14:K14) -> 135.21873 | L13: =SUM(L14:L14) -> 156.02161 | ... N13: =SUM(N14:N14) -> 197.62737
C14: 资本金 | D14: =SUM(E14:X14) -> 20000 | E14: ='附表2 投资计划与资金筹措平衡表 '!D12*'0基本假设 '!$N$15 -> 18980.659 | F14: ='附表2 投资计划与资金筹措平衡表 '!E12*'0基本假设 '!$N$15 -> 20.802881 | G14: ='附表2 投资计划与资金筹措平衡表 '!F12*'0基本假设 '!$N$15 -> 52.007204 | H14: ='附表2 投资计划与资金筹措平衡表 '!G12*'0基本假设 '!$N$15 -> 72.810085 | I14: ='附表2 投资计划与资金筹措平衡表 '!H12*'0基本假设 '!$N$15 -> 93.612966 | J14: ='附表2 投资计划与资金筹措平衡表 '!I12*'0基本假设 '!$N$15 -> 114.41585 | K14: ='附表2 投资计划与资金筹措平衡表 '!J12*'0基本假设 '!$N$15 -> 135.21873 | L14: ='附表2 投资计划与资金筹措平衡表 '!K12*'0基本假设 '!$N$15 -> 156.02161 | ... N14: ='附表2 投资计划与资金筹措平衡表 '!M12*'0基本假设 '!$N$15 -> 197.62737
B15: 2.2 | C15: 中信建设企业所得税 | D15: =SUM(E15:X15) -> 215.33959 | E15: =(E7)*15% -> 0 | F15: =(F7)*15% -> 43.076409 | G15: =(G7)*15% -> 21.532898 | H15: =(H7)*15% -> 21.532898 | I15: =(I7)*15% -> 21.532898 | J15: =(J7)*15% -> 21.532898 | K15: =(K7)*15% -> 21.532898 | L15: =(L7)*15% -> 21.532898 | ... N15: =(N7)*15% -> 21.532898
B16: 2.3 | C16: 海外投资保险费用 | E16: ='附表2 投资计划与资金筹措平衡表 '!D12*'0基本假设 '!$N$15*'0基本假设 '!$L$43 -> 0 | F16: =('附表2 投资计划与资金筹措平衡表 '!D12+'附表2 投资计划与资金筹措平衡表 '!E12)*'0基本假设 '!$N$15*'0基本假设 '!$L$43 -> 0 | G16: =('附表2 投资计划与资金筹措平衡表 '!E12+'附表2 投资计划与资金筹措平衡表 '!F12)*'0基本假设 '!$N$15*'0基本假设 '!$L$43 -> 0 | H16: =('附表2 投资计划与资金筹措平衡表 '!F12+'附表2 投资计划与资金筹措平衡表 '!G12)*'0基本假设 '!$N$15*'0基本假设 '!$L$43 -> 0 | I16: =('附表2 投资计划与资金筹措平衡表 '!G12+'附表2 投资计划与资金筹措平衡表 '!H12)*'0基本假设 '!$N$15*'0基本假设 '!$L$43 -> 0 | J16: =('附表2 投资计划与资金筹措平衡表 '!H12+'附表2 投资计划与资金筹措平衡表 '!I12)*'0基本假设 '!$N$15*'0基本假设 '!$L$43 -> 0 | K16: =('附表2 投资计划与资金筹措平衡表 '!I12+'附表2 投资计划与资金筹措平衡表 '!J12)*'0基本假设 '!$N$15*'0基本假设 '!$L$43 -> 0 | L16: =('附表2 投资计划与资金筹措平衡表 '!J12+'附表2 投资计划与资金筹措平衡表 '!K12)*'0基本假设 '!$N$15*'0基本假设 '!$L$43 -> 0 | M16: =('附表2 投资计划与资金筹措平衡表 '!K12+'附表2 投资计划与资金筹措平衡表 '!L12)*'0基本假设 '!$N$15*'0基本假设 '!$L$43 -> 0 | ... R16: =('附表2 投资计划与资金筹措平衡表 '!P12+'附表2 投资计划与资金筹措平衡表 '!Q12)*'0基本假设 '!$N$15*'0基本假设 '!$L$43 -> 0 | S16: =('附表2 投资计划与资金筹措平衡表 '!W12+'附表2 投资计划与资金筹措平衡表 '!X12)*'0基本假设 '!$N$15*'0基本假设 '!$L$43 -> 0 | T16: =('附表2 投资计划与资金筹措平衡表 '!X12+'附表2 投资计划与资金筹措平衡表 '!Y12)*'0基本假设 '!$N$15*'0基本假设 '!$L$43 -> 0 | U16: =('附表2 投资计划与资金筹措平衡表 '!Y12+'附表2 投资计划与资金筹措平衡表 '!Z12)*'0基本假设 '!$N$15*'0基本假设 '!$L$43 -> 0 | V16: =('附表2 投资计划与资金筹措平衡表 '!Z12+'附表2 投资计划与资金筹措平衡表 '!AA12)*'0基本假设 '!$N$15*'0基本假设 '!$L$43 -> 0 | W16: =('附表2 投资计划与资金筹措平衡表 '!AA12+'附表2 投资计划与资金筹措平衡表 '!AB12)*'0基本假设 '!$N$15*'0基本假设 '!$L$43 -> 0 | X16: =('附表2 投资计划与资金筹措平衡表 '!AB12+'附表2 投资计划与资金筹措平衡表 '!AC12)*'0基本假设 '!$N$15*'0基本假设 '!$L$43 -> 0
B17: 3 | C17: 净现金流量 | D17: =SUM(E17:X17) -> 7618.9129 | E17: =E4-E12 -> -18230.659 | F17: =F4-F12 -> 973.29677 | G17: =G4-G12 -> 820.01255 | H17: =H4-H12 -> 8451.7124 | I17: =I4-I12 -> 3739.767 | J17: =J4-J12 -> 3172.0798 | K17: =K4-K12 -> 201.02317 | L17: =L4-L12 -> 180.22029 | ... X17: =X4-X12 -> 6085.4285
B18: 4 | C18: 累计增量净现金流量 | E18: =E17 -> -18230.659 | F18: =E18+F17 -> -17257.362 | G18: =F18+G17 -> -16437.349 | H18: =G18+H17 -> -7985.6371 | I18: =H18+I17 -> -4245.8701 | J18: =I18+J17 -> -1073.7903 | K18: =J18+K17 -> -872.76717 | L18: =K18+L17 -> -692.54688 | M18: =L18+M17 -> -533.12947 | ... X18: =W18+X17 -> 7618.9129
C21: 总包管理费率 | D21: ='0基本假设 '!L53 -> 0.05
C22: 总包份额比例 | D22: 1
C23: FIRR | D23: =(1+IRR(E17:X17))^4-1 -> 0.22291174 | E23: =IF(D23>=13%,"可行","不可行") -> 可行
C24: 投资回收期（静态） | D24: =(COUNTIF(E18:X18,"<0")+ABS(INDEX(E18:X18,1,COUNTIF(E18:X18,"<0")))/(INDEX(E18:X18,1,COUNTIF(E18:X18,"<0")+1)+ABS(INDEX(E18:X18,1,COUNTIF(E18:X18,"<0")))))/4 -> 2.960404
C25: 净现值（基准投资折现率） | D25: =NPV(1.5%,E17:X17) -> 4764.7211 | E25: =IF(D25>0,"可行","不可行") -> 可行
C26: 工程净利润 | D26: =D7-D15 -> 1220.2577
C27: 投资收益 | D27: =D17-D26 -> 6398.6552
C28: 建设期累计净现金流 | D28: =N18 -> -394.51494 | E28: =IF(D28>=0,"建设期回正","建设期回收率"&ROUND((D13+D28)/D13,2)) -> 建设期回收率0.98
B32: 点击返回目录

Sheet 附表15中信金资现金流量表（中间级）
B2: 附表15 中信金资现金流量表(中间级）(单位：万元)
B3: 序号 | C3: 项目 | D3: 合计 | E3: 第1年Q1 | F3: 第1年Q2 | G3: 第1年Q3 | H3: 第1年Q4 | I3: 第2年Q1 | J3: 第2年Q2 | K3: 第2年Q3 | L3: 第2年Q4 | M3: 第3年Q1 | N3: 第3年Q2 | O3: 第3年Q3 | P3: 第3年Q4 | Q3: 第4年Q1 | R3: 第4年Q2 | S3: 第4年Q3 | T3: 第4年Q4 | U3: 第5年Q1 | V3: 第5年Q2 | W3: 第5年Q3 | X3: 第5年Q4
B4: 1 | C4: 现金流入 | D4: =SUM(E4:X4) -> 50618.006 | E4: =SUM(E5:E7,E10,E11) -> 0 | F4: =SUM(F5:F7,F10,F11) -> 65.576325 | G4: =SUM(G5:G7,G10,G11) -> 163.94081 | H4: =SUM(H5:H7,H10,H11) -> 229.51714 | I4: =SUM(I5:I7,I10,I11) -> 295.09346 | J4: =SUM(J5:J7,J10,J11) -> 360.66979 | K4: =SUM(K5:K7,K10,K11) -> 426.24611 | L4: =SUM(L5:L7,L10,L11) -> 491.82244 | ... X4: =SUM(X5:X7,X10,X11) -> 4740.4766
B5: 1.1 | C5: 实分利润 | D5: =SUM(E5:X5) -> 0
B6: 1.2 | C6: 减资退出 | D6: =SUM(E6:X6) -> 0
B7: 1.3 | C7: 贷款本息 | D7: =SUM(E7:X7) -> 50618.006 | E7: ='附表7 银行贷款还本付息表'!E23 -> 0 | F7: ='附表7 银行贷款还本付息表'!F23 -> 65.576325 | G7: ='附表7 银行贷款还本付息表'!G23 -> 163.94081 | H7: ='附表7 银行贷款还本付息表'!H23 -> 229.51714 | I7: ='附表7 银行贷款还本付息表'!I23 -> 295.09346 | J7: ='附表7 银行贷款还本付息表'!J23 -> 360.66979 | K7: ='附表7 银行贷款还本付息表'!K23 -> 426.24611 | L7: ='附表7 银行贷款还本付息表'!L23 -> 491.82244 | ... X7: ='附表7 银行贷款还本付息表'!X23 -> 4740.4766
B10: 1.4 | C10: 无偿接收固定资产估值 | D10: =SUM(E10:X10) -> 0
B11: 1.5 | C11: 土地增值收入
B12: 2 | C12: 现金流出 | D12: =SUM(E12:X12) -> 43717.55 | E12: =SUM(E13,E16:E19) -> 0 | F12: =SUM(F13,F16:F19) -> 8743.51 | G12: =SUM(G13,G16:G19) -> 4371.755 | H12: =SUM(H13,H16:H19) -> 4371.755 | I12: =SUM(I13,I16:I19) -> 4371.755 | J12: =SUM(J13,J16:J19) -> 4371.755 | K12: =SUM(K13,K16:K19) -> 4371.755 | L12: =SUM(L13,L16:L19) -> 4371.755 | ... X12: =SUM(X13,X16:X19) -> 0
B13: 2.1 | C13: 实际出资额 | D13: =SUM(E13:X13) -> 0 | E13: =SUM(E14:E15) -> 0 | F13: =SUM(F14:F15) -> 0 | G13: =SUM(G14:G15) -> 0 | H13: =SUM(H14:H15) -> 0 | I13: =SUM(I14:I15) -> 0 | J13: =SUM(J14:J15) -> 0 | K13: =SUM(K14:K15) -> 0 | L13: =SUM(L14:L15) -> 0 | ... N13: =SUM(N14:N15) -> 0
C14: 资本金 | D14: =SUM(E14:X14) -> 0
C15: 建设期拨款 | D15: =SUM(E15:X15) -> 0 | E15: ='附表2 投资计划与资金筹措平衡表 '!D21 -> 0 | F15: ='附表2 投资计划与资金筹措平衡表 '!E21 -> 0 | G15: ='附表2 投资计划与资金筹措平衡表 '!F21 -> 0 | H15: ='附表2 投资计划与资金筹措平衡表 '!G21 -> 0 | I15: ='附表2 投资计划与资金筹措平衡表 '!H21 -> 0 | J15: ='附表2 投资计划与资金筹措平衡表 '!I21 -> 0 | K15: ='附表2 投资计划与资金筹措平衡表 '!J21 -> 0 | L15: ='附表2 投资计划与资金筹措平衡表 '!K21 -> 0 | ... N15: ='附表2 投资计划与资金筹措平衡表 '!M21 -> 0
B16: 2.2 | C16: 补偿优先级 | D16: =SUM(E16:X16) -> 0
B17: 2.3 | C17: 补偿村集体-土地款 | D17: =SUM(E17:X17) -> 0
B18: 2.4 | C18: 补偿村集体 | D18: =SUM(E18:X18) -> 0
B19: 2.5 | C19: 贷款本金 | D19: =SUM(E19:X19) -> 43717.55 | E19: ='附表7 银行贷款还本付息表'!E7 -> 0 | F19: ='附表7 银行贷款还本付息表'!F7 -> 8743.51 | G19: ='附表7 银行贷款还本付息表'!G7 -> 4371.755 | H19: ='附表7 银行贷款还本付息表'!H7 -> 4371.755 | I19: ='附表7 银行贷款还本付息表'!I7 -> 4371.755 | J19: ='附表7 银行贷款还本付息表'!J7 -> 4371.755 | K19: ='附表7 银行贷款还本付息表'!K7 -> 4371.755 | L19: ='附表7 银行贷款还本付息表'!L7 -> 4371.755 | ... X19: ='附表7 银行贷款还本付息表'!X7 -> 0
B20: 3 | C20: 净现金流量 | D20: =SUM(E20:X20) -> 6900.4559 | E20: =E4-E12 -> 0 | F20: =F4-F12 -> -8677.9337 | G20: =G4-G12 -> -4207.8142 | H20: =H4-H12 -> -4142.2379 | I20: =I4-I12 -> -4076.6615 | J20: =J4-J12 -> -4011.0852 | K20: =K4-K12 -> -3945.5089 | L20: =L4-L12 -> -3879.9326 | ... X20: =X4-X12 -> 4740.4766
B21: 4 | C21: 累计增量净现金流量 | E21: =E20 -> 0 | F21: =E21+F20 -> -8677.9337 | G21: =F21+G20 -> -12885.748 | H21: =G21+H20 -> -17027.986 | I21: =H21+I20 -> -21104.647 | J21: =I21+J20 -> -25115.732 | K21: =J21+K20 -> -29061.241 | L21: =K21+L20 -> -32941.174 | M21: =L21+M20 -> -36755.53 | ... X21: =W21+X20 -> 6900.4559
C24: FIRR | D24: =(1+IRR(E20:X20))^4-1 -> 0.064778846 | E24: =IF(D24>=13%,"可行","不可行") -> 不可行
C25: 投资回收期（静态） | D25: =(COUNTIF(E21:X21,"<0")+ABS(INDEX(E21:X21,1,COUNTIF(E21:X21,"<0")))/(INDEX(E21:X21,1,COUNTIF(E21:X21,"<0")+1)+ABS(INDEX(E21:X21,1,COUNTIF(E21:X21,"<0")))))/4 -> 4.6360885
C26: 净现值（基准投资折现率） | D26: =NPV(1.5%,E20:X20) -> 301.90109 | E26: =IF(D26>0,"可行","不可行") -> 可行
C27: 投资收益 | D27: =D20 -> 6900.4559
B31: 点击返回目录

Sheet 附表16五江现金流量表（劣后级）
B2: 附表16 五江现金流量表(劣后级）(单位：万元)
B3: 序号 | C3: 项目 | D3: 合计 | E3: 第1年Q1 | F3: 第1年Q2 | G3: 第1年Q3 | H3: 第1年Q4 | I3: 第2年Q1 | J3: 第2年Q2 | K3: 第2年Q3 | L3: 第2年Q4 | M3: 第3年Q1 | N3: 第3年Q2 | O3: 第3年Q3 | P3: 第3年Q4 | Q3: 第4年Q1 | R3: 第4年Q2 | S3: 第4年Q3 | T3: 第4年Q4 | U3: 第5年Q1 | V3: 第5年Q2 | W3: 第5年Q3 | X3: 第5年Q4
B4: 1 | C4: 现金流入 | D4: =SUM(E4:X4) -> 16534.275 | E4: =SUM(E5:E7,E10,E11) -> 0 | F4: =SUM(F5:F7,F10,F11) -> -100 | G4: =SUM(G5:G7,G10,G11) -> -100 | H4: =SUM(H5:H7,H10,H11) -> 5348.0864 | I4: =SUM(I5:I7,I10,I11) -> 1424.075 | J4: =SUM(J5:J7,J10,J11) -> 987.82525 | K4: =SUM(K5:K7,K10,K11) -> -1857.3799 | L4: =SUM(L5:L7,L10,L11) -> -2032.4608 | ... X4: =SUM(X5:X7,X10,X11) -> 7143.6838
B5: 1.1 | C5: 实分利润 | D5: =SUM(E5:X5) -> -3624.3408 | E5: =附表9利润表!D17 -> 0 | F5: =附表9利润表!E17 -> -100 | G5: =附表9利润表!F17 -> -100 | H5: =附表9利润表!G17 -> -2602.5657 | I5: =附表9利润表!H17 -> -1962.4285 | J5: =附表9利润表!I17 -> -1962.4285 | K5: =附表9利润表!J17 -> -1857.3799 | L5: =附表9利润表!K17 -> -2032.4608 | ... X5: =附表9利润表!W17 -> 1272.4775
B6: 1.2 | C6: 减资退出 | D6: =SUM(E6:X6) -> 20158.616 | E6: ='附表11 财务计划现金流量表'!E29*'0基本假设 '!$N$14 -> 0 | F6: ='附表11 财务计划现金流量表'!F29*'0基本假设 '!$N$14 -> 0 | G6: ='附表11 财务计划现金流量表'!G29*'0基本假设 '!$N$14 -> 0 | H6: ='附表11 财务计划现金流量表'!H29*'0基本假设 '!$N$14 -> 7950.6522 | I6: ='附表11 财务计划现金流量表'!I29*'0基本假设 '!$N$14 -> 3386.5035 | J6: ='附表11 财务计划现金流量表'!J29*'0基本假设 '!$N$14 -> 2950.2537 | K6: ='附表11 财务计划现金流量表'!K29*'0基本假设 '!$N$14 -> 0 | L6: ='附表11 财务计划现金流量表'!L29*'0基本假设 '!$N$14 -> 0 | ... X6: ='附表11 财务计划现金流量表'!X29*'0基本假设 '!$N$14 -> 5871.2064
B7: 1.3 | C7: 贷款本息 | D7: =SUM(E7:X7) -> 0
B10: 1.4 | C10: 无偿接收固定资产估值 | D10: =SUM(E10:X10) -> 0
B11: 1.5 | C11: 土地增值收入
B12: 2 | C12: 现金流出 | D12: =SUM(E12:X12) -> 26240.039 | E12: =SUM(E13,E16:E19) -> 19730.659 | F12: =SUM(F13,F16:F19) -> 770.80288 | G12: =SUM(G13,G16:G19) -> 802.0072 | H12: =SUM(H13,H16:H19) -> 524.66063 | I12: =SUM(I13,I16:I19) -> 418.46963 | J12: =SUM(J13,J16:J19) -> 328.63799 | K12: =SUM(K13,K16:K19) -> 349.44088 | L12: =SUM(L13,L16:L19) -> 370.24376 | ... X12: =SUM(X13,X16:X19) -> 214.22215
B13: 2.1 | C13: 实际出资额 | D13: =SUM(E13:X13) -> 20000 | E13: =SUM(E14:E15) -> 18980.659 | F13: =SUM(F14:F15) -> 20.802881 | G13: =SUM(G14:G15) -> 52.007204 | H13: =SUM(H14:H15) -> 72.810085 | I13: =SUM(I14:I15) -> 93.612966 | J13: =SUM(J14:J15) -> 114.41585 | K13: =SUM(K14:K15) -> 135.21873 | L13: =SUM(L14:L15) -> 156.02161 | ... N13: =SUM(N14:N15) -> 197.62737
C14: 资本金 | D14: =SUM(E14:X14) -> 20000 | E14: ='附表2 投资计划与资金筹措平衡表 '!D12*'0基本假设 '!$N$14 -> 18980.659 | F14: ='附表2 投资计划与资金筹措平衡表 '!E12*'0基本假设 '!$N$14 -> 20.802881 | G14: ='附表2 投资计划与资金筹措平衡表 '!F12*'0基本假设 '!$N$14 -> 52.007204 | H14: ='附表2 投资计划与资金筹措平衡表 '!G12*'0基本假设 '!$N$14 -> 72.810085 | I14: ='附表2 投资计划与资金筹措平衡表 '!H12*'0基本假设 '!$N$14 -> 93.612966 | J14: ='附表2 投资计划与资金筹措平衡表 '!I12*'0基本假设 '!$N$14 -> 114.41585 | K14: ='附表2 投资计划与资金筹措平衡表 '!J12*'0基本假设 '!$N$14 -> 135.21873 | L14: ='附表2 投资计划与资金筹措平衡表 '!K12*'0基本假设 '!$N$14 -> 156.02161 | ... N14: ='附表2 投资计划与资金筹措平衡表 '!M12*'0基本假设 '!$N$14 -> 197.62737
C15: 建设期拨款 | D15: =SUM(E15:X15) -> 0 | E15: ='附表2 投资计划与资金筹措平衡表 '!D21 -> 0 | F15: ='附表2 投资计划与资金筹措平衡表 '!E21 -> 0 | G15: ='附表2 投资计划与资金筹措平衡表 '!F21 -> 0 | H15: ='附表2 投资计划与资金筹措平衡表 '!G21 -> 0 | I15: ='附表2 投资计划与资金筹措平衡表 '!H21 -> 0 | J15: ='附表2 投资计划与资金筹措平衡表 '!I21 -> 0 | K15: ='附表2 投资计划与资金筹措平衡表 '!J21 -> 0 | L15: ='附表2 投资计划与资金筹措平衡表 '!K21 -> 0 | ... N15: ='附表2 投资计划与资金筹措平衡表 '!M21 -> 0
B16: 2.2 | C16: 补偿优先级 | D16: =SUM(E16:X16) -> 6240.0394 | E16: ='附表10 资金来源与运用表'!D31*'0基本假设 '!$L$36*'0基本假设 '!$N$15 -> 750 | F16: ='附表10 资金来源与运用表'!E31*'0基本假设 '!$L$36*'0基本假设 '!$N$15 -> 750 | G16: ='附表10 资金来源与运用表'!F31*'0基本假设 '!$L$36*'0基本假设 '!$N$15 -> 750 | H16: ='附表10 资金来源与运用表'!G31*'0基本假设 '!$L$36*'0基本假设 '!$N$15 -> 451.85054 | I16: ='附表10 资金来源与运用表'!H31*'0基本假设 '!$L$36*'0基本假设 '!$N$15 -> 324.85666 | J16: ='附表10 资金来源与运用表'!I31*'0基本假设 '!$L$36*'0基本假设 '!$N$15 -> 214.22215 | K16: ='附表10 资金来源与运用表'!J31*'0基本假设 '!$L$36*'0基本假设 '!$N$15 -> 214.22215 | L16: ='附表10 资金来源与运用表'!K31*'0基本假设 '!$L$36*'0基本假设 '!$N$15 -> 214.22215 | ... W16: ='附表10 资金来源与运用表'!V31*'0基本假设 '!$L$36*'0基本假设 '!$N$15 -> 214.22215 | X16: =W16 -> 214.22215
B17: 2.3 | C17: 补偿村集体-土地款 | D17: =SUM(E17:X17) -> 0
B18: 2.4 | C18: 补偿村集体 | D18: =SUM(E18:X18) -> 0
B19: 2.5 | C19: 贷款本金 | D19: =SUM(E19:X19) -> 0
B20: 3 | C20: 净现金流量 | D20: =SUM(E20:X20) -> -9705.7644 | E20: =E4-E12 -> -19730.659 | F20: =F4-F12 -> -870.80288 | G20: =G4-G12 -> -902.0072 | H20: =H4-H12 -> 4823.4258 | I20: =I4-I12 -> 1005.6054 | J20: =J4-J12 -> 659.18726 | K20: =K4-K12 -> -2206.8208 | L20: =L4-L12 -> -2402.7046 | ... X20: =X4-X12 -> 6929.4617
B21: 4 | C21: 累计增量净现金流量 | E21: =E20 -> -19730.659 | F21: =E21+F20 -> -20601.462 | G21: =F21+G20 -> -21503.469 | H21: =G21+H20 -> -16680.043 | I21: =H21+I20 -> -15674.438 | J21: =I21+J20 -> -15015.25 | K21: =J21+K20 -> -17222.071 | L21: =K21+L20 -> -19624.776 | M21: =L21+M20 -> -22118.316 | ... X21: =W21+X20 -> -9705.7644
C24: FIRR | D24: =(1+IRR(E20:X20))^4-1 -> -0.1303485 | E24: =IF(D24>=13%,"可行","不可行") -> 不可行
C25: 投资回收期（静态） | D25: =(COUNTIF(E21:X21,"<0")+ABS(INDEX(E21:X21,1,COUNTIF(E21:X21,"<0")))/(INDEX(E21:X21,1,COUNTIF(E21:X21,"<0")+1)+ABS(INDEX(E21:X21,1,COUNTIF(E21:X21,"<0")))))/4 -> #REF!
C26: 净现值（基准投资折现率） | D26: =NPV(1.5%,E20:X20) -> -12048.128 | E26: =IF(D26>0,"可行","不可行") -> 不可行
C27: 投资收益 | D27: =D20 -> -9705.7644
B31: 点击返回目录
B32: 附表16.1 亏掉劣后级项目最长去化周期计算（返还4.2亿，劣后级实收3.2亿）
B33: 序号 | C33: 项目 | D33: 合计 | E33: 单位
B34: 1 | C34: 项目每年固定资金支出 | D34: =SUM(D35:D37) -> 3122.8943 | E34: 万元
B35: 1.1 | C35: 每年贷款资金成本 | D35: =AVERAGE('附表7 银行贷款还本付息表'!$O$26:$X$26)*4 -> 1474.8864 | E35: 万元
B36: 1.2 | C36: 每年优先级资金成本 | D36: =AVERAGE('附表16五江现金流量表（劣后级）'!$E$16:$X$16)*4 -> 1248.0079 | E36: 万元
B37: 1.3 | C37: 每年运营成本 | D37: =AVERAGE('5.1运营成本明细表'!$H$9:$Z$9)*4 -> 400 | E37: 万元
B38: 2 | C38: 5年内劣后级全亏空可供亏空的金额 | D38: =D39-D40 -> 42294.236 | E38: 万元
B39: 2.1 | C39: 亏劣后可供亏空的金额 | D39: =D14+32000 -> 52000 | E39: 万元
B40: 2.2 | C40: 五年末劣后级亏空的金额 | D40: =-X21 -> 9705.7644 | E40: 万元
B41: 3 | C41: 剩余可亏空的金额的年数 | D41: =D38/D34 -> 13.543281 | E41: 年
B42: 4 | C42: 项目自平衡年数 | D42: =5+D41 -> 18.543281 | E42: 年
B44: 附表16.2 不亏劣后级项目最长去化周期计算（返还4.2亿，劣后级实收3.2亿）
B45: 序号 | C45: 项目 | D45: 合计 | E45: 单位
B46: 1 | C46: 项目每年固定资金支出 | D46: =D34 -> 3122.8943 | E46: 万元
B47: 1.1 | C47: 每年贷款资金成本 | D47: =D35 -> 1474.8864 | E47: 万元
B48: 1.2 | C48: 每年优先级资金成本 | D48: =D36 -> 1248.0079 | E48: 万元
B49: 1.3 | C49: 每年运营成本 | D49: =D37 -> 400 | E49: 万元
B50: 2 | C50: 5年内劣后级全亏空可供亏空的金额 | D50: =D51-D52 -> 22294.236 | E50: 万元
B51: 2.1 | C51: 亏劣后可供亏空的金额 | D51: =32000 -> 32000 | E51: 万元
B52: 2.2 | C52: 五年末劣后级亏空的金额 | D52: =-X21 -> 9705.7644 | E52: 万元
B53: 3 | C53: 剩余可亏空的金额的年数 | D53: =D50/D46 -> 7.1389659 | E53: 年
B54: 4 | C54: 项目自平衡年数 | D54: =5+D53 -> 12.138966 | E54: 年
B57: 附表16.3 亏掉劣后级项目最长去化周期计算（返还2.1亿，劣后级实收1.1亿）
B58: 序号 | C58: 项目 | D58: 合计 | E58: 单位
B59: 1 | C59: 项目每年固定资金支出 | D59: =SUM(D60:D62) -> 3122.8943 | E59: 万元
B60: 1.1 | C60: 每年贷款资金成本 | D60: =AVERAGE('附表7 银行贷款还本付息表'!$O$26:$X$26)*4 -> 1474.8864 | E60: 万元
B61: 1.2 | C61: 每年优先级资金成本 | D61: =AVERAGE('附表16五江现金流量表（劣后级）'!$E$16:$X$16)*4 -> 1248.0079 | E61: 万元
B62: 1.3 | C62: 每年运营成本 | D62: =AVERAGE('5.1运营成本明细表'!$H$9:$Z$9)*4 -> 400 | E62: 万元
B63: 2 | C63: 5年内劣后级全亏空可供亏空的金额 | D63: =D64-D65 -> 21294.236 | E63: 万元
B64: 2.1 | C64: 亏劣后可供亏空的金额 | D64: =D14+11000 -> 31000 | E64: 万元
B65: 2.2 | C65: 五年末劣后级亏空的金额 | D65: =-X21 -> 9705.7644 | E65: 万元
B66: 3 | C66: 剩余可亏空的金额的年数 | D66: =D63/D59 -> 6.8187501 | E66: 年
B67: 4 | C67: 项目自平衡年数 | D67: =5+D66 -> 11.81875 | E67: 年
B69: 附表16.4 不亏劣后级项目最长去化周期计算（返还2.1亿，劣后级实收1.1亿）
B70: 序号 | C70: 项目 | D70: 合计 | E70: 单位
B71: 1 | C71: 项目每年固定资金支出 | D71: =D59 -> 3122.8943 | E71: 万元
B72: 1.1 | C72: 每年贷款资金成本 | D72: =D60 -> 1474.8864 | E72: 万元
B73: 1.2 | C73: 每年优先级资金成本 | D73: =D61 -> 1248.0079 | E73: 万元
B74: 1.3 | C74: 每年运营成本 | D74: =D62 -> 400 | E74: 万元
B75: 2 | C75: 5年内劣后级全亏空可供亏空的金额 | D75: =D76-D77 -> 1294.2356 | E75: 万元
B76: 2.1 | C76: 亏劣后可供亏空的金额 | D76: =11000 -> 11000 | E76: 万元
B77: 2.2 | C77: 五年末劣后级亏空的金额 | D77: =-X21 -> 9705.7644 | E77: 万元
B78: 3 | C78: 剩余可亏空的金额的年数 | D78: =D75/D71 -> 0.41443466 | E78: 年
B79: 4 | C79: 项目自平衡年数 | D79: =5+D78 -> 5.4144347 | E79: 年
